Workbook

Sheet BD LP
B1: 1 | C1: 2 | D1: 3 | E1: 4 | F1: 5 | G1: 6 | H1: 7 | I1: 8 | J1: 9 | K1: 10 | M1: 11 | N1: 12 | O1: 13 | P1: 14 | Q1: 15 | R1: 16 | S1: 17 | T1: 18 | U1: 19 | V1: 20 | W1: 21 | X1: 22 | Y1: 23 | Z1: 24 | AA1: 25 | AB1: 26 | AC1: 27 | AD1: 28 | AE1: 29 | AF1: 30 | AH1: 32 | AI1: 33 | AJ1: 34
A2: BASE | B2: CÓDIGO | C2: - | D2: FS00 | E2: CATEGORY | F2: JEFE CATEGORÍA | G2: CATEGORÍA | H2: FAMILIA | I2: DESCRIPCIÓN | J2: UMV | K2: UMB | L2: UM Tipo Comercio | M2: DESCRIPCION UMV | N2: T° | O2: ORIGEN | P2: COSTO OCT | Q2: ESTADO OCT | R2: PRECIO OCT | S2: Dif. COSTOS MESES | T2: CAT. MANUAL al 27-10 | U2: S. PROPUESTO LP NOV | V2: COSTO OCT AL 27-10 | W2: COSTO | X2: DIF EN COSTOS MES | Y2: ESTADO | Z2: PRECIO | AA2: DIFERENCIAS | AB2: %MG UMV | AC2: MARGEN UNITARIO | AD2: Peso Neto UMV (KG) | AE2: Contribución x KG | AF2: VENTA X UNIDAD | AG2: VENTA X COMERCIO | AH2: D. AUTÓNOMO | AI2: DA MEDIOCAMPO | AJ2: PRODUCTO FOCO | AK2: LP PERSONAL
A3: EXCLUSIVOS | B3: 101600020 | C3: =+MaestraLP3[[#This Row],[CÓDIGO]]&MaestraLP3[[#Headers],[-]]&MaestraLP3[[#This Row],[UMV]] -> 101600020-C12 | D3: =+MaestraLP3[[#This Row],[CÓDIGO]]&MaestraLP3[[#Headers],[FS00]] -> 101600020FS00 | E3: BELTRÁN FRANZANI | F3: CAMILA UGARTE | G3: CAFE Y DERIVADOS | H3: CAFES DE GRANO MOLIDO | I3: CAFE CREMA E GUSTO TARRO LAVAZZA 250 g | J3: C12 | K3: UN | M3: =VLOOKUP(MaestraLP3[[#This Row],[UMV]],VALIDACIONES!J:L,3,0) -> Caja 12 Unidades | N3: SECO | O3: NFS | P3: 31946 | Q3: MANTIENE | R3: 117000 | S3: =IFERROR((MaestraLP3[[#This Row],[COSTO ]]/MaestraLP3[[#This Row],[COSTO OCT]]-1),0) -> 0 | T3: ACTIVO | V3: =+VLOOKUP(MaestraLP3[[#This Row],[-]],'[1]BD MES'!$A:$N,14,0) -> 31947 | W3: 31946 | X3: =+(MaestraLP3[[#This Row],[COSTO ]]-MaestraLP3[[#This Row],[COSTO OCT AL 27-10]])/MaestraLP3[[#This Row],[COSTO OCT AL 27-10]] -> -3.1301844e-05 | Y3: =++IF(Q3="HASTA AGOTAR STOCK","HASTA AGOTAR STOCK",IF(MaestraLP3[[#This Row],[PRECIO OCT]]=0,"NO PARA LP",IF(MaestraLP3[[#This Row],[PRECIO OCT]]=0,"INCORPORACIÓN",IF(AA3=0,"MANTIENE",IF(AA3<0,"BAJA",IF(AA3>0,"ALZA","")))))) -> MANTIENE | Z3: 117000 | AA3: =IF(Z3=0,"INDICAR PRECIO VTA",Z3-MaestraLP3[[#This Row],[PRECIO OCT]]) -> 0 | AB3: =+IFERROR((Z3-W3)/Z3,"-") -> 0.72695726 | AC3: =IFERROR(MaestraLP3[[#This Row],[PRECIO]]*MaestraLP3[[#This Row],[%MG UMV]],0) -> 85054 | AD3: 3 | AE3: =IFERROR(MaestraLP3[[#This Row],[MARGEN UNITARIO]]/MaestraLP3[[#This Row],[Peso Neto UMV (KG)]],0) -> 28351.333 | AF3: NO | AG3: 1 | AH3: 0.1 | AI3: 0 | AJ3: SI | AK3: NO
A4: EXCLUSIVOS | B4: 101600051 | C4: =+MaestraLP3[[#This Row],[CÓDIGO]]&MaestraLP3[[#Headers],[-]]&MaestraLP3[[#This Row],[UMV]] -> 101600051-C12 | D4: =+MaestraLP3[[#This Row],[CÓDIGO]]&MaestraLP3[[#Headers],[FS00]] -> 101600051FS00 | E4: BELTRÁN FRANZANI | F4: CAMILA UGARTE | G4: CAFE Y DERIVADOS | H4: CAFES DE GRANO MOLIDO | I4: CAFÉ DESCAFEINADO LAVAZZA 250 g | J4: C12 | K4: UN | M4: =VLOOKUP(MaestraLP3[[#This Row],[UMV]],VALIDACIONES!J:L,3,0) -> Caja 12 Unidades | N4: SECO | O4: NFS | P4: 57642.25 | Q4: MANTIENE | R4: 121500 | S4: =IFERROR((MaestraLP3[[#This Row],[COSTO ]]/MaestraLP3[[#This Row],[COSTO OCT]]-1),0) -> -0.065644211 | T4: ACTIVO | V4: =+VLOOKUP(MaestraLP3[[#This Row],[-]],'[1]BD MES'!$A:$N,14,0) -> 52836.93 | W4: 53858.37 | X4: =+(MaestraLP3[[#This Row],[COSTO ]]-MaestraLP3[[#This Row],[COSTO OCT AL 27-10]])/MaestraLP3[[#This Row],[COSTO OCT AL 27-10]] -> 0.019331933 | Y4: =++IF(Q4="HASTA AGOTAR STOCK","HASTA AGOTAR STOCK",IF(MaestraLP3[[#This Row],[PRECIO OCT]]=0,"NO PARA LP",IF(MaestraLP3[[#This Row],[PRECIO OCT]]=0,"INCORPORACIÓN",IF(AA4=0,"MANTIENE",IF(AA4<0,"BAJA",IF(AA4>0,"ALZA","")))))) -> MANTIENE | Z4: 121500 | AA4: =IF(Z4=0,"INDICAR PRECIO VTA",Z4-MaestraLP3[[#This Row],[PRECIO OCT]]) -> 0 | AB4: =+IFERROR((Z4-W4)/Z4,"-") -> 0.55672123 | AC4: =IFERROR(MaestraLP3[[#This Row],[PRECIO]]*MaestraLP3[[#This Row],[%MG UMV]],0) -> 67641.63 | AD4: 3 | AE4: =IFERROR(MaestraLP3[[#This Row],[MARGEN UNITARIO]]/MaestraLP3[[#This Row],[Peso Neto UMV (KG)]],0) -> 22547.21 | AF4: SI | AG4: 1 | AH4: 0.1 | AI4: 0 | AJ4: SI | AK4: NO
A5: EXCLUSIVOS | B5: 101600036 | C5: =+MaestraLP3[[#This Row],[CÓDIGO]]&MaestraLP3[[#Headers],[-]]&MaestraLP3[[#This Row],[UMV]] -> 101600036-C06 | D5: =+MaestraLP3[[#This Row],[CÓDIGO]]&MaestraLP3[[#Headers],[FS00]] -> 101600036FS00 | E5: BELTRÁN FRANZANI | F5: CAMILA UGARTE | G5: CAFE Y DERIVADOS | H5: CAFES DE GRANO MOLIDO | I5: CAFÉ MOLIDO TIERRA BIO 180 g | J5: C06 | K5: UN | M5: =VLOOKUP(MaestraLP3[[#This Row],[UMV]],VALIDACIONES!J:L,3,0) -> Caja 6 Unidades | N5: SECO | O5: NFS | P5: 24001 | Q5: MANTIENE | R5: 61998 | S5: =IFERROR((MaestraLP3[[#This Row],[COSTO ]]/MaestraLP3[[#This Row],[COSTO OCT]]-1),0) -> -0.05728428 | T5: ACTIVO | V5: =+VLOOKUP(MaestraLP3[[#This Row],[-]],'[1]BD MES'!$A:$N,14,0) -> 22626.5 | W5: 22626.12 | X5: =+(MaestraLP3[[#This Row],[COSTO ]]-MaestraLP3[[#This Row],[COSTO OCT AL 27-10]])/MaestraLP3[[#This Row],[COSTO OCT AL 27-10]] -> -1.6794467e-05 | Y5: =++IF(Q5="HASTA AGOTAR STOCK","HASTA AGOTAR STOCK",IF(MaestraLP3[[#This Row],[PRECIO OCT]]=0,"NO PARA LP",IF(MaestraLP3[[#This Row],[PRECIO OCT]]=0,"INCORPORACIÓN",IF(AA5=0,"MANTIENE",IF(AA5<0,"BAJA",IF(AA5>0,"ALZA","")))))) -> MANTIENE | Z5: 61998 | AA5: =IF(Z5=0,"INDICAR PRECIO VTA",Z5-MaestraLP3[[#This Row],[PRECIO OCT]]) -> 0 | AB5: =+IFERROR((Z5-W5)/Z5,"-") -> 0.63505081 | AC5: =IFERROR(MaestraLP3[[#This Row],[PRECIO]]*MaestraLP3[[#This Row],[%MG UMV]],0) -> 39371.88 | AD5: 1.08 | AE5: =IFERROR(MaestraLP3[[#This Row],[MARGEN UNITARIO]]/MaestraLP3[[#This Row],[Peso Neto UMV (KG)]],0) -> 36455.444 | AF5: SI | AG5: 1 | AH5: 0.1 | AI5: 0 | AK5: NO
A6: EXCLUSIVOS | B6: 101600038 | C6: =+MaestraLP3[[#This Row],[CÓDIGO]]&MaestraLP3[[#Headers],[-]]&MaestraLP3[[#This Row],[UMV]] -> 101600038-C06 | D6: =+MaestraLP3[[#This Row],[CÓDIGO]]&MaestraLP3[[#Headers],[FS00]] -> 101600038FS00 | E6: BELTRÁN FRANZANI | F6: CAMILA UGARTE | G6: CAFE Y DERIVADOS | H6: CAFES DE GRANO MOLIDO | I6: CAFÉ MOLIDO TIERRA FOR AFRICA 180g | J6: C06 | K6: UN | M6: =VLOOKUP(MaestraLP3[[#This Row],[UMV]],VALIDACIONES!J:L,3,0) -> Caja 6 Unidades | N6: SECO | O6: NFS | P6: 21646.39 | Q6: MANTIENE | R6: 61998 | S6: =IFERROR((MaestraLP3[[#This Row],[COSTO ]]/MaestraLP3[[#This Row],[COSTO OCT]]-1),0) -> -0.055910939 | T6: ACTIVO | V6: =+VLOOKUP(MaestraLP3[[#This Row],[-]],'[1]BD MES'!$A:$N,14,0) -> 20436.12 | W6: 20436.12 | X6: =+(MaestraLP3[[#This Row],[COSTO ]]-MaestraLP3[[#This Row],[COSTO OCT AL 27-10]])/MaestraLP3[[#This Row],[COSTO OCT AL 27-10]] -> 0 | Y6: =++IF(Q6="HASTA AGOTAR STOCK","HASTA AGOTAR STOCK",IF(MaestraLP3[[#This Row],[PRECIO OCT]]=0,"NO PARA LP",IF(MaestraLP3[[#This Row],[PRECIO OCT]]=0,"INCORPORACIÓN",IF(AA6=0,"MANTIENE",IF(AA6<0,"BAJA",IF(AA6>0,"ALZA","")))))) -> MANTIENE | Z6: 61998 | AA6: =IF(Z6=0,"INDICAR PRECIO VTA",Z6-MaestraLP3[[#This Row],[PRECIO OCT]]) -> 0 | AB6: =+IFERROR((Z6-W6)/Z6,"-") -> 0.67037453 | AC6: =IFERROR(MaestraLP3[[#This Row],[PRECIO]]*MaestraLP3[[#This Row],[%MG UMV]],0) -> 41561.88 | AD6: 1.08 | AE6: =IFERROR(MaestraLP3[[#This Row],[MARGEN UNITARIO]]/MaestraLP3[[#This Row],[Peso Neto UMV (KG)]],0) -> 38483.222 | AF6: SI | AG6: 1 | AH6: 0.1 | AI6: 0 | AK6: NO
A7: EXCLUSIVOS | B7: 101600062 | C7: =+MaestraLP3[[#This Row],[CÓDIGO]]&MaestraLP3[[#Headers],[-]]&MaestraLP3[[#This Row],[UMV]] -> 101600062-C06 | D7: =+MaestraLP3[[#This Row],[CÓDIGO]]&MaestraLP3[[#Headers],[FS00]] -> 101600062FS00 | E7: BELTRÁN FRANZANI | F7: CAMILA UGARTE | G7: CAFE Y DERIVADOS | H7: CAFES DE GRANO MOLIDO | I7: CAFÉ MOLIDO TIERRA FOR CUBA 180g | J7: C06 | K7: UN | M7: =VLOOKUP(MaestraLP3[[#This Row],[UMV]],VALIDACIONES!J:L,3,0) -> Caja 6 Unidades | N7: SECO | O7: NFS | P7: 15990.86 | Q7: MANTIENE | R7: 61998 | S7: =IFERROR((MaestraLP3[[#This Row],[COSTO ]]/MaestraLP3[[#This Row],[COSTO OCT]]-1),0) -> 8.7550013e-06 | T7: ACTIVO | V7: =+VLOOKUP(MaestraLP3[[#This Row],[-]],'[1]BD MES'!$A:$N,14,0) -> 15991 | W7: 15991 | X7: =+(MaestraLP3[[#This Row],[COSTO ]]-MaestraLP3[[#This Row],[COSTO OCT AL 27-10]])/MaestraLP3[[#This Row],[COSTO OCT AL 27-10]] -> 0 | Y7: =++IF(Q7="HASTA AGOTAR STOCK","HASTA AGOTAR STOCK",IF(MaestraLP3[[#This Row],[PRECIO OCT]]=0,"NO PARA LP",IF(MaestraLP3[[#This Row],[PRECIO OCT]]=0,"INCORPORACIÓN",IF(AA7=0,"MANTIENE",IF(AA7<0,"BAJA",IF(AA7>0,"ALZA","")))))) -> MANTIENE | Z7: 61998 | AA7: =IF(Z7=0,"INDICAR PRECIO VTA",Z7-MaestraLP3[[#This Row],[PRECIO OCT]]) -> 0 | AB7: =+IFERROR((Z7-W7)/Z7,"-") -> 0.74207232 | AC7: =IFERROR(MaestraLP3[[#This Row],[PRECIO]]*MaestraLP3[[#This Row],[%MG UMV]],0) -> 46007 | AD7: 1.08 | AE7: =IFERROR(MaestraLP3[[#This Row],[MARGEN UNITARIO]]/MaestraLP3[[#This Row],[Peso Neto UMV (KG)]],0) -> 42599.074 | AF7: SI | AG7: 1 | AH7: 0.1 | AI7: 0 | AK7: NO
A8: EXCLUSIVOS | B8: 101600070 | C8: =+MaestraLP3[[#This Row],[CÓDIGO]]&MaestraLP3[[#Headers],[-]]&MaestraLP3[[#This Row],[UMV]] -> 101600070-C06 | D8: =+MaestraLP3[[#This Row],[CÓDIGO]]&MaestraLP3[[#Headers],[FS00]] -> 101600070FS00 | E8: BELTRÁN FRANZANI | F8: CAMILA UGARTE | G8: CAFE Y DERIVADOS | H8: CAFES SOLUBLES | I8: CAFE PRONTISSIMO CLASI LATA LAVAZZA 95 g | J8: C06 | K8: UN | M8: =VLOOKUP(MaestraLP3[[#This Row],[UMV]],VALIDACIONES!J:L,3,0) -> Caja 6 Unidades | N8: SECO | O8: NFS | P8: 18598 | Q8: ALZA | R8: 39990 | S8: =IFERROR((MaestraLP3[[#This Row],[COSTO ]]/MaestraLP3[[#This Row],[COSTO OCT]]-1),0) -> 0.021077535 | T8: ACTIVO | V8: =+VLOOKUP(MaestraLP3[[#This Row],[-]],'[1]BD MES'!$A:$N,14,0) -> 18990 | W8: 18990 | X8: =+(MaestraLP3[[#This Row],[COSTO ]]-MaestraLP3[[#This Row],[COSTO OCT AL 27-10]])/MaestraLP3[[#This Row],[COSTO OCT AL 27-10]] -> 0 | Y8: =++IF(Q8="HASTA AGOTAR STOCK","HASTA AGOTAR STOCK",IF(MaestraLP3[[#This Row],[PRECIO OCT]]=0,"NO PARA LP",IF(MaestraLP3[[#This Row],[PRECIO OCT]]=0,"INCORPORACIÓN",IF(AA8=0,"MANTIENE",IF(AA8<0,"BAJA",IF(AA8>0,"ALZA","")))))) -> MANTIENE | Z8: 39990 | AA8: =IF(Z8=0,"INDICAR PRECIO VTA",Z8-MaestraLP3[[#This Row],[PRECIO OCT]]) -> 0 | AB8: =+IFERROR((Z8-W8)/Z8,"-") -> 0.52513128 | AC8: =IFERROR(MaestraLP3[[#This Row],[PRECIO]]*MaestraLP3[[#This Row],[%MG UMV]],0) -> 21000 | AD8: 0.57 | AE8: =IFERROR(MaestraLP3[[#This Row],[MARGEN UNITARIO]]/MaestraLP3[[#This Row],[Peso Neto UMV (KG)]],0) -> 36842.105 | AF8: NO | AG8: 1 | AH8: 0.1 | AI8: 0 | AJ8: SI | AK8: NO
A9: EXCLUSIVOS | B9: 101600041 | C9: =+MaestraLP3[[#This Row],[CÓDIGO]]&MaestraLP3[[#Headers],[-]]&MaestraLP3[[#This Row],[UMV]] -> 101600041-C10 | D9: =+MaestraLP3[[#This Row],[CÓDIGO]]&MaestraLP3[[#Headers],[FS00]] -> 101600041FS00 | E9: BELTRÁN FRANZANI | F9: CAMILA UGARTE | G9: CAFE Y DERIVADOS | H9: CAPSULAS Y PODS | I9: CAPSULA ESPRESSO CLASSICO LAVAZZA 57 g | J9: C10 | K9: UN | L9: UN | M9: =VLOOKUP(MaestraLP3[[#This Row],[UMV]],VALIDACIONES!J:L,3,0) -> Caja 10 Unidades | N9: SECO | O9: NFS | P9: 26822.2 | Q9: BAJA | R9: 41930 | S9: =IFERROR((MaestraLP3[[#This Row],[COSTO ]]/MaestraLP3[[#This Row],[COSTO OCT]]-1),0) -> 0.020664226 | T9: ACTIVO | V9: =+VLOOKUP(MaestraLP3[[#This Row],[-]],'[1]BD MES'!$A:$N,14,0) -> 27372.58 | W9: 27376.46 | X9: =+(MaestraLP3[[#This Row],[COSTO ]]-MaestraLP3[[#This Row],[COSTO OCT AL 27-10]])/MaestraLP3[[#This Row],[COSTO OCT AL 27-10]] -> 0.00014174769 | Y9: =++IF(Q9="HASTA AGOTAR STOCK","HASTA AGOTAR STOCK",IF(MaestraLP3[[#This Row],[PRECIO OCT]]=0,"NO PARA LP",IF(MaestraLP3[[#This Row],[PRECIO OCT]]=0,"INCORPORACIÓN",IF(AA9=0,"MANTIENE",IF(AA9<0,"BAJA",IF(AA9>0,"ALZA","")))))) -> MANTIENE | Z9: 41930 | AA9: =IF(Z9=0,"INDICAR PRECIO VTA",Z9-MaestraLP3[[#This Row],[PRECIO OCT]]) -> 0 | AB9: =+IFERROR((Z9-W9)/Z9,"-") -> 0.34709134 | AC9: =IFERROR(MaestraLP3[[#This Row],[PRECIO]]*MaestraLP3[[#This Row],[%MG UMV]],0) -> 14553.54 | AD9: 0.57 | AE9: =IFERROR(MaestraLP3[[#This Row],[MARGEN UNITARIO]]/MaestraLP3[[#This Row],[Peso Neto UMV (KG)]],0) -> 25532.526 | AF9: NO | AG9: 2 y 3 | AH9: 0.1 | AI9: 0 | AJ9: SI | AK9: NO
A10: EXCLUSIVOS | B10: 101600042 | C10: =+MaestraLP3[[#This Row],[CÓDIGO]]&MaestraLP3[[#Headers],[-]]&MaestraLP3[[#This Row],[UMV]] -> 101600042-C10 | D10: =+MaestraLP3[[#This Row],[CÓDIGO]]&MaestraLP3[[#Headers],[FS00]] -> 101600042FS00 | E10: BELTRÁN FRANZANI | F10: CAMILA UGARTE | G10: CAFE Y DERIVADOS | H10: CAPSULAS Y PODS | I10: CAPSULA ESPRESSO INTENSO LAVAZZA 57 g | J10: C10 | K10: UN | L10: UN | M10: =VLOOKUP(MaestraLP3[[#This Row],[UMV]],VALIDACIONES!J:L,3,0) -> Caja 10 Unidades | N10: SECO | O10: NFS | P10: 22229 | Q10: BAJA | R10: 41930 | S10: =IFERROR((MaestraLP3[[#This Row],[COSTO ]]/MaestraLP3[[#This Row],[COSTO OCT]]-1),0) -> 0.25466733 | T10: ACTIVO | V10: =+VLOOKUP(MaestraLP3[[#This Row],[-]],'[1]BD MES'!$A:$N,14,0) -> 27713.98 | W10: 27890 | X10: =+(MaestraLP3[[#This Row],[COSTO ]]-MaestraLP3[[#This Row],[COSTO OCT AL 27-10]])/MaestraLP3[[#This Row],[COSTO OCT AL 27-10]] -> 0.0063513072 | Y10: =++IF(Q10="HASTA AGOTAR STOCK","HASTA AGOTAR STOCK",IF(MaestraLP3[[#This Row],[PRECIO OCT]]=0,"NO PARA LP",IF(MaestraLP3[[#This Row],[PRECIO OCT]]=0,"INCORPORACIÓN",IF(AA10=0,"MANTIENE",IF(AA10<0,"BAJA",IF(AA10>0,"ALZA","")))))) -> MANTIENE | Z10: 41930 | AA10: =IF(Z10=0,"INDICAR PRECIO VTA",Z10-MaestraLP3[[#This Row],[PRECIO OCT]]) -> 0 | AB10: =+IFERROR((Z10-W10)/Z10,"-") -> 0.33484379 | AC10: =IFERROR(MaestraLP3[[#This Row],[PRECIO]]*MaestraLP3[[#This Row],[%MG UMV]],0) -> 14040 | AD10: 0.53 | AE10: =IFERROR(MaestraLP3[[#This Row],[MARGEN UNITARIO]]/MaestraLP3[[#This Row],[Peso Neto UMV (KG)]],0) -> 26490.566 | AF10: NO | AG10: 2 y 3 | AH10: 0.1 | AI10: 0 | AJ10: SI | AK10: NO
A11: EXCLUSIVOS | B11: 101600043 | C11: =+MaestraLP3[[#This Row],[CÓDIGO]]&MaestraLP3[[#Headers],[-]]&MaestraLP3[[#This Row],[UMV]] -> 101600043-C10 | D11: =+MaestraLP3[[#This Row],[CÓDIGO]]&MaestraLP3[[#Headers],[FS00]] -> 101600043FS00 | E11: BELTRÁN FRANZANI | F11: CAMILA UGARTE | G11: CAFE Y DERIVADOS | H11: CAPSULAS Y PODS | I11: CAPSULA ESPRESSO QUALITA ORO LAVAZZA 55g | J11: C10 | K11: UN | L11: UN | M11: =VLOOKUP(MaestraLP3[[#This Row],[UMV]],VALIDACIONES!J:L,3,0) -> Caja 10 Unidades | N11: SECO | O11: NFS | P11: 25549.45 | Q11: BAJA | R11: 41930 | S11: =IFERROR((MaestraLP3[[#This Row],[COSTO ]]/MaestraLP3[[#This Row],[COSTO OCT]]-1),0) -> 0.017007803 | T11: ACTIVO | V11: =+VLOOKUP(MaestraLP3[[#This Row],[-]],'[1]BD MES'!$A:$N,14,0) -> 27446.33 | W11: 25983.99 | X11: =+(MaestraLP3[[#This Row],[COSTO ]]-MaestraLP3[[#This Row],[COSTO OCT AL 27-10]])/MaestraLP3[[#This Row],[COSTO OCT AL 27-10]] -> -0.053279983 | Y11: =++IF(Q11="HASTA AGOTAR STOCK","HASTA AGOTAR STOCK",IF(MaestraLP3[[#This Row],[PRECIO OCT]]=0,"NO PARA LP",IF(MaestraLP3[[#This Row],[PRECIO OCT]]=0,"INCORPORACIÓN",IF(AA11=0,"MANTIENE",IF(AA11<0,"BAJA",IF(AA11>0,"ALZA","")))))) -> MANTIENE | Z11: 41930 | AA11: =IF(Z11=0,"INDICAR PRECIO VTA",Z11-MaestraLP3[[#This Row],[PRECIO OCT]]) -> 0 | AB11: =+IFERROR((Z11-W11)/Z11,"-") -> 0.38030074 | AC11: =IFERROR(MaestraLP3[[#This Row],[PRECIO]]*MaestraLP3[[#This Row],[%MG UMV]],0) -> 15946.01 | AD11: 0.55 | AE11: =IFERROR(MaestraLP3[[#This Row],[MARGEN UNITARIO]]/MaestraLP3[[#This Row],[Peso Neto UMV (KG)]],0) -> 28992.745 | AF11: NO | AG11: 2 y 3 | AH11: 0.1 | AI11: 0 | AJ11: SI | AK11: NO
A12: EXCLUSIVOS | B12: 104543140 | C12: =+MaestraLP3[[#This Row],[CÓDIGO]]&MaestraLP3[[#Headers],[-]]&MaestraLP3[[#This Row],[UMV]] -> 104543140-Z50 | D12: =+MaestraLP3[[#This Row],[CÓDIGO]]&MaestraLP3[[#Headers],[FS00]] -> 104543140FS00 | E12: BERNARDITA UNDURRAGA | F12: BERNARDITA UNDURRAGA | G12: BOLLERIA | H12: BOLLERIA PARA HORNEAR | I12: GALLETA CHOCOLATE HILTON 63,78 G | J12: Z50 | K12: Z50 | M12: =VLOOKUP(MaestraLP3[[#This Row],[UMV]],VALIDACIONES!J:L,3,0) -> Caja 150 Unidades | N12: CONGELADOS | O12: IFS | P12: 85543 | Q12: NO PARA LP | R12: 0 | S12: =IFERROR((MaestraLP3[[#This Row],[COSTO ]]/MaestraLP3[[#This Row],[COSTO OCT]]-1),0) -> 0 | T12: CALZADA | U12: CALZADA | V12: =+VLOOKUP(MaestraLP3[[#This Row],[-]],'[1]BD MES'!$A:$N,14,0) -> 75270 | W12: 85543 | X12: =+(MaestraLP3[[#This Row],[COSTO ]]-MaestraLP3[[#This Row],[COSTO OCT AL 27-10]])/MaestraLP3[[#This Row],[COSTO OCT AL 27-10]] -> 0.136482 | Y12: =++IF(Q12="HASTA AGOTAR STOCK","HASTA AGOTAR STOCK",IF(MaestraLP3[[#This Row],[PRECIO OCT]]=0,"NO PARA LP",IF(MaestraLP3[[#This Row],[PRECIO OCT]]=0,"INCORPORACIÓN",IF(AA12=0,"MANTIENE",IF(AA12<0,"BAJA",IF(AA12>0,"ALZA","")))))) -> NO PARA LP | AA12: =IF(Z12=0,"INDICAR PRECIO VTA",Z12-MaestraLP3[[#This Row],[PRECIO OCT]]) -> INDICAR PRECIO VTA | AB12: =+IFERROR((Z12-W12)/Z12,"-") -> - | AC12: =IFERROR(MaestraLP3[[#This Row],[PRECIO]]*MaestraLP3[[#This Row],[%MG UMV]],0) -> 0 | AD12: 9.56 | AE12: =IFERROR(MaestraLP3[[#This Row],[MARGEN UNITARIO]]/MaestraLP3[[#This Row],[Peso Neto UMV (KG)]],0) -> 0 | AF12: NO | AG12: 1 | AH12: 0.05 | AI12: 0.05 | AK12: NO
A13: EXCLUSIVOS | B13: 104548580 | C13: =+MaestraLP3[[#This Row],[CÓDIGO]]&MaestraLP3[[#Headers],[-]]&MaestraLP3[[#This Row],[UMV]] -> 104548580-UN | D13: =+MaestraLP3[[#This Row],[CÓDIGO]]&MaestraLP3[[#Headers],[FS00]] -> 104548580FS00 | E13: BERNARDITA UNDURRAGA | F13: BERNARDITA UNDURRAGA | G13: BOLLERIA | H13: BOLLERIA PARA HORNEAR | I13: MINI CROISSANT 35 G | J13: UN | K13: UN | M13: =VLOOKUP(MaestraLP3[[#This Row],[UMV]],VALIDACIONES!J:L,3,0) -> Unidad | N13: CONGELADOS | O13: IFS | P13: 96 | Q13: NO PARA LP | R13: 0 | S13: =IFERROR((MaestraLP3[[#This Row],[COSTO ]]/MaestraLP3[[#This Row],[COSTO OCT]]-1),0) -> 0 | T13: CALZADA | U13: CALZADA | V13: =+VLOOKUP(MaestraLP3[[#This Row],[-]],'[1]BD MES'!$A:$N,14,0) -> 95 | W13: 96 | X13: =+(MaestraLP3[[#This Row],[COSTO ]]-MaestraLP3[[#This Row],[COSTO OCT AL 27-10]])/MaestraLP3[[#This Row],[COSTO OCT AL 27-10]] -> 0.010526316 | Y13: =++IF(Q13="HASTA AGOTAR STOCK","HASTA AGOTAR STOCK",IF(MaestraLP3[[#This Row],[PRECIO OCT]]=0,"NO PARA LP",IF(MaestraLP3[[#This Row],[PRECIO OCT]]=0,"INCORPORACIÓN",IF(AA13=0,"MANTIENE",IF(AA13<0,"BAJA",IF(AA13>0,"ALZA","")))))) -> NO PARA LP | Z13: 0 | AA13: =IF(Z13=0,"INDICAR PRECIO VTA",Z13-MaestraLP3[[#This Row],[PRECIO OCT]]) -> INDICAR PRECIO VTA | AB13: =+IFERROR((Z13-W13)/Z13,"-") -> - | AC13: =IFERROR(MaestraLP3[[#This Row],[PRECIO]]*MaestraLP3[[#This Row],[%MG UMV]],0) -> 0 | AD13: 0.04 | AE13: =IFERROR(MaestraLP3[[#This Row],[MARGEN UNITARIO]]/MaestraLP3[[#This Row],[Peso Neto UMV (KG)]],0) -> 0 | AF13: NO | AG13: 1 | AH13: 0 | AI13: 0 | AK13: NO
A14: EXCLUSIVOS | B14: 104544050 | C14: =+MaestraLP3[[#This Row],[CÓDIGO]]&MaestraLP3[[#Headers],[-]]&MaestraLP3[[#This Row],[UMV]] -> 104544050-CJ | D14: =+MaestraLP3[[#This Row],[CÓDIGO]]&MaestraLP3[[#Headers],[FS00]] -> 104544050FS00 | E14: BERNARDITA UNDURRAGA | F14: BERNARDITA UNDURRAGA | G14: BOLLERIA | H14: BOLLERIA PARA HORNEAR | I14: MINI CROISSANT RECTO 5 KG | J14: CJ | K14: CJ | M14: =VLOOKUP(MaestraLP3[[#This Row],[UMV]],VALIDACIONES!J:L,3,0) -> Caja | N14: CONGELADOS | O14: IFS | P14: 22773 | Q14: NO PARA LP | R14: 0 | S14: =IFERROR((MaestraLP3[[#This Row],[COSTO ]]/MaestraLP3[[#This Row],[COSTO OCT]]-1),0) -> 0 | T14: CALZADA | U14: CALZADA | V14: =+VLOOKUP(MaestraLP3[[#This Row],[-]],'[1]BD MES'!$A:$N,14,0) -> 22773 | W14: 22773 | X14: =+(MaestraLP3[[#This Row],[COSTO ]]-MaestraLP3[[#This Row],[COSTO OCT AL 27-10]])/MaestraLP3[[#This Row],[COSTO OCT AL 27-10]] -> 0 | Y14: =++IF(Q14="HASTA AGOTAR STOCK","HASTA AGOTAR STOCK",IF(MaestraLP3[[#This Row],[PRECIO OCT]]=0,"NO PARA LP",IF(MaestraLP3[[#This Row],[PRECIO OCT]]=0,"INCORPORACIÓN",IF(AA14=0,"MANTIENE",IF(AA14<0,"BAJA",IF(AA14>0,"ALZA","")))))) -> NO PARA LP | Z14: 0 | AA14: =IF(Z14=0,"INDICAR PRECIO VTA",Z14-MaestraLP3[[#This Row],[PRECIO OCT]]) -> INDICAR PRECIO VTA | AB14: =+IFERROR((Z14-W14)/Z14,"-") -> - | AC14: =IFERROR(MaestraLP3[[#This Row],[PRECIO]]*MaestraLP3[[#This Row],[%MG UMV]],0) -> 0 | AD14: 5 | AE14: =IFERROR(MaestraLP3[[#This Row],[MARGEN UNITARIO]]/MaestraLP3[[#This Row],[Peso Neto UMV (KG)]],0) -> 0 | AF14: NO | AG14: 1 | AH14: 0 | AI14: 0 | AK14: NO
A15: EXCLUSIVOS | B15: 104544060 | C15: =+MaestraLP3[[#This Row],[CÓDIGO]]&MaestraLP3[[#Headers],[-]]&MaestraLP3[[#This Row],[UMV]] -> 104544060-CJ | D15: =+MaestraLP3[[#This Row],[CÓDIGO]]&MaestraLP3[[#Headers],[FS00]] -> 104544060FS00 | E15: BERNARDITA UNDURRAGA | F15: BERNARDITA UNDURRAGA | G15: BOLLERIA | H15: BOLLERIA PARA HORNEAR | I15: PALMERA MINI 5 KG | J15: CJ | K15: CJ | M15: =VLOOKUP(MaestraLP3[[#This Row],[UMV]],VALIDACIONES!J:L,3,0) -> Caja | N15: CONGELADOS | O15: IFS | P15: 24051 | Q15: NO PARA LP | R15: 0 | S15: =IFERROR((MaestraLP3[[#This Row],[COSTO ]]/MaestraLP3[[#This Row],[COSTO OCT]]-1),0) -> 0 | T15: CALZADA | U15: CALZADA | V15: =+VLOOKUP(MaestraLP3[[#This Row],[-]],'[1]BD MES'!$A:$N,14,0) -> 24051 | W15: 24051 | X15: =+(MaestraLP3[[#This Row],[COSTO ]]-MaestraLP3[[#This Row],[COSTO OCT AL 27-10]])/MaestraLP3[[#This Row],[COSTO OCT AL 27-10]] -> 0 | Y15: =++IF(Q15="HASTA AGOTAR STOCK","HASTA AGOTAR STOCK",IF(MaestraLP3[[#This Row],[PRECIO OCT]]=0,"NO PARA LP",IF(MaestraLP3[[#This Row],[PRECIO OCT]]=0,"INCORPORACIÓN",IF(AA15=0,"MANTIENE",IF(AA15<0,"BAJA",IF(AA15>0,"ALZA","")))))) -> NO PARA LP | Z15: 0 | AA15: =IF(Z15=0,"INDICAR PRECIO VTA",Z15-MaestraLP3[[#This Row],[PRECIO OCT]]) -> INDICAR PRECIO VTA | AB15: =+IFERROR((Z15-W15)/Z15,"-") -> - | AC15: =IFERROR(MaestraLP3[[#This Row],[PRECIO]]*MaestraLP3[[#This Row],[%MG UMV]],0) -> 0 | AD15: 5 | AE15: =IFERROR(MaestraLP3[[#This Row],[MARGEN UNITARIO]]/MaestraLP3[[#This Row],[Peso Neto UMV (KG)]],0) -> 0 | AF15: NO | AG15: 1 | AH15: 0 | AI15: 0 | AK15: NO
A16: EXCLUSIVOS | B16: 104548600 | C16: =+MaestraLP3[[#This Row],[CÓDIGO]]&MaestraLP3[[#Headers],[-]]&MaestraLP3[[#This Row],[UMV]] -> 104548600-UN | D16: =+MaestraLP3[[#This Row],[CÓDIGO]]&MaestraLP3[[#Headers],[FS00]] -> 104548600FS00 | E16: BERNARDITA UNDURRAGA | F16: BERNARDITA UNDURRAGA | G16: BOLLERIA | H16: BOLLERIA PARA HORNEAR | I16: PALMERITA 23 G | J16: UN | K16: UN | M16: =VLOOKUP(MaestraLP3[[#This Row],[UMV]],VALIDACIONES!J:L,3,0) -> Unidad | N16: CONGELADOS | O16: IFS | P16: 69 | Q16: NO PARA LP | R16: 0 | S16: =IFERROR((MaestraLP3[[#This Row],[COSTO ]]/MaestraLP3[[#This Row],[COSTO OCT]]-1),0) -> 0 | T16: CALZADA | U16: CALZADA | V16: =+VLOOKUP(MaestraLP3[[#This Row],[-]],'[1]BD MES'!$A:$N,14,0) -> 71 | W16: 69 | X16: =+(MaestraLP3[[#This Row],[COSTO ]]-MaestraLP3[[#This Row],[COSTO OCT AL 27-10]])/MaestraLP3[[#This Row],[COSTO OCT AL 27-10]] -> -0.028169014 | Y16: =++IF(Q16="HASTA AGOTAR STOCK","HASTA AGOTAR STOCK",IF(MaestraLP3[[#This Row],[PRECIO OCT]]=0,"NO PARA LP",IF(MaestraLP3[[#This Row],[PRECIO OCT]]=0,"INCORPORACIÓN",IF(AA16=0,"MANTIENE",IF(AA16<0,"BAJA",IF(AA16>0,"ALZA","")))))) -> NO PARA LP | Z16: 0 | AA16: =IF(Z16=0,"INDICAR PRECIO VTA",Z16-MaestraLP3[[#This Row],[PRECIO OCT]]) -> INDICAR PRECIO VTA | AB16: =+IFERROR((Z16-W16)/Z16,"-") -> - | AC16: =IFERROR(MaestraLP3[[#This Row],[PRECIO]]*MaestraLP3[[#This Row],[%MG UMV]],0) -> 0 | AD16: 0.02 | AE16: =IFERROR(MaestraLP3[[#This Row],[MARGEN UNITARIO]]/MaestraLP3[[#This Row],[Peso Neto UMV (KG)]],0) -> 0 | AF16: NO | AG16: 1 | AH16: 0 | AI16: 0 | AK16: NO
A17: EXCLUSIVOS | B17: 104548530 | C17: =+MaestraLP3[[#This Row],[CÓDIGO]]&MaestraLP3[[#Headers],[-]]&MaestraLP3[[#This Row],[UMV]] -> 104548530-C60 | D17: =+MaestraLP3[[#This Row],[CÓDIGO]]&MaestraLP3[[#Headers],[FS00]] -> 104548530FS00 | E17: BERNARDITA UNDURRAGA | F17: BERNARDITA UNDURRAGA | G17: BOLLERIA | H17: BOLLERIA PARA HORNEAR | I17: ROLLITO DE CHOCOLATE 80 G | J17: C60 | K17: UN | M17: =VLOOKUP(MaestraLP3[[#This Row],[UMV]],VALIDACIONES!J:L,3,0) -> Caja 60 Unidades | N17: CONGELADOS | O17: IFS | P17: 42660 | Q17: NO PARA LP | R17: 0 | S17: =IFERROR((MaestraLP3[[#This Row],[COSTO ]]/MaestraLP3[[#This Row],[COSTO OCT]]-1),0) -> 0 | T17: CALZADA | U17: CALZADA | V17: =+VLOOKUP(MaestraLP3[[#This Row],[-]],'[1]BD MES'!$A:$N,14,0) -> 46200 | W17: 42660 | X17: =+(MaestraLP3[[#This Row],[COSTO ]]-MaestraLP3[[#This Row],[COSTO OCT AL 27-10]])/MaestraLP3[[#This Row],[COSTO OCT AL 27-10]] -> -0.076623377 | Y17: =++IF(Q17="HASTA AGOTAR STOCK","HASTA AGOTAR STOCK",IF(MaestraLP3[[#This Row],[PRECIO OCT]]=0,"NO PARA LP",IF(MaestraLP3[[#This Row],[PRECIO OCT]]=0,"INCORPORACIÓN",IF(AA17=0,"MANTIENE",IF(AA17<0,"BAJA",IF(AA17>0,"ALZA","")))))) -> NO PARA LP | Z17: 0 | AA17: =IF(Z17=0,"INDICAR PRECIO VTA",Z17-MaestraLP3[[#This Row],[PRECIO OCT]]) -> INDICAR PRECIO VTA | AB17: =+IFERROR((Z17-W17)/Z17,"-") -> - | AC17: =IFERROR(MaestraLP3[[#This Row],[PRECIO]]*MaestraLP3[[#This Row],[%MG UMV]],0) -> 0 | AD17: 4.8 | AE17: =IFERROR(MaestraLP3[[#This Row],[MARGEN UNITARIO]]/MaestraLP3[[#This Row],[Peso Neto UMV (KG)]],0) -> 0 | AF17: NO | AG17: 1 | AH17: 0 | AI17: 0 | AK17: NO
A18: EXCLUSIVOS | B18: 104548520 | C18: =+MaestraLP3[[#This Row],[CÓDIGO]]&MaestraLP3[[#Headers],[-]]&MaestraLP3[[#This Row],[UMV]] -> 104548520-C31 | D18: =+MaestraLP3[[#This Row],[CÓDIGO]]&MaestraLP3[[#Headers],[FS00]] -> 104548520FS00 | E18: BERNARDITA UNDURRAGA | F18: BERNARDITA UNDURRAGA | G18: BOLLERIA | H18: PANES PARA HORNEAR | I18: PAN BAGUETTE GRANDE 260 G | J18: C31 | K18: UN | M18: =VLOOKUP(MaestraLP3[[#This Row],[UMV]],VALIDACIONES!J:L,3,0) -> Caja 31 Unidades | N18: CONGELADOS | O18: IFS | P18: 15190 | Q18: NO PARA LP | R18: 0 | S18: =IFERROR((MaestraLP3[[#This Row],[COSTO ]]/MaestraLP3[[#This Row],[COSTO OCT]]-1),0) -> 0 | T18: CALZADA | U18: CALZADA | V18: =+VLOOKUP(MaestraLP3[[#This Row],[-]],'[1]BD MES'!$A:$N,14,0) -> 12028 | W18: 15190 | X18: =+(MaestraLP3[[#This Row],[COSTO ]]-MaestraLP3[[#This Row],[COSTO OCT AL 27-10]])/MaestraLP3[[#This Row],[COSTO OCT AL 27-10]] -> 0.2628866 | Y18: =++IF(Q18="HASTA AGOTAR STOCK","HASTA AGOTAR STOCK",IF(MaestraLP3[[#This Row],[PRECIO OCT]]=0,"NO PARA LP",IF(MaestraLP3[[#This Row],[PRECIO OCT]]=0,"INCORPORACIÓN",IF(AA18=0,"MANTIENE",IF(AA18<0,"BAJA",IF(AA18>0,"ALZA","")))))) -> NO PARA LP | Z18: 0 | AA18: =IF(Z18=0,"INDICAR PRECIO VTA",Z18-MaestraLP3[[#This Row],[PRECIO OCT]]) -> INDICAR PRECIO VTA | AB18: =+IFERROR((Z18-W18)/Z18,"-") -> - | AC18: =IFERROR(MaestraLP3[[#This Row],[PRECIO]]*MaestraLP3[[#This Row],[%MG UMV]],0) -> 0 | AD18: 8.06 | AE18: =IFERROR(MaestraLP3[[#This Row],[MARGEN UNITARIO]]/MaestraLP3[[#This Row],[Peso Neto UMV (KG)]],0) -> 0 | AF18: NO | AG18: 1 | AH18: 0 | AI18: 0 | AK18: NO
A19: EXCLUSIVOS | B19: 104548510 | C19: =+MaestraLP3[[#This Row],[CÓDIGO]]&MaestraLP3[[#Headers],[-]]&MaestraLP3[[#This Row],[UMV]] -> 104548510-C20 | D19: =+MaestraLP3[[#This Row],[CÓDIGO]]&MaestraLP3[[#Headers],[FS00]] -> 104548510FS00 | E19: BERNARDITA UNDURRAGA | F19: BERNARDITA UNDURRAGA | G19: BOLLERIA | H19: PANES PARA HORNEAR | I19: PAN BATARD 440 G | J19: C20 | K19: UN | M19: =VLOOKUP(MaestraLP3[[#This Row],[UMV]],VALIDACIONES!J:L,3,0) -> Caja 20 Unidades | N19: CONGELADOS | O19: IFS | P19: 15580 | Q19: NO PARA LP | R19: 0 | S19: =IFERROR((MaestraLP3[[#This Row],[COSTO ]]/MaestraLP3[[#This Row],[COSTO OCT]]-1),0) -> 0 | T19: CALZADA | U19: CALZADA | V19: =+VLOOKUP(MaestraLP3[[#This Row],[-]],'[1]BD MES'!$A:$N,14,0) -> 12480 | W19: 15580 | X19: =+(MaestraLP3[[#This Row],[COSTO ]]-MaestraLP3[[#This Row],[COSTO OCT AL 27-10]])/MaestraLP3[[#This Row],[COSTO OCT AL 27-10]] -> 0.24839744 | Y19: =++IF(Q19="HASTA AGOTAR STOCK","HASTA AGOTAR STOCK",IF(MaestraLP3[[#This Row],[PRECIO OCT]]=0,"NO PARA LP",IF(MaestraLP3[[#This Row],[PRECIO OCT]]=0,"INCORPORACIÓN",IF(AA19=0,"MANTIENE",IF(AA19<0,"BAJA",IF(AA19>0,"ALZA","")))))) -> NO PARA LP | Z19: 0 | AA19: =IF(Z19=0,"INDICAR PRECIO VTA",Z19-MaestraLP3[[#This Row],[PRECIO OCT]]) -> INDICAR PRECIO VTA | AB19: =+IFERROR((Z19-W19)/Z19,"-") -> - | AC19: =IFERROR(MaestraLP3[[#This Row],[PRECIO]]*MaestraLP3[[#This Row],[%MG UMV]],0) -> 0 | AD19: 8.8 | AE19: =IFERROR(MaestraLP3[[#This Row],[MARGEN UNITARIO]]/MaestraLP3[[#This Row],[Peso Neto UMV (KG)]],0) -> 0 | AF19: NO | AG19: 1 | AH19: 0 | AI19: 0 | AK19: NO
A20: EXCLUSIVOS | B20: 104548500 | C20: =+MaestraLP3[[#This Row],[CÓDIGO]]&MaestraLP3[[#Headers],[-]]&MaestraLP3[[#This Row],[UMV]] -> 104548500-C20 | D20: =+MaestraLP3[[#This Row],[CÓDIGO]]&MaestraLP3[[#Headers],[FS00]] -> 104548500FS00 | E20: BERNARDITA UNDURRAGA | F20: BERNARDITA UNDURRAGA | G20: BOLLERIA | H20: PANES PARA HORNEAR | I20: PAN BATARD INTEGRAL 440 G | J20: C20 | K20: UN | M20: =VLOOKUP(MaestraLP3[[#This Row],[UMV]],VALIDACIONES!J:L,3,0) -> Caja 20 Unidades | N20: CONGELADOS | O20: IFS | P20: 18740 | Q20: NO PARA LP | R20: 0 | S20: =IFERROR((MaestraLP3[[#This Row],[COSTO ]]/MaestraLP3[[#This Row],[COSTO OCT]]-1),0) -> 0 | T20: CALZADA | U20: CALZADA | V20: =+VLOOKUP(MaestraLP3[[#This Row],[-]],'[1]BD MES'!$A:$N,14,0) -> 15980 | W20: 18740 | X20: =+(MaestraLP3[[#This Row],[COSTO ]]-MaestraLP3[[#This Row],[COSTO OCT AL 27-10]])/MaestraLP3[[#This Row],[COSTO OCT AL 27-10]] -> 0.17271589 | Y20: =++IF(Q20="HASTA AGOTAR STOCK","HASTA AGOTAR STOCK",IF(MaestraLP3[[#This Row],[PRECIO OCT]]=0,"NO PARA LP",IF(MaestraLP3[[#This Row],[PRECIO OCT]]=0,"INCORPORACIÓN",IF(AA20=0,"MANTIENE",IF(AA20<0,"BAJA",IF(AA20>0,"ALZA","")))))) -> NO PARA LP | Z20: 0 | AA20: =IF(Z20=0,"INDICAR PRECIO VTA",Z20-MaestraLP3[[#This Row],[PRECIO OCT]]) -> INDICAR PRECIO VTA | AB20: =+IFERROR((Z20-W20)/Z20,"-") -> - | AC20: =IFERROR(MaestraLP3[[#This Row],[PRECIO]]*MaestraLP3[[#This Row],[%MG UMV]],0) -> 0 | AD20: 8.8 | AE20: =IFERROR(MaestraLP3[[#This Row],[MARGEN UNITARIO]]/MaestraLP3[[#This Row],[Peso Neto UMV (KG)]],0) -> 0 | AF20: NO | AG20: 1 | AH20: 0 | AI20: 0 | AK20: NO
A21: EXCLUSIVOS | B21: 104548590 | C21: =+MaestraLP3[[#This Row],[CÓDIGO]]&MaestraLP3[[#Headers],[-]]&MaestraLP3[[#This Row],[UMV]] -> 104548590-C20 | D21: =+MaestraLP3[[#This Row],[CÓDIGO]]&MaestraLP3[[#Headers],[FS00]] -> 104548590FS00 | E21: BERNARDITA UNDURRAGA | F21: BERNARDITA UNDURRAGA | G21: BOLLERIA | H21: PANES PARA HORNEAR | I21: PAN BATARD MULTICEREAL 440 G | J21: C20 | K21: UN | M21: =VLOOKUP(MaestraLP3[[#This Row],[UMV]],VALIDACIONES!J:L,3,0) -> Caja 20 Unidades | N21: CONGELADOS | O21: IFS | P21: 20060 | Q21: NO PARA LP | R21: 0 | S21: =IFERROR((MaestraLP3[[#This Row],[COSTO ]]/MaestraLP3[[#This Row],[COSTO OCT]]-1),0) -> 0 | T21: CALZADA | U21: CALZADA | V21: =+VLOOKUP(MaestraLP3[[#This Row],[-]],'[1]BD MES'!$A:$N,14,0) -> 17300 | W21: 20060 | X21: =+(MaestraLP3[[#This Row],[COSTO ]]-MaestraLP3[[#This Row],[COSTO OCT AL 27-10]])/MaestraLP3[[#This Row],[COSTO OCT AL 27-10]] -> 0.15953757 | Y21: =++IF(Q21="HASTA AGOTAR STOCK","HASTA AGOTAR STOCK",IF(MaestraLP3[[#This Row],[PRECIO OCT]]=0,"NO PARA LP",IF(MaestraLP3[[#This Row],[PRECIO OCT]]=0,"INCORPORACIÓN",IF(AA21=0,"MANTIENE",IF(AA21<0,"BAJA",IF(AA21>0,"ALZA","")))))) -> NO PARA LP | Z21: 0 | AA21: =IF(Z21=0,"INDICAR PRECIO VTA",Z21-MaestraLP3[[#This Row],[PRECIO OCT]]) -> INDICAR PRECIO VTA | AB21: =+IFERROR((Z21-W21)/Z21,"-") -> - | AC21: =IFERROR(MaestraLP3[[#This Row],[PRECIO]]*MaestraLP3[[#This Row],[%MG UMV]],0) -> 0 | AD21: 8.8 | AE21: =IFERROR(MaestraLP3[[#This Row],[MARGEN UNITARIO]]/MaestraLP3[[#This Row],[Peso Neto UMV (KG)]],0) -> 0 | AF21: NO | AG21: 1 | AH21: 0 | AI21: 0 | AK21: NO
A22: EXCLUSIVOS | B22: 104548570 | C22: =+MaestraLP3[[#This Row],[CÓDIGO]]&MaestraLP3[[#Headers],[-]]&MaestraLP3[[#This Row],[UMV]] -> 104548570-C40 | D22: =+MaestraLP3[[#This Row],[CÓDIGO]]&MaestraLP3[[#Headers],[FS00]] -> 104548570FS00 | E22: BERNARDITA UNDURRAGA | F22: BERNARDITA UNDURRAGA | G22: BOLLERIA | H22: PANES PARA HORNEAR | I22: PAN CIABATTA 130 G | J22: C40 | K22: UN | M22: =VLOOKUP(MaestraLP3[[#This Row],[UMV]],VALIDACIONES!J:L,3,0) -> Caja 40 Unidades | N22: CONGELADOS | O22: IFS | P22: 12440 | Q22: NO PARA LP | R22: 0 | S22: =IFERROR((MaestraLP3[[#This Row],[COSTO ]]/MaestraLP3[[#This Row],[COSTO OCT]]-1),0) -> 0 | T22: ACTIVO | U22: ACTIVO | V22: =+VLOOKUP(MaestraLP3[[#This Row],[-]],'[1]BD MES'!$A:$N,14,0) -> 9760 | W22: 12440 | X22: =+(MaestraLP3[[#This Row],[COSTO ]]-MaestraLP3[[#This Row],[COSTO OCT AL 27-10]])/MaestraLP3[[#This Row],[COSTO OCT AL 27-10]] -> 0.27459016 | Y22: =++IF(Q22="HASTA AGOTAR STOCK","HASTA AGOTAR STOCK",IF(MaestraLP3[[#This Row],[PRECIO OCT]]=0,"NO PARA LP",IF(MaestraLP3[[#This Row],[PRECIO OCT]]=0,"INCORPORACIÓN",IF(AA22=0,"MANTIENE",IF(AA22<0,"BAJA",IF(AA22>0,"ALZA","")))))) -> NO PARA LP | Z22: 0 | AA22: =IF(Z22=0,"INDICAR PRECIO VTA",Z22-MaestraLP3[[#This Row],[PRECIO OCT]]) -> INDICAR PRECIO VTA | AB22: =+IFERROR((Z22-W22)/Z22,"-") -> - | AC22: =IFERROR(MaestraLP3[[#This Row],[PRECIO]]*MaestraLP3[[#This Row],[%MG UMV]],0) -> 0 | AD22: 5.2 | AE22: =IFERROR(MaestraLP3[[#This Row],[MARGEN UNITARIO]]/MaestraLP3[[#This Row],[Peso Neto UMV (KG)]],0) -> 0 | AF22: NO | AG22: 1 | AH22: 0 | AI22: 0 | AK22: NO
A23: EXCLUSIVOS | B23: 104548560 | C23: =+MaestraLP3[[#This Row],[CÓDIGO]]&MaestraLP3[[#Headers],[-]]&MaestraLP3[[#This Row],[UMV]] -> 104548560-C31 | D23: =+MaestraLP3[[#This Row],[CÓDIGO]]&MaestraLP3[[#Headers],[FS00]] -> 104548560FS00 | E23: BERNARDITA UNDURRAGA | F23: BERNARDITA UNDURRAGA | G23: BOLLERIA | H23: PANES PARA HORNEAR | I23: PAN CIABATTA GRANDE 300 G | J23: C31 | K23: UN | M23: =VLOOKUP(MaestraLP3[[#This Row],[UMV]],VALIDACIONES!J:L,3,0) -> Caja 31 Unidades | N23: CONGELADOS | O23: IFS | P23: 21886 | Q23: NO PARA LP | R23: 0 | S23: =IFERROR((MaestraLP3[[#This Row],[COSTO ]]/MaestraLP3[[#This Row],[COSTO OCT]]-1),0) -> 0 | T23: CALZADA | U23: CALZADA | V23: =+VLOOKUP(MaestraLP3[[#This Row],[-]],'[1]BD MES'!$A:$N,14,0) -> 19313 | W23: 21886 | X23: =+(MaestraLP3[[#This Row],[COSTO ]]-MaestraLP3[[#This Row],[COSTO OCT AL 27-10]])/MaestraLP3[[#This Row],[COSTO OCT AL 27-10]] -> 0.13322632 | Y23: =++IF(Q23="HASTA AGOTAR STOCK","HASTA AGOTAR STOCK",IF(MaestraLP3[[#This Row],[PRECIO OCT]]=0,"NO PARA LP",IF(MaestraLP3[[#This Row],[PRECIO OCT]]=0,"INCORPORACIÓN",IF(AA23=0,"MANTIENE",IF(AA23<0,"BAJA",IF(AA23>0,"ALZA","")))))) -> NO PARA LP | Z23: 22900 | AA23: =IF(Z23=0,"INDICAR PRECIO VTA",Z23-MaestraLP3[[#This Row],[PRECIO OCT]]) -> 22900 | AB23: =+IFERROR((Z23-W23)/Z23,"-") -> 0.044279476 | AC23: =IFERROR(MaestraLP3[[#This Row],[PRECIO]]*MaestraLP3[[#This Row],[%MG UMV]],0) -> 1014 | AD23: 9.3 | AE23: =IFERROR(MaestraLP3[[#This Row],[MARGEN UNITARIO]]/MaestraLP3[[#This Row],[Peso Neto UMV (KG)]],0) -> 109.03226 | AF23: NO | AG23: 1 | AH23: 0 | AI23: 0 | AK23: NO
A24: EXCLUSIVOS | B24: 104548550 | C24: =+MaestraLP3[[#This Row],[CÓDIGO]]&MaestraLP3[[#Headers],[-]]&MaestraLP3[[#This Row],[UMV]] -> 104548550-C20 | D24: =+MaestraLP3[[#This Row],[CÓDIGO]]&MaestraLP3[[#Headers],[FS00]] -> 104548550FS00 | E24: BERNARDITA UNDURRAGA | F24: BERNARDITA UNDURRAGA | G24: BOLLERIA | H24: PANES PARA HORNEAR | I24: PAN GRAND RUSTICA 340 G | J24: C20 | K24: UN | M24: =VLOOKUP(MaestraLP3[[#This Row],[UMV]],VALIDACIONES!J:L,3,0) -> Caja 20 Unidades | N24: CONGELADOS | O24: IFS | P24: 17680 | Q24: NO PARA LP | R24: 0 | S24: =IFERROR((MaestraLP3[[#This Row],[COSTO ]]/MaestraLP3[[#This Row],[COSTO OCT]]-1),0) -> 0 | T24: CALZADA | U24: CALZADA | V24: =+VLOOKUP(MaestraLP3[[#This Row],[-]],'[1]BD MES'!$A:$N,14,0) -> 17680 | W24: 17680 | X24: =+(MaestraLP3[[#This Row],[COSTO ]]-MaestraLP3[[#This Row],[COSTO OCT AL 27-10]])/MaestraLP3[[#This Row],[COSTO OCT AL 27-10]] -> 0 | Y24: =++IF(Q24="HASTA AGOTAR STOCK","HASTA AGOTAR STOCK",IF(MaestraLP3[[#This Row],[PRECIO OCT]]=0,"NO PARA LP",IF(MaestraLP3[[#This Row],[PRECIO OCT]]=0,"INCORPORACIÓN",IF(AA24=0,"MANTIENE",IF(AA24<0,"BAJA",IF(AA24>0,"ALZA","")))))) -> NO PARA LP | Z24: 0 | AA24: =IF(Z24=0,"INDICAR PRECIO VTA",Z24-MaestraLP3[[#This Row],[PRECIO OCT]]) -> INDICAR PRECIO VTA | AB24: =+IFERROR((Z24-W24)/Z24,"-") -> - | AC24: =IFERROR(MaestraLP3[[#This Row],[PRECIO]]*MaestraLP3[[#This Row],[%MG UMV]],0) -> 0 | AD24: 6.8 | AE24: =IFERROR(MaestraLP3[[#This Row],[MARGEN UNITARIO]]/MaestraLP3[[#This Row],[Peso Neto UMV (KG)]],0) -> 0 | AF24: NO | AG24: 1 | AH24: 0 | AI24: 0 | AK24: NO
... A40: EXCLUSIVOS | B40: 104548380 | C40: =+MaestraLP3[[#This Row],[CÓDIGO]]&MaestraLP3[[#Headers],[-]]&MaestraLP3[[#This Row],[UMV]] -> 104548380-V00 | D40: =+MaestraLP3[[#This Row],[CÓDIGO]]&MaestraLP3[[#Headers],[FS00]] -> 104548380FS00 | E40: MARÍA DE LOS ÁNGELES QUIRÓZ | F40: GIORGIO LEVA | G40: SUMINISTROS | H40: DESECHABLES | I40: POTE 12 OZ / 340 CC | J40: V00 | K40: UN | M40: =VLOOKUP(MaestraLP3[[#This Row],[UMV]],VALIDACIONES!J:L,3,0) -> Caja 500 Unidades | N40: SECO | O40: NFS | P40: 30000 | Q40: NO PARA LP | R40: 0 | S40: =IFERROR((MaestraLP3[[#This Row],[COSTO ]]/MaestraLP3[[#This Row],[COSTO OCT]]-1),0) -> 0 | T40: CALZADA | U40: CALZADA | V40: =+VLOOKUP(MaestraLP3[[#This Row],[-]],'[1]BD MES'!$A:$N,14,0) -> 30000 | W40: 30000 | X40: =+(MaestraLP3[[#This Row],[COSTO ]]-MaestraLP3[[#This Row],[COSTO OCT AL 27-10]])/MaestraLP3[[#This Row],[COSTO OCT AL 27-10]] -> 0 | Y40: =++IF(Q40="HASTA AGOTAR STOCK","HASTA AGOTAR STOCK",IF(MaestraLP3[[#This Row],[PRECIO OCT]]=0,"NO PARA LP",IF(MaestraLP3[[#This Row],[PRECIO OCT]]=0,"INCORPORACIÓN",IF(AA40=0,"MANTIENE",IF(AA40<0,"BAJA",IF(AA40>0,"ALZA","")))))) -> NO PARA LP | Z40: 0 | AA40: =IF(Z40=0,"INDICAR PRECIO VTA",Z40-MaestraLP3[[#This Row],[PRECIO OCT]]) -> INDICAR PRECIO VTA | AB40: =+IFERROR((Z40-W40)/Z40,"-") -> - | AC40: =IFERROR(MaestraLP3[[#This Row],[PRECIO]]*MaestraLP3[[#This Row],[%MG UMV]],0) -> 0 | AD40: 5 | AE40: =IFERROR(MaestraLP3[[#This Row],[MARGEN UNITARIO]]/MaestraLP3[[#This Row],[Peso Neto UMV (KG)]],0) -> 0 | AF40: NO | AG40: 1 | AH40: 0 | AI40: 0 | AK40: NO
A41: EXCLUSIVOS | B41: 104541910 | C41: =+MaestraLP3[[#This Row],[CÓDIGO]]&MaestraLP3[[#Headers],[-]]&MaestraLP3[[#This Row],[UMV]] -> 104541910-1Q | D41: =+MaestraLP3[[#This Row],[CÓDIGO]]&MaestraLP3[[#Headers],[FS00]] -> 104541910FS00 | E41: MARÍA DE LOS ÁNGELES QUIRÓZ | F41: GIORGIO LEVA | G41: SUMINISTROS | H41: DESECHABLES | I41: POTE P/KRAFT BLANCO PLA YOGEN FRUZ 16 OZ | J41: 1Q | K41: UN | M41: =VLOOKUP(MaestraLP3[[#This Row],[UMV]],VALIDACIONES!J:L,3,0) -> Caja 1000 Unidades | N41: SECO | O41: NFS | P41: 60000 | Q41: NO PARA LP | R41: 0 | S41: =IFERROR((MaestraLP3[[#This Row],[COSTO ]]/MaestraLP3[[#This Row],[COSTO OCT]]-1),0) -> 0 | T41: CALZADA | U41: CALZADA | V41: =+VLOOKUP(MaestraLP3[[#This Row],[-]],'[1]BD MES'!$A:$N,14,0) -> 60000 | W41: 60000 | X41: =+(MaestraLP3[[#This Row],[COSTO ]]-MaestraLP3[[#This Row],[COSTO OCT AL 27-10]])/MaestraLP3[[#This Row],[COSTO OCT AL 27-10]] -> 0 | Y41: =++IF(Q41="HASTA AGOTAR STOCK","HASTA AGOTAR STOCK",IF(MaestraLP3[[#This Row],[PRECIO OCT]]=0,"NO PARA LP",IF(MaestraLP3[[#This Row],[PRECIO OCT]]=0,"INCORPORACIÓN",IF(AA41=0,"MANTIENE",IF(AA41<0,"BAJA",IF(AA41>0,"ALZA","")))))) -> NO PARA LP | Z41: 0 | AA41: =IF(Z41=0,"INDICAR PRECIO VTA",Z41-MaestraLP3[[#This Row],[PRECIO OCT]]) -> INDICAR PRECIO VTA | AB41: =+IFERROR((Z41-W41)/Z41,"-") -> - | AC41: =IFERROR(MaestraLP3[[#This Row],[PRECIO]]*MaestraLP3[[#This Row],[%MG UMV]],0) -> 0 | AD41: 14 | AE41: =IFERROR(MaestraLP3[[#This Row],[MARGEN UNITARIO]]/MaestraLP3[[#This Row],[Peso Neto UMV (KG)]],0) -> 0 | AF41: NO | AG41: 1 | AH41: 0 | AI41: 0 | AJ41: SI | AK41: NO
A42: EXCLUSIVOS | B42: 104541920 | C42: =+MaestraLP3[[#This Row],[CÓDIGO]]&MaestraLP3[[#Headers],[-]]&MaestraLP3[[#This Row],[UMV]] -> 104541920-V00 | D42: =+MaestraLP3[[#This Row],[CÓDIGO]]&MaestraLP3[[#Headers],[FS00]] -> 104541920FS00 | E42: MARÍA DE LOS ÁNGELES QUIRÓZ | F42: GIORGIO LEVA | G42: SUMINISTROS | H42: DESECHABLES | I42: POTE P/KRAFT BLANCO PLA YOGEN FRUZ 24 OZ | J42: V00 | K42: UN | M42: =VLOOKUP(MaestraLP3[[#This Row],[UMV]],VALIDACIONES!J:L,3,0) -> Caja 500 Unidades | N42: SECO | O42: NFS | P42: 52500 | Q42: NO PARA LP | R42: 0 | S42: =IFERROR((MaestraLP3[[#This Row],[COSTO ]]/MaestraLP3[[#This Row],[COSTO OCT]]-1),0) -> 0 | T42: CALZADA | U42: CALZADA | V42: =+VLOOKUP(MaestraLP3[[#This Row],[-]],'[1]BD MES'!$A:$N,14,0) -> 52500 | W42: 52500 | X42: =+(MaestraLP3[[#This Row],[COSTO ]]-MaestraLP3[[#This Row],[COSTO OCT AL 27-10]])/MaestraLP3[[#This Row],[COSTO OCT AL 27-10]] -> 0 | Y42: =++IF(Q42="HASTA AGOTAR STOCK","HASTA AGOTAR STOCK",IF(MaestraLP3[[#This Row],[PRECIO OCT]]=0,"NO PARA LP",IF(MaestraLP3[[#This Row],[PRECIO OCT]]=0,"INCORPORACIÓN",IF(AA42=0,"MANTIENE",IF(AA42<0,"BAJA",IF(AA42>0,"ALZA","")))))) -> NO PARA LP | Z42: 0 | AA42: =IF(Z42=0,"INDICAR PRECIO VTA",Z42-MaestraLP3[[#This Row],[PRECIO OCT]]) -> INDICAR PRECIO VTA | AB42: =+IFERROR((Z42-W42)/Z42,"-") -> - | AC42: =IFERROR(MaestraLP3[[#This Row],[PRECIO]]*MaestraLP3[[#This Row],[%MG UMV]],0) -> 0 | AD42: 8.5 | AE42: =IFERROR(MaestraLP3[[#This Row],[MARGEN UNITARIO]]/MaestraLP3[[#This Row],[Peso Neto UMV (KG)]],0) -> 0 | AF42: NO | AG42: 1 | AH42: 0 | AI42: 0 | AJ42: SI | AK42: NO
A43: EXCLUSIVOS | B43: 104541900 | C43: =+MaestraLP3[[#This Row],[CÓDIGO]]&MaestraLP3[[#Headers],[-]]&MaestraLP3[[#This Row],[UMV]] -> 104541900-1Q | D43: =+MaestraLP3[[#This Row],[CÓDIGO]]&MaestraLP3[[#Headers],[FS00]] -> 104541900FS00 | E43: MARÍA DE LOS ÁNGELES QUIRÓZ | F43: GIORGIO LEVA | G43: SUMINISTROS | H43: DESECHABLES | I43: POTE P/KRAFT BLANCO PLA YOURSERV 12 OZ | J43: 1Q | K43: UN | M43: =VLOOKUP(MaestraLP3[[#This Row],[UMV]],VALIDACIONES!J:L,3,0) -> Caja 1000 Unidades | N43: SECO | O43: NFS | P43: 62000 | Q43: NO PARA LP | R43: 0 | S43: =IFERROR((MaestraLP3[[#This Row],[COSTO ]]/MaestraLP3[[#This Row],[COSTO OCT]]-1),0) -> 0 | T43: CALZADA | U43: CALZADA | V43: =+VLOOKUP(MaestraLP3[[#This Row],[-]],'[1]BD MES'!$A:$N,14,0) -> 62000 | W43: 62000 | X43: =+(MaestraLP3[[#This Row],[COSTO ]]-MaestraLP3[[#This Row],[COSTO OCT AL 27-10]])/MaestraLP3[[#This Row],[COSTO OCT AL 27-10]] -> 0 | Y43: =++IF(Q43="HASTA AGOTAR STOCK","HASTA AGOTAR STOCK",IF(MaestraLP3[[#This Row],[PRECIO OCT]]=0,"NO PARA LP",IF(MaestraLP3[[#This Row],[PRECIO OCT]]=0,"INCORPORACIÓN",IF(AA43=0,"MANTIENE",IF(AA43<0,"BAJA",IF(AA43>0,"ALZA","")))))) -> NO PARA LP | Z43: 0 | AA43: =IF(Z43=0,"INDICAR PRECIO VTA",Z43-MaestraLP3[[#This Row],[PRECIO OCT]]) -> INDICAR PRECIO VTA | AB43: =+IFERROR((Z43-W43)/Z43,"-") -> - | AC43: =IFERROR(MaestraLP3[[#This Row],[PRECIO]]*MaestraLP3[[#This Row],[%MG UMV]],0) -> 0 | AD43: 10 | AE43: =IFERROR(MaestraLP3[[#This Row],[MARGEN UNITARIO]]/MaestraLP3[[#This Row],[Peso Neto UMV (KG)]],0) -> 0 | AF43: NO | AG43: 1 | AH43: 0 | AI43: 0 | AJ43: SI | AK43: NO
A44: EXCLUSIVOS | B44: 104542540 | C44: =+MaestraLP3[[#This Row],[CÓDIGO]]&MaestraLP3[[#Headers],[-]]&MaestraLP3[[#This Row],[UMV]] -> 104542540-1Q | D44: =+MaestraLP3[[#This Row],[CÓDIGO]]&MaestraLP3[[#Headers],[FS00]] -> 104542540FS00 | E44: MARÍA DE LOS ÁNGELES QUIRÓZ | F44: GIORGIO LEVA | G44: SUMINISTROS | H44: DESECHABLES | I44: POTE PAPEL KRAFT BLANCO PLA FILIPPO 4 OZ | J44: 1Q | K44: UN | M44: =VLOOKUP(MaestraLP3[[#This Row],[UMV]],VALIDACIONES!J:L,3,0) -> Caja 1000 Unidades | N44: SECO | O44: NFS | P44: 44000 | Q44: NO PARA LP | R44: 0 | S44: =IFERROR((MaestraLP3[[#This Row],[COSTO ]]/MaestraLP3[[#This Row],[COSTO OCT]]-1),0) -> 0 | T44: CALZADA | U44: CALZADA | V44: =+VLOOKUP(MaestraLP3[[#This Row],[-]],'[1]BD MES'!$A:$N,14,0) -> 44000 | W44: 44000 | X44: =+(MaestraLP3[[#This Row],[COSTO ]]-MaestraLP3[[#This Row],[COSTO OCT AL 27-10]])/MaestraLP3[[#This Row],[COSTO OCT AL 27-10]] -> 0 | Y44: =++IF(Q44="HASTA AGOTAR STOCK","HASTA AGOTAR STOCK",IF(MaestraLP3[[#This Row],[PRECIO OCT]]=0,"NO PARA LP",IF(MaestraLP3[[#This Row],[PRECIO OCT]]=0,"INCORPORACIÓN",IF(AA44=0,"MANTIENE",IF(AA44<0,"BAJA",IF(AA44>0,"ALZA","")))))) -> NO PARA LP | Z44: 0 | AA44: =IF(Z44=0,"INDICAR PRECIO VTA",Z44-MaestraLP3[[#This Row],[PRECIO OCT]]) -> INDICAR PRECIO VTA | AB44: =+IFERROR((Z44-W44)/Z44,"-") -> - | AC44: =IFERROR(MaestraLP3[[#This Row],[PRECIO]]*MaestraLP3[[#This Row],[%MG UMV]],0) -> 0 | AD44: 6 | AE44: =IFERROR(MaestraLP3[[#This Row],[MARGEN UNITARIO]]/MaestraLP3[[#This Row],[Peso Neto UMV (KG)]],0) -> 0 | AF44: NO | AG44: 1 | AH44: 0 | AI44: 0 | AK44: NO
A45: EXCLUSIVOS | B45: 104548330 | C45: =+MaestraLP3[[#This Row],[CÓDIGO]]&MaestraLP3[[#Headers],[-]]&MaestraLP3[[#This Row],[UMV]] -> 104548330-X00 | D45: =+MaestraLP3[[#This Row],[CÓDIGO]]&MaestraLP3[[#Headers],[FS00]] -> 104548330FS00 | E45: MARÍA DE LOS ÁNGELES QUIRÓZ | F45: GIORGIO LEVA | G45: SUMINISTROS | H45: DESECHABLES | I45: TAPA BOWL 1300 CC / 185 MM | J45: X00 | K45: UN | M45: =VLOOKUP(MaestraLP3[[#This Row],[UMV]],VALIDACIONES!J:L,3,0) -> Caja 300 Unidades | N45: SECO | O45: NFS | P45: 22200 | Q45: NO PARA LP | R45: 0 | S45: =IFERROR((MaestraLP3[[#This Row],[COSTO ]]/MaestraLP3[[#This Row],[COSTO OCT]]-1),0) -> 0 | T45: CALZADA | U45: CALZADA | V45: =+VLOOKUP(MaestraLP3[[#This Row],[-]],'[1]BD MES'!$A:$N,14,0) -> 22200 | W45: 22200 | X45: =+(MaestraLP3[[#This Row],[COSTO ]]-MaestraLP3[[#This Row],[COSTO OCT AL 27-10]])/MaestraLP3[[#This Row],[COSTO OCT AL 27-10]] -> 0 | Y45: =++IF(Q45="HASTA AGOTAR STOCK","HASTA AGOTAR STOCK",IF(MaestraLP3[[#This Row],[PRECIO OCT]]=0,"NO PARA LP",IF(MaestraLP3[[#This Row],[PRECIO OCT]]=0,"INCORPORACIÓN",IF(AA45=0,"MANTIENE",IF(AA45<0,"BAJA",IF(AA45>0,"ALZA","")))))) -> NO PARA LP | Z45: 0 | AA45: =IF(Z45=0,"INDICAR PRECIO VTA",Z45-MaestraLP3[[#This Row],[PRECIO OCT]]) -> INDICAR PRECIO VTA | AB45: =+IFERROR((Z45-W45)/Z45,"-") -> - | AC45: =IFERROR(MaestraLP3[[#This Row],[PRECIO]]*MaestraLP3[[#This Row],[%MG UMV]],0) -> 0 | AD45: 3 | AE45: =IFERROR(MaestraLP3[[#This Row],[MARGEN UNITARIO]]/MaestraLP3[[#This Row],[Peso Neto UMV (KG)]],0) -> 0 | AF45: NO | AG45: 1 | AH45: 0 | AI45: 0 | AK45: NO
A46: EXCLUSIVOS | B46: 104548390 | C46: =+MaestraLP3[[#This Row],[CÓDIGO]]&MaestraLP3[[#Headers],[-]]&MaestraLP3[[#This Row],[UMV]] -> 104548390-X00 | D46: =+MaestraLP3[[#This Row],[CÓDIGO]]&MaestraLP3[[#Headers],[FS00]] -> 104548390FS00 | E46: MARÍA DE LOS ÁNGELES QUIRÓZ | F46: GIORGIO LEVA | G46: SUMINISTROS | H46: DESECHABLES | I46: TAPA BOWL PLA 750 ML / 148 MM | J46: X00 | K46: UN | M46: =VLOOKUP(MaestraLP3[[#This Row],[UMV]],VALIDACIONES!J:L,3,0) -> Caja 300 Unidades | N46: SECO | O46: NFS | P46: 14700 | Q46: NO PARA LP | R46: 0 | S46: =IFERROR((MaestraLP3[[#This Row],[COSTO ]]/MaestraLP3[[#This Row],[COSTO OCT]]-1),0) -> 0 | T46: CALZADA | U46: CALZADA | V46: =+VLOOKUP(MaestraLP3[[#This Row],[-]],'[1]BD MES'!$A:$N,14,0) -> 14700 | W46: 14700 | X46: =+(MaestraLP3[[#This Row],[COSTO ]]-MaestraLP3[[#This Row],[COSTO OCT AL 27-10]])/MaestraLP3[[#This Row],[COSTO OCT AL 27-10]] -> 0 | Y46: =++IF(Q46="HASTA AGOTAR STOCK","HASTA AGOTAR STOCK",IF(MaestraLP3[[#This Row],[PRECIO OCT]]=0,"NO PARA LP",IF(MaestraLP3[[#This Row],[PRECIO OCT]]=0,"INCORPORACIÓN",IF(AA46=0,"MANTIENE",IF(AA46<0,"BAJA",IF(AA46>0,"ALZA","")))))) -> NO PARA LP | Z46: 0 | AA46: =IF(Z46=0,"INDICAR PRECIO VTA",Z46-MaestraLP3[[#This Row],[PRECIO OCT]]) -> INDICAR PRECIO VTA | AB46: =+IFERROR((Z46-W46)/Z46,"-") -> - | AC46: =IFERROR(MaestraLP3[[#This Row],[PRECIO]]*MaestraLP3[[#This Row],[%MG UMV]],0) -> 0 | AD46: 3 | AE46: =IFERROR(MaestraLP3[[#This Row],[MARGEN UNITARIO]]/MaestraLP3[[#This Row],[Peso Neto UMV (KG)]],0) -> 0 | AF46: NO | AG46: 1 | AH46: 0 | AI46: 0 | AK46: NO
A47: EXCLUSIVOS | B47: 104542950 | C47: =+MaestraLP3[[#This Row],[CÓDIGO]]&MaestraLP3[[#Headers],[-]]&MaestraLP3[[#This Row],[UMV]] -> 104542950-1Q | D47: =+MaestraLP3[[#This Row],[CÓDIGO]]&MaestraLP3[[#Headers],[FS00]] -> 104542950FS00 | E47: MARÍA DE LOS ÁNGELES QUIRÓZ | F47: GIORGIO LEVA | G47: SUMINISTROS | H47: DESECHABLES | I47: TAPA DOMO PLA TRANSPARENTE 12/16 OZ | J47: 1Q | K47: UN | M47: =VLOOKUP(MaestraLP3[[#This Row],[UMV]],VALIDACIONES!J:L,3,0) -> Caja 1000 Unidades | N47: SECO | O47: NFS | P47: 37100 | Q47: NO PARA LP | R47: 0 | S47: =IFERROR((MaestraLP3[[#This Row],[COSTO ]]/MaestraLP3[[#This Row],[COSTO OCT]]-1),0) -> 0 | T47: CALZADA | U47: CALZADA | V47: =+VLOOKUP(MaestraLP3[[#This Row],[-]],'[1]BD MES'!$A:$N,14,0) -> 37100 | W47: 37100 | X47: =+(MaestraLP3[[#This Row],[COSTO ]]-MaestraLP3[[#This Row],[COSTO OCT AL 27-10]])/MaestraLP3[[#This Row],[COSTO OCT AL 27-10]] -> 0 | Y47: =++IF(Q47="HASTA AGOTAR STOCK","HASTA AGOTAR STOCK",IF(MaestraLP3[[#This Row],[PRECIO OCT]]=0,"NO PARA LP",IF(MaestraLP3[[#This Row],[PRECIO OCT]]=0,"INCORPORACIÓN",IF(AA47=0,"MANTIENE",IF(AA47<0,"BAJA",IF(AA47>0,"ALZA","")))))) -> NO PARA LP | Z47: 0 | AA47: =IF(Z47=0,"INDICAR PRECIO VTA",Z47-MaestraLP3[[#This Row],[PRECIO OCT]]) -> INDICAR PRECIO VTA | AB47: =+IFERROR((Z47-W47)/Z47,"-") -> - | AC47: =IFERROR(MaestraLP3[[#This Row],[PRECIO]]*MaestraLP3[[#This Row],[%MG UMV]],0) -> 0 | AD47: 4 | AE47: =IFERROR(MaestraLP3[[#This Row],[MARGEN UNITARIO]]/MaestraLP3[[#This Row],[Peso Neto UMV (KG)]],0) -> 0 | AF47: NO | AG47: 1 | AH47: 0.07 | AI47: 0.1 | AJ47: SI | AK47: NO
A48: EXCLUSIVOS | B48: 104542960 | C48: =+MaestraLP3[[#This Row],[CÓDIGO]]&MaestraLP3[[#Headers],[-]]&MaestraLP3[[#This Row],[UMV]] -> 104542960-1Q | D48: =+MaestraLP3[[#This Row],[CÓDIGO]]&MaestraLP3[[#Headers],[FS00]] -> 104542960FS00 | E48: MARÍA DE LOS ÁNGELES QUIRÓZ | F48: GIORGIO LEVA | G48: SUMINISTROS | H48: DESECHABLES | I48: TAPA PLANA PLA TRANSPARENTE 12/16 OZ | J48: 1Q | K48: UN | M48: =VLOOKUP(MaestraLP3[[#This Row],[UMV]],VALIDACIONES!J:L,3,0) -> Caja 1000 Unidades | N48: SECO | O48: NFS | P48: 33300 | Q48: NO PARA LP | R48: 0 | S48: =IFERROR((MaestraLP3[[#This Row],[COSTO ]]/MaestraLP3[[#This Row],[COSTO OCT]]-1),0) -> 0 | T48: CALZADA | U48: CALZADA | V48: =+VLOOKUP(MaestraLP3[[#This Row],[-]],'[1]BD MES'!$A:$N,14,0) -> 33300 | W48: 33300 | X48: =+(MaestraLP3[[#This Row],[COSTO ]]-MaestraLP3[[#This Row],[COSTO OCT AL 27-10]])/MaestraLP3[[#This Row],[COSTO OCT AL 27-10]] -> 0 | Y48: =++IF(Q48="HASTA AGOTAR STOCK","HASTA AGOTAR STOCK",IF(MaestraLP3[[#This Row],[PRECIO OCT]]=0,"NO PARA LP",IF(MaestraLP3[[#This Row],[PRECIO OCT]]=0,"INCORPORACIÓN",IF(AA48=0,"MANTIENE",IF(AA48<0,"BAJA",IF(AA48>0,"ALZA","")))))) -> NO PARA LP | Z48: 0 | AA48: =IF(Z48=0,"INDICAR PRECIO VTA",Z48-MaestraLP3[[#This Row],[PRECIO OCT]]) -> INDICAR PRECIO VTA | AB48: =+IFERROR((Z48-W48)/Z48,"-") -> - | AC48: =IFERROR(MaestraLP3[[#This Row],[PRECIO]]*MaestraLP3[[#This Row],[%MG UMV]],0) -> 0 | AD48: 3 | AE48: =IFERROR(MaestraLP3[[#This Row],[MARGEN UNITARIO]]/MaestraLP3[[#This Row],[Peso Neto UMV (KG)]],0) -> 0 | AF48: SI | AG48: 1 | AH48: -0.001 | AI48: 0.1 | AJ48: SI | AK48: NO
A49: EXCLUSIVOS | B49: 104548340 | C49: =+MaestraLP3[[#This Row],[CÓDIGO]]&MaestraLP3[[#Headers],[-]]&MaestraLP3[[#This Row],[UMV]] -> 104548340-V00 | D49: =+MaestraLP3[[#This Row],[CÓDIGO]]&MaestraLP3[[#Headers],[FS00]] -> 104548340FS00 | E49: MARÍA DE LOS ÁNGELES QUIRÓZ | F49: GIORGIO LEVA | G49: SUMINISTROS | H49: DESECHABLES | I49: TAPA POTE PLA 12 OZ /115 MM | J49: V00 | K49: UN | M49: =VLOOKUP(MaestraLP3[[#This Row],[UMV]],VALIDACIONES!J:L,3,0) -> Caja 500 Unidades | N49: SECO | O49: NFS | P49: 30000 | Q49: NO PARA LP | R49: 0 | S49: =IFERROR((MaestraLP3[[#This Row],[COSTO ]]/MaestraLP3[[#This Row],[COSTO OCT]]-1),0) -> 0 | T49: CALZADA | U49: CALZADA | V49: =+VLOOKUP(MaestraLP3[[#This Row],[-]],'[1]BD MES'!$A:$N,14,0) -> 30000 | W49: 30000 | X49: =+(MaestraLP3[[#This Row],[COSTO ]]-MaestraLP3[[#This Row],[COSTO OCT AL 27-10]])/MaestraLP3[[#This Row],[COSTO OCT AL 27-10]] -> 0 | Y49: =++IF(Q49="HASTA AGOTAR STOCK","HASTA AGOTAR STOCK",IF(MaestraLP3[[#This Row],[PRECIO OCT]]=0,"NO PARA LP",IF(MaestraLP3[[#This Row],[PRECIO OCT]]=0,"INCORPORACIÓN",IF(AA49=0,"MANTIENE",IF(AA49<0,"BAJA",IF(AA49>0,"ALZA","")))))) -> NO PARA LP | Z49: 0 | AA49: =IF(Z49=0,"INDICAR PRECIO VTA",Z49-MaestraLP3[[#This Row],[PRECIO OCT]]) -> INDICAR PRECIO VTA | AB49: =+IFERROR((Z49-W49)/Z49,"-") -> - | AC49: =IFERROR(MaestraLP3[[#This Row],[PRECIO]]*MaestraLP3[[#This Row],[%MG UMV]],0) -> 0 | AD49: 0.5 | AE49: =IFERROR(MaestraLP3[[#This Row],[MARGEN UNITARIO]]/MaestraLP3[[#This Row],[Peso Neto UMV (KG)]],0) -> 0 | AF49: NO | AG49: 1 | AH49: 0 | AI49: 0 | AK49: NO
A50: EXCLUSIVOS | B50: 104547120 | C50: =+MaestraLP3[[#This Row],[CÓDIGO]]&MaestraLP3[[#Headers],[-]]&MaestraLP3[[#This Row],[UMV]] -> 104547120-2Q | D50: =+MaestraLP3[[#This Row],[CÓDIGO]]&MaestraLP3[[#Headers],[FS00]] -> 104547120FS00 | E50: MARÍA DE LOS ÁNGELES QUIRÓZ | F50: GIORGIO LEVA | G50: SUMINISTROS | H50: DESECHABLES | I50: TAPA VASO 12 OZ PLATON | J50: 2Q | K50: UN | M50: =VLOOKUP(MaestraLP3[[#This Row],[UMV]],VALIDACIONES!J:L,3,0) -> Caja 2000 Unidades | N50: SECO | O50: NFS | P50: 44000 | Q50: NO PARA LP | R50: 0 | S50: =IFERROR((MaestraLP3[[#This Row],[COSTO ]]/MaestraLP3[[#This Row],[COSTO OCT]]-1),0) -> 0 | T50: CALZADA | U50: CALZADA | V50: =+VLOOKUP(MaestraLP3[[#This Row],[-]],'[1]BD MES'!$A:$N,14,0) -> 44000 | W50: 44000 | X50: =+(MaestraLP3[[#This Row],[COSTO ]]-MaestraLP3[[#This Row],[COSTO OCT AL 27-10]])/MaestraLP3[[#This Row],[COSTO OCT AL 27-10]] -> 0 | Y50: =++IF(Q50="HASTA AGOTAR STOCK","HASTA AGOTAR STOCK",IF(MaestraLP3[[#This Row],[PRECIO OCT]]=0,"NO PARA LP",IF(MaestraLP3[[#This Row],[PRECIO OCT]]=0,"INCORPORACIÓN",IF(AA50=0,"MANTIENE",IF(AA50<0,"BAJA",IF(AA50>0,"ALZA","")))))) -> NO PARA LP | Z50: 0 | AA50: =IF(Z50=0,"INDICAR PRECIO VTA",Z50-MaestraLP3[[#This Row],[PRECIO OCT]]) -> INDICAR PRECIO VTA | AB50: =+IFERROR((Z50-W50)/Z50,"-") -> - | AC50: =IFERROR(MaestraLP3[[#This Row],[PRECIO]]*MaestraLP3[[#This Row],[%MG UMV]],0) -> 0 | AD50: 6 | AE50: =IFERROR(MaestraLP3[[#This Row],[MARGEN UNITARIO]]/MaestraLP3[[#This Row],[Peso Neto UMV (KG)]],0) -> 0 | AF50: NO | AG50: 1 | AH50: 0 | AI50: 0 | AJ50: SI | AK50: NO
A51: EXCLUSIVOS | B51: 104547130 | C51: =+MaestraLP3[[#This Row],[CÓDIGO]]&MaestraLP3[[#Headers],[-]]&MaestraLP3[[#This Row],[UMV]] -> 104547130-2Q | D51: =+MaestraLP3[[#This Row],[CÓDIGO]]&MaestraLP3[[#Headers],[FS00]] -> 104547130FS00 | E51: MARÍA DE LOS ÁNGELES QUIRÓZ | F51: GIORGIO LEVA | G51: SUMINISTROS | H51: DESECHABLES | I51: TAPA VASO 21 OZ PLATON | J51: 2Q | K51: UN | M51: =VLOOKUP(MaestraLP3[[#This Row],[UMV]],VALIDACIONES!J:L,3,0) -> Caja 2000 Unidades | N51: SECO | O51: NFS | P51: 54000 | Q51: NO PARA LP | R51: 0 | S51: =IFERROR((MaestraLP3[[#This Row],[COSTO ]]/MaestraLP3[[#This Row],[COSTO OCT]]-1),0) -> 0 | T51: CALZADA | U51: CALZADA | V51: =+VLOOKUP(MaestraLP3[[#This Row],[-]],'[1]BD MES'!$A:$N,14,0) -> 54000 | W51: 54000 | X51: =+(MaestraLP3[[#This Row],[COSTO ]]-MaestraLP3[[#This Row],[COSTO OCT AL 27-10]])/MaestraLP3[[#This Row],[COSTO OCT AL 27-10]] -> 0 | Y51: =++IF(Q51="HASTA AGOTAR STOCK","HASTA AGOTAR STOCK",IF(MaestraLP3[[#This Row],[PRECIO OCT]]=0,"NO PARA LP",IF(MaestraLP3[[#This Row],[PRECIO OCT]]=0,"INCORPORACIÓN",IF(AA51=0,"MANTIENE",IF(AA51<0,"BAJA",IF(AA51>0,"ALZA","")))))) -> NO PARA LP | Z51: 0 | AA51: =IF(Z51=0,"INDICAR PRECIO VTA",Z51-MaestraLP3[[#This Row],[PRECIO OCT]]) -> INDICAR PRECIO VTA | AB51: =+IFERROR((Z51-W51)/Z51,"-") -> - | AC51: =IFERROR(MaestraLP3[[#This Row],[PRECIO]]*MaestraLP3[[#This Row],[%MG UMV]],0) -> 0 | AD51: 6 | AE51: =IFERROR(MaestraLP3[[#This Row],[MARGEN UNITARIO]]/MaestraLP3[[#This Row],[Peso Neto UMV (KG)]],0) -> 0 | AF51: NO | AG51: 1 | AH51: 0 | AI51: 0 | AJ51: SI | AK51: NO
A52: EXCLUSIVOS | B52: 104541950 | C52: =+MaestraLP3[[#This Row],[CÓDIGO]]&MaestraLP3[[#Headers],[-]]&MaestraLP3[[#This Row],[UMV]] -> 104541950-1Q | D52: =+MaestraLP3[[#This Row],[CÓDIGO]]&MaestraLP3[[#Headers],[FS00]] -> 104541950FS00 | E52: MARÍA DE LOS ÁNGELES QUIRÓZ | F52: GIORGIO LEVA | G52: SUMINISTROS | H52: DESECHABLES | I52: TAPA VASO PLA TRANSPARENTE 16 OZ | J52: 1Q | K52: UN | M52: =VLOOKUP(MaestraLP3[[#This Row],[UMV]],VALIDACIONES!J:L,3,0) -> Caja 1000 Unidades | N52: SECO | O52: NFS | P52: 31000 | Q52: NO PARA LP | R52: 0 | S52: =IFERROR((MaestraLP3[[#This Row],[COSTO ]]/MaestraLP3[[#This Row],[COSTO OCT]]-1),0) -> 0 | T52: CALZADA | U52: CALZADA | V52: =+VLOOKUP(MaestraLP3[[#This Row],[-]],'[1]BD MES'!$A:$N,14,0) -> 31000 | W52: 31000 | X52: =+(MaestraLP3[[#This Row],[COSTO ]]-MaestraLP3[[#This Row],[COSTO OCT AL 27-10]])/MaestraLP3[[#This Row],[COSTO OCT AL 27-10]] -> 0 | Y52: =++IF(Q52="HASTA AGOTAR STOCK","HASTA AGOTAR STOCK",IF(MaestraLP3[[#This Row],[PRECIO OCT]]=0,"NO PARA LP",IF(MaestraLP3[[#This Row],[PRECIO OCT]]=0,"INCORPORACIÓN",IF(AA52=0,"MANTIENE",IF(AA52<0,"BAJA",IF(AA52>0,"ALZA","")))))) -> NO PARA LP | Z52: 0 | AA52: =IF(Z52=0,"INDICAR PRECIO VTA",Z52-MaestraLP3[[#This Row],[PRECIO OCT]]) -> INDICAR PRECIO VTA | AB52: =+IFERROR((Z52-W52)/Z52,"-") -> - | AC52: =IFERROR(MaestraLP3[[#This Row],[PRECIO]]*MaestraLP3[[#This Row],[%MG UMV]],0) -> 0 | AD52: 4 | AE52: =IFERROR(MaestraLP3[[#This Row],[MARGEN UNITARIO]]/MaestraLP3[[#This Row],[Peso Neto UMV (KG)]],0) -> 0 | AF52: NO | AG52: 1 | AH52: 0.07 | AI52: 0.1 | AJ52: SI | AK52: NO
A53: EXCLUSIVOS | B53: 104548400 | C53: =+MaestraLP3[[#This Row],[CÓDIGO]]&MaestraLP3[[#Headers],[-]]&MaestraLP3[[#This Row],[UMV]] -> 104548400-1Q | D53: =+MaestraLP3[[#This Row],[CÓDIGO]]&MaestraLP3[[#Headers],[FS00]] -> 104548400FS00 | E53: MARÍA DE LOS ÁNGELES QUIRÓZ | F53: GIORGIO LEVA | G53: SUMINISTROS | H53: DESECHABLES | I53: TENEDOR PLA | J53: 1Q | K53: UN | M53: =VLOOKUP(MaestraLP3[[#This Row],[UMV]],VALIDACIONES!J:L,3,0) -> Caja 1000 Unidades | N53: SECO | O53: NFS | P53: 19000 | Q53: NO PARA LP | R53: 0 | S53: =IFERROR((MaestraLP3[[#This Row],[COSTO ]]/MaestraLP3[[#This Row],[COSTO OCT]]-1),0) -> 0 | T53: CALZADA | U53: CALZADA | V53: =+VLOOKUP(MaestraLP3[[#This Row],[-]],'[1]BD MES'!$A:$N,14,0) -> 19000 | W53: 19000 | X53: =+(MaestraLP3[[#This Row],[COSTO ]]-MaestraLP3[[#This Row],[COSTO OCT AL 27-10]])/MaestraLP3[[#This Row],[COSTO OCT AL 27-10]] -> 0 | Y53: =++IF(Q53="HASTA AGOTAR STOCK","HASTA AGOTAR STOCK",IF(MaestraLP3[[#This Row],[PRECIO OCT]]=0,"NO PARA LP",IF(MaestraLP3[[#This Row],[PRECIO OCT]]=0,"INCORPORACIÓN",IF(AA53=0,"MANTIENE",IF(AA53<0,"BAJA",IF(AA53>0,"ALZA","")))))) -> NO PARA LP | Z53: 0 | AA53: =IF(Z53=0,"INDICAR PRECIO VTA",Z53-MaestraLP3[[#This Row],[PRECIO OCT]]) -> INDICAR PRECIO VTA | AB53: =+IFERROR((Z53-W53)/Z53,"-") -> - | AC53: =IFERROR(MaestraLP3[[#This Row],[PRECIO]]*MaestraLP3[[#This Row],[%MG UMV]],0) -> 0 | AD53: 10 | AE53: =IFERROR(MaestraLP3[[#This Row],[MARGEN UNITARIO]]/MaestraLP3[[#This Row],[Peso Neto UMV (KG)]],0) -> 0 | AF53: NO | AG53: 1 | AH53: 0 | AI53: 0 | AK53: NO
A54: EXCLUSIVOS | B54: 104545260 | C54: =+MaestraLP3[[#This Row],[CÓDIGO]]&MaestraLP3[[#Headers],[-]]&MaestraLP3[[#This Row],[UMV]] -> 104545260-2Q | D54: =+MaestraLP3[[#This Row],[CÓDIGO]]&MaestraLP3[[#Headers],[FS00]] -> 104545260FS00 | E54: MARÍA DE LOS ÁNGELES QUIRÓZ | F54: GIORGIO LEVA | G54: SUMINISTROS | H54: DESECHABLES | I54: VASO 12 OZ PLATON | J54: 2Q | K54: UN | M54: =VLOOKUP(MaestraLP3[[#This Row],[UMV]],VALIDACIONES!J:L,3,0) -> Caja 2000 Unidades | N54: SECO | O54: NFS | P54: 66000 | Q54: NO PARA LP | R54: 0 | S54: =IFERROR((MaestraLP3[[#This Row],[COSTO ]]/MaestraLP3[[#This Row],[COSTO OCT]]-1),0) -> 0 | T54: CALZADA | U54: CALZADA | V54: =+VLOOKUP(MaestraLP3[[#This Row],[-]],'[1]BD MES'!$A:$N,14,0) -> 66000 | W54: 66000 | X54: =+(MaestraLP3[[#This Row],[COSTO ]]-MaestraLP3[[#This Row],[COSTO OCT AL 27-10]])/MaestraLP3[[#This Row],[COSTO OCT AL 27-10]] -> 0 | Y54: =++IF(Q54="HASTA AGOTAR STOCK","HASTA AGOTAR STOCK",IF(MaestraLP3[[#This Row],[PRECIO OCT]]=0,"NO PARA LP",IF(MaestraLP3[[#This Row],[PRECIO OCT]]=0,"INCORPORACIÓN",IF(AA54=0,"MANTIENE",IF(AA54<0,"BAJA",IF(AA54>0,"ALZA","")))))) -> NO PARA LP | Z54: 0 | AA54: =IF(Z54=0,"INDICAR PRECIO VTA",Z54-MaestraLP3[[#This Row],[PRECIO OCT]]) -> INDICAR PRECIO VTA | AB54: =+IFERROR((Z54-W54)/Z54,"-") -> - | AC54: =IFERROR(MaestraLP3[[#This Row],[PRECIO]]*MaestraLP3[[#This Row],[%MG UMV]],0) -> 0 | AD54: 14 | AE54: =IFERROR(MaestraLP3[[#This Row],[MARGEN UNITARIO]]/MaestraLP3[[#This Row],[Peso Neto UMV (KG)]],0) -> 0 | AF54: NO | AG54: 1 | AH54: 0 | AI54: 0 | AJ54: SI | AK54: NO
A55: EXCLUSIVOS | B55: 104545270 | C55: =+MaestraLP3[[#This Row],[CÓDIGO]]&MaestraLP3[[#Headers],[-]]&MaestraLP3[[#This Row],[UMV]] -> 104545270-1Q | D55: =+MaestraLP3[[#This Row],[CÓDIGO]]&MaestraLP3[[#Headers],[FS00]] -> 104545270FS00 | E55: MARÍA DE LOS ÁNGELES QUIRÓZ | F55: GIORGIO LEVA | G55: SUMINISTROS | H55: DESECHABLES | I55: VASO 21 OZ PLATON | J55: 1Q | K55: UN | M55: =VLOOKUP(MaestraLP3[[#This Row],[UMV]],VALIDACIONES!J:L,3,0) -> Caja 1000 Unidades | N55: SECO | O55: NFS | P55: 50000 | Q55: NO PARA LP | R55: 0 | S55: =IFERROR((MaestraLP3[[#This Row],[COSTO ]]/MaestraLP3[[#This Row],[COSTO OCT]]-1),0) -> 0 | T55: CALZADA | U55: CALZADA | V55: =+VLOOKUP(MaestraLP3[[#This Row],[-]],'[1]BD MES'!$A:$N,14,0) -> 50000 | W55: 50000 | X55: =+(MaestraLP3[[#This Row],[COSTO ]]-MaestraLP3[[#This Row],[COSTO OCT AL 27-10]])/MaestraLP3[[#This Row],[COSTO OCT AL 27-10]] -> 0 | Y55: =++IF(Q55="HASTA AGOTAR STOCK","HASTA AGOTAR STOCK",IF(MaestraLP3[[#This Row],[PRECIO OCT]]=0,"NO PARA LP",IF(MaestraLP3[[#This Row],[PRECIO OCT]]=0,"INCORPORACIÓN",IF(AA55=0,"MANTIENE",IF(AA55<0,"BAJA",IF(AA55>0,"ALZA","")))))) -> NO PARA LP | Z55: 0 | AA55: =IF(Z55=0,"INDICAR PRECIO VTA",Z55-MaestraLP3[[#This Row],[PRECIO OCT]]) -> INDICAR PRECIO VTA | AB55: =+IFERROR((Z55-W55)/Z55,"-") -> - | AC55: =IFERROR(MaestraLP3[[#This Row],[PRECIO]]*MaestraLP3[[#This Row],[%MG UMV]],0) -> 0 | AD55: 12 | AE55: =IFERROR(MaestraLP3[[#This Row],[MARGEN UNITARIO]]/MaestraLP3[[#This Row],[Peso Neto UMV (KG)]],0) -> 0 | AF55: NO | AG55: 1 | AH55: 0 | AI55: 0 | AJ55: SI | AK55: NO
A56: EXCLUSIVOS | B56: 104540520 | C56: =+MaestraLP3[[#This Row],[CÓDIGO]]&MaestraLP3[[#Headers],[-]]&MaestraLP3[[#This Row],[UMV]] -> 104540520-V00 | D56: =+MaestraLP3[[#This Row],[CÓDIGO]]&MaestraLP3[[#Headers],[FS00]] -> 104540520FS00 | E56: MARÍA DE LOS ÁNGELES QUIRÓZ | F56: GIORGIO LEVA | G56: SUMINISTROS | H56: DESECHABLES | I56: VASO D/PARED 12 OZ COMPOSTABLE VILAPERT | J56: V00 | K56: UN | M56: =VLOOKUP(MaestraLP3[[#This Row],[UMV]],VALIDACIONES!J:L,3,0) -> Caja 500 Unidades | N56: SECO | O56: NFS | P56: 49500 | Q56: NO PARA LP | R56: 0 | S56: =IFERROR((MaestraLP3[[#This Row],[COSTO ]]/MaestraLP3[[#This Row],[COSTO OCT]]-1),0) -> 0 | T56: CALZADA | U56: CALZADA | V56: =+VLOOKUP(MaestraLP3[[#This Row],[-]],'[1]BD MES'!$A:$N,14,0) -> 50500 | W56: 49500 | X56: =+(MaestraLP3[[#This Row],[COSTO ]]-MaestraLP3[[#This Row],[COSTO OCT AL 27-10]])/MaestraLP3[[#This Row],[COSTO OCT AL 27-10]] -> -0.01980198 | Y56: =++IF(Q56="HASTA AGOTAR STOCK","HASTA AGOTAR STOCK",IF(MaestraLP3[[#This Row],[PRECIO OCT]]=0,"NO PARA LP",IF(MaestraLP3[[#This Row],[PRECIO OCT]]=0,"INCORPORACIÓN",IF(AA56=0,"MANTIENE",IF(AA56<0,"BAJA",IF(AA56>0,"ALZA","")))))) -> NO PARA LP | Z56: 0 | AA56: =IF(Z56=0,"INDICAR PRECIO VTA",Z56-MaestraLP3[[#This Row],[PRECIO OCT]]) -> INDICAR PRECIO VTA | AB56: =+IFERROR((Z56-W56)/Z56,"-") -> - | AC56: =IFERROR(MaestraLP3[[#This Row],[PRECIO]]*MaestraLP3[[#This Row],[%MG UMV]],0) -> 0 | AD56: 13 | AE56: =IFERROR(MaestraLP3[[#This Row],[MARGEN UNITARIO]]/MaestraLP3[[#This Row],[Peso Neto UMV (KG)]],0) -> 0 | AF56: NO | AG56: 1 | AH56: 0 | AI56: 0 | AJ56: SI | AK56: NO
A57: EXCLUSIVOS | B57: 104540530 | C57: =+MaestraLP3[[#This Row],[CÓDIGO]]&MaestraLP3[[#Headers],[-]]&MaestraLP3[[#This Row],[UMV]] -> 104540530-V00 | D57: =+MaestraLP3[[#This Row],[CÓDIGO]]&MaestraLP3[[#Headers],[FS00]] -> 104540530FS00 | E57: MARÍA DE LOS ÁNGELES QUIRÓZ | F57: GIORGIO LEVA | G57: SUMINISTROS | H57: DESECHABLES | I57: VASO D/PARED 16 OZ COMPOSTABLE VILAPERT | J57: V00 | K57: UN | M57: =VLOOKUP(MaestraLP3[[#This Row],[UMV]],VALIDACIONES!J:L,3,0) -> Caja 500 Unidades | N57: SECO | O57: NFS | P57: 58000 | Q57: NO PARA LP | R57: 0 | S57: =IFERROR((MaestraLP3[[#This Row],[COSTO ]]/MaestraLP3[[#This Row],[COSTO OCT]]-1),0) -> 0 | T57: CALZADA | U57: CALZADA | V57: =+VLOOKUP(MaestraLP3[[#This Row],[-]],'[1]BD MES'!$A:$N,14,0) -> 58000 | W57: 58000 | X57: =+(MaestraLP3[[#This Row],[COSTO ]]-MaestraLP3[[#This Row],[COSTO OCT AL 27-10]])/MaestraLP3[[#This Row],[COSTO OCT AL 27-10]] -> 0 | Y57: =++IF(Q57="HASTA AGOTAR STOCK","HASTA AGOTAR STOCK",IF(MaestraLP3[[#This Row],[PRECIO OCT]]=0,"NO PARA LP",IF(MaestraLP3[[#This Row],[PRECIO OCT]]=0,"INCORPORACIÓN",IF(AA57=0,"MANTIENE",IF(AA57<0,"BAJA",IF(AA57>0,"ALZA","")))))) -> NO PARA LP | Z57: 0 | AA57: =IF(Z57=0,"INDICAR PRECIO VTA",Z57-MaestraLP3[[#This Row],[PRECIO OCT]]) -> INDICAR PRECIO VTA | AB57: =+IFERROR((Z57-W57)/Z57,"-") -> - | AC57: =IFERROR(MaestraLP3[[#This Row],[PRECIO]]*MaestraLP3[[#This Row],[%MG UMV]],0) -> 0 | AD57: 11.5 | AE57: =IFERROR(MaestraLP3[[#This Row],[MARGEN UNITARIO]]/MaestraLP3[[#This Row],[Peso Neto UMV (KG)]],0) -> 0 | AF57: NO | AG57: 1 | AH57: 0 | AI57: 0 | AJ57: SI | AK57: NO
A58: EXCLUSIVOS | B58: 104540510 | C58: =+MaestraLP3[[#This Row],[CÓDIGO]]&MaestraLP3[[#Headers],[-]]&MaestraLP3[[#This Row],[UMV]] -> 104540510-V00 | D58: =+MaestraLP3[[#This Row],[CÓDIGO]]&MaestraLP3[[#Headers],[FS00]] -> 104540510FS00 | E58: MARÍA DE LOS ÁNGELES QUIRÓZ | F58: GIORGIO LEVA | G58: SUMINISTROS | H58: DESECHABLES | I58: VASO D/PARED 8 OZ COMPOSTABLE VILAPERT | J58: V00 | K58: UN | M58: =VLOOKUP(MaestraLP3[[#This Row],[UMV]],VALIDACIONES!J:L,3,0) -> Caja 500 Unidades | N58: SECO | O58: NFS | P58: 40500 | Q58: NO PARA LP | R58: 0 | S58: =IFERROR((MaestraLP3[[#This Row],[COSTO ]]/MaestraLP3[[#This Row],[COSTO OCT]]-1),0) -> 0 | T58: CALZADA | U58: CALZADA | V58: =+VLOOKUP(MaestraLP3[[#This Row],[-]],'[1]BD MES'!$A:$N,14,0) -> 41500 | W58: 40500 | X58: =+(MaestraLP3[[#This Row],[COSTO ]]-MaestraLP3[[#This Row],[COSTO OCT AL 27-10]])/MaestraLP3[[#This Row],[COSTO OCT AL 27-10]] -> -0.024096386 | Y58: =++IF(Q58="HASTA AGOTAR STOCK","HASTA AGOTAR STOCK",IF(MaestraLP3[[#This Row],[PRECIO OCT]]=0,"NO PARA LP",IF(MaestraLP3[[#This Row],[PRECIO OCT]]=0,"INCORPORACIÓN",IF(AA58=0,"MANTIENE",IF(AA58<0,"BAJA",IF(AA58>0,"ALZA","")))))) -> NO PARA LP | Z58: 0 | AA58: =IF(Z58=0,"INDICAR PRECIO VTA",Z58-MaestraLP3[[#This Row],[PRECIO OCT]]) -> INDICAR PRECIO VTA | AB58: =+IFERROR((Z58-W58)/Z58,"-") -> - | AC58: =IFERROR(MaestraLP3[[#This Row],[PRECIO]]*MaestraLP3[[#This Row],[%MG UMV]],0) -> 0 | AD58: 13 | AE58: =IFERROR(MaestraLP3[[#This Row],[MARGEN UNITARIO]]/MaestraLP3[[#This Row],[Peso Neto UMV (KG)]],0) -> 0 | AF58: NO | AG58: 1 | AH58: 0 | AI58: 0 | AJ58: SI | AK58: NO
A59: EXCLUSIVOS | B59: 104542990 | C59: =+MaestraLP3[[#This Row],[CÓDIGO]]&MaestraLP3[[#Headers],[-]]&MaestraLP3[[#This Row],[UMV]] -> 104542990-V00 | D59: =+MaestraLP3[[#This Row],[CÓDIGO]]&MaestraLP3[[#Headers],[FS00]] -> 104542990FS00 | E59: MARÍA DE LOS ÁNGELES QUIRÓZ | F59: GIORGIO LEVA | G59: SUMINISTROS | H59: DESECHABLES | I59: VASO D/PARED COMPOSTABLE CESTSIBON 12 OZ | J59: V00 | K59: UN | M59: =VLOOKUP(MaestraLP3[[#This Row],[UMV]],VALIDACIONES!J:L,3,0) -> Caja 500 Unidades | N59: SECO | O59: NFS | P59: 36500 | Q59: NO PARA LP | R59: 0 | S59: =IFERROR((MaestraLP3[[#This Row],[COSTO ]]/MaestraLP3[[#This Row],[COSTO OCT]]-1),0) -> 0 | T59: CALZADA | U59: CALZADA | V59: =+VLOOKUP(MaestraLP3[[#This Row],[-]],'[1]BD MES'!$A:$N,14,0) -> 36500 | W59: 36500 | X59: =+(MaestraLP3[[#This Row],[COSTO ]]-MaestraLP3[[#This Row],[COSTO OCT AL 27-10]])/MaestraLP3[[#This Row],[COSTO OCT AL 27-10]] -> 0 | Y59: =++IF(Q59="HASTA AGOTAR STOCK","HASTA AGOTAR STOCK",IF(MaestraLP3[[#This Row],[PRECIO OCT]]=0,"NO PARA LP",IF(MaestraLP3[[#This Row],[PRECIO OCT]]=0,"INCORPORACIÓN",IF(AA59=0,"MANTIENE",IF(AA59<0,"BAJA",IF(AA59>0,"ALZA","")))))) -> NO PARA LP | Z59: 0 | AA59: =IF(Z59=0,"INDICAR PRECIO VTA",Z59-MaestraLP3[[#This Row],[PRECIO OCT]]) -> INDICAR PRECIO VTA | AB59: =+IFERROR((Z59-W59)/Z59,"-") -> - | AC59: =IFERROR(MaestraLP3[[#This Row],[PRECIO]]*MaestraLP3[[#This Row],[%MG UMV]],0) -> 0 | AD59: 9 | AE59: =IFERROR(MaestraLP3[[#This Row],[MARGEN UNITARIO]]/MaestraLP3[[#This Row],[Peso Neto UMV (KG)]],0) -> 0 | AF59: NO | AG59: 1 | AH59: 0 | AI59: 0 | AK59: NO
A60: EXCLUSIVOS | B60: 104542980 | C60: =+MaestraLP3[[#This Row],[CÓDIGO]]&MaestraLP3[[#Headers],[-]]&MaestraLP3[[#This Row],[UMV]] -> 104542980-V00 | D60: =+MaestraLP3[[#This Row],[CÓDIGO]]&MaestraLP3[[#Headers],[FS00]] -> 104542980FS00 | E60: MARÍA DE LOS ÁNGELES QUIRÓZ | F60: GIORGIO LEVA | G60: SUMINISTROS | H60: DESECHABLES | I60: VASO D/PARED COMPOSTABLE CESTSIBON 8 OZ | J60: V00 | K60: UN | M60: =VLOOKUP(MaestraLP3[[#This Row],[UMV]],VALIDACIONES!J:L,3,0) -> Caja 500 Unidades | N60: SECO | O60: NFS | P60: 29000 | Q60: NO PARA LP | R60: 0 | S60: =IFERROR((MaestraLP3[[#This Row],[COSTO ]]/MaestraLP3[[#This Row],[COSTO OCT]]-1),0) -> 0 | T60: CALZADA | U60: CALZADA | V60: =+VLOOKUP(MaestraLP3[[#This Row],[-]],'[1]BD MES'!$A:$N,14,0) -> 29000 | W60: 29000 | X60: =+(MaestraLP3[[#This Row],[COSTO ]]-MaestraLP3[[#This Row],[COSTO OCT AL 27-10]])/MaestraLP3[[#This Row],[COSTO OCT AL 27-10]] -> 0 | Y60: =++IF(Q60="HASTA AGOTAR STOCK","HASTA AGOTAR STOCK",IF(MaestraLP3[[#This Row],[PRECIO OCT]]=0,"NO PARA LP",IF(MaestraLP3[[#This Row],[PRECIO OCT]]=0,"INCORPORACIÓN",IF(AA60=0,"MANTIENE",IF(AA60<0,"BAJA",IF(AA60>0,"ALZA","")))))) -> NO PARA LP | Z60: 0 | AA60: =IF(Z60=0,"INDICAR PRECIO VTA",Z60-MaestraLP3[[#This Row],[PRECIO OCT]]) -> INDICAR PRECIO VTA | AB60: =+IFERROR((Z60-W60)/Z60,"-") -> - | AC60: =IFERROR(MaestraLP3[[#This Row],[PRECIO]]*MaestraLP3[[#This Row],[%MG UMV]],0) -> 0 | AD60: 7 | AE60: =IFERROR(MaestraLP3[[#This Row],[MARGEN UNITARIO]]/MaestraLP3[[#This Row],[Peso Neto UMV (KG)]],0) -> 0 | AF60: NO | AG60: 1 | AH60: 0 | AI60: 0 | AK60: NO
A61: EXCLUSIVOS | B61: 104542550 | C61: =+MaestraLP3[[#This Row],[CÓDIGO]]&MaestraLP3[[#Headers],[-]]&MaestraLP3[[#This Row],[UMV]] -> 104542550-1Q | D61: =+MaestraLP3[[#This Row],[CÓDIGO]]&MaestraLP3[[#Headers],[FS00]] -> 104542550FS00 | E61: MARÍA DE LOS ÁNGELES QUIRÓZ | F61: GIORGIO LEVA | G61: SUMINISTROS | H61: DESECHABLES | I61: VASO D/PARED COMPOSTABLE FILIPPO 6 OZ | J61: 1Q | K61: UN | M61: =VLOOKUP(MaestraLP3[[#This Row],[UMV]],VALIDACIONES!J:L,3,0) -> Caja 1000 Unidades | N61: SECO | O61: NFS | P61: 35000 | Q61: NO PARA LP | R61: 0 | S61: =IFERROR((MaestraLP3[[#This Row],[COSTO ]]/MaestraLP3[[#This Row],[COSTO OCT]]-1),0) -> 0 | T61: CALZADA | U61: CALZADA | V61: =+VLOOKUP(MaestraLP3[[#This Row],[-]],'[1]BD MES'!$A:$N,14,0) -> 35000 | W61: 35000 | X61: =+(MaestraLP3[[#This Row],[COSTO ]]-MaestraLP3[[#This Row],[COSTO OCT AL 27-10]])/MaestraLP3[[#This Row],[COSTO OCT AL 27-10]] -> 0 | Y61: =++IF(Q61="HASTA AGOTAR STOCK","HASTA AGOTAR STOCK",IF(MaestraLP3[[#This Row],[PRECIO OCT]]=0,"NO PARA LP",IF(MaestraLP3[[#This Row],[PRECIO OCT]]=0,"INCORPORACIÓN",IF(AA61=0,"MANTIENE",IF(AA61<0,"BAJA",IF(AA61>0,"ALZA","")))))) -> NO PARA LP | Z61: 0 | AA61: =IF(Z61=0,"INDICAR PRECIO VTA",Z61-MaestraLP3[[#This Row],[PRECIO OCT]]) -> INDICAR PRECIO VTA | AB61: =+IFERROR((Z61-W61)/Z61,"-") -> - | AC61: =IFERROR(MaestraLP3[[#This Row],[PRECIO]]*MaestraLP3[[#This Row],[%MG UMV]],0) -> 0 | AD61: 6 | AE61: =IFERROR(MaestraLP3[[#This Row],[MARGEN UNITARIO]]/MaestraLP3[[#This Row],[Peso Neto UMV (KG)]],0) -> 0 | AF61: NO | AG61: 1 | AH61: 0 | AI61: 0 | AK61: NO
A62: EXCLUSIVOS | B62: 104544300 | C62: =+MaestraLP3[[#This Row],[CÓDIGO]]&MaestraLP3[[#Headers],[-]]&MaestraLP3[[#This Row],[UMV]] -> 104544300-V00 | D62: =+MaestraLP3[[#This Row],[CÓDIGO]]&MaestraLP3[[#Headers],[FS00]] -> 104544300FS00 | E62: MARÍA DE LOS ÁNGELES QUIRÓZ | F62: GIORGIO LEVA | G62: SUMINISTROS | H62: DESECHABLES | I62: VASO D/PARED COMPOSTABLE FILIPPO 6 OZ | J62: V00 | K62: UN | M62: =VLOOKUP(MaestraLP3[[#This Row],[UMV]],VALIDACIONES!J:L,3,0) -> Caja 500 Unidades | N62: SECO | O62: NFS | P62: 17500 | Q62: NO PARA LP | R62: 0 | S62: =IFERROR((MaestraLP3[[#This Row],[COSTO ]]/MaestraLP3[[#This Row],[COSTO OCT]]-1),0) -> 0 | T62: CALZADA | U62: CALZADA | V62: =+VLOOKUP(MaestraLP3[[#This Row],[-]],'[1]BD MES'!$A:$N,14,0) -> 17500 | W62: 17500 | X62: =+(MaestraLP3[[#This Row],[COSTO ]]-MaestraLP3[[#This Row],[COSTO OCT AL 27-10]])/MaestraLP3[[#This Row],[COSTO OCT AL 27-10]] -> 0 | Y62: =++IF(Q62="HASTA AGOTAR STOCK","HASTA AGOTAR STOCK",IF(MaestraLP3[[#This Row],[PRECIO OCT]]=0,"NO PARA LP",IF(MaestraLP3[[#This Row],[PRECIO OCT]]=0,"INCORPORACIÓN",IF(AA62=0,"MANTIENE",IF(AA62<0,"BAJA",IF(AA62>0,"ALZA","")))))) -> NO PARA LP | Z62: 0 | AA62: =IF(Z62=0,"INDICAR PRECIO VTA",Z62-MaestraLP3[[#This Row],[PRECIO OCT]]) -> INDICAR PRECIO VTA | AB62: =+IFERROR((Z62-W62)/Z62,"-") -> - | AC62: =IFERROR(MaestraLP3[[#This Row],[PRECIO]]*MaestraLP3[[#This Row],[%MG UMV]],0) -> 0 | AD62: 3 | AE62: =IFERROR(MaestraLP3[[#This Row],[MARGEN UNITARIO]]/MaestraLP3[[#This Row],[Peso Neto UMV (KG)]],0) -> 0 | AF62: NO | AG62: 1 | AH62: 0 | AI62: 0 | AK62: NO
A63: EXCLUSIVOS | B63: 104541960 | C63: =+MaestraLP3[[#This Row],[CÓDIGO]]&MaestraLP3[[#Headers],[-]]&MaestraLP3[[#This Row],[UMV]] -> 104541960-1Q | D63: =+MaestraLP3[[#This Row],[CÓDIGO]]&MaestraLP3[[#Headers],[FS00]] -> 104541960FS00 | E63: MARÍA DE LOS ÁNGELES QUIRÓZ | F63: GIORGIO LEVA | G63: SUMINISTROS | H63: DESECHABLES | I63: VASO PLA COMPOSTABLE PRETZEELS 12 OZ | J63: 1Q | K63: UN | M63: =VLOOKUP(MaestraLP3[[#This Row],[UMV]],VALIDACIONES!J:L,3,0) -> Caja 1000 Unidades | N63: SECO | O63: NFS | P63: 55000 | Q63: NO PARA LP | R63: 0 | S63: =IFERROR((MaestraLP3[[#This Row],[COSTO ]]/MaestraLP3[[#This Row],[COSTO OCT]]-1),0) -> 0 | T63: CALZADA | U63: CALZADA | V63: =+VLOOKUP(MaestraLP3[[#This Row],[-]],'[1]BD MES'!$A:$N,14,0) -> 55000 | W63: 55000 | X63: =+(MaestraLP3[[#This Row],[COSTO ]]-MaestraLP3[[#This Row],[COSTO OCT AL 27-10]])/MaestraLP3[[#This Row],[COSTO OCT AL 27-10]] -> 0 | Y63: =++IF(Q63="HASTA AGOTAR STOCK","HASTA AGOTAR STOCK",IF(MaestraLP3[[#This Row],[PRECIO OCT]]=0,"NO PARA LP",IF(MaestraLP3[[#This Row],[PRECIO OCT]]=0,"INCORPORACIÓN",IF(AA63=0,"MANTIENE",IF(AA63<0,"BAJA",IF(AA63>0,"ALZA","")))))) -> NO PARA LP | Z63: 0 | AA63: =IF(Z63=0,"INDICAR PRECIO VTA",Z63-MaestraLP3[[#This Row],[PRECIO OCT]]) -> INDICAR PRECIO VTA | AB63: =+IFERROR((Z63-W63)/Z63,"-") -> - | AC63: =IFERROR(MaestraLP3[[#This Row],[PRECIO]]*MaestraLP3[[#This Row],[%MG UMV]],0) -> 0 | AD63: 12 | AE63: =IFERROR(MaestraLP3[[#This Row],[MARGEN UNITARIO]]/MaestraLP3[[#This Row],[Peso Neto UMV (KG)]],0) -> 0 | AF63: NO | AG63: 1 | AH63: 0 | AI63: 0 | AJ63: SI | AK63: NO
A64: EXCLUSIVOS | B64: 104541970 | C64: =+MaestraLP3[[#This Row],[CÓDIGO]]&MaestraLP3[[#Headers],[-]]&MaestraLP3[[#This Row],[UMV]] -> 104541970-1Q | D64: =+MaestraLP3[[#This Row],[CÓDIGO]]&MaestraLP3[[#Headers],[FS00]] -> 104541970FS00 | E64: MARÍA DE LOS ÁNGELES QUIRÓZ | F64: GIORGIO LEVA | G64: SUMINISTROS | H64: DESECHABLES | I64: VASO PLA TRANS/COMP YOGEN FRUZ 16 OZ | J64: 1Q | K64: UN | M64: =VLOOKUP(MaestraLP3[[#This Row],[UMV]],VALIDACIONES!J:L,3,0) -> Caja 1000 Unidades | N64: SECO | O64: NFS | P64: 134000 | Q64: NO PARA LP | R64: 0 | S64: =IFERROR((MaestraLP3[[#This Row],[COSTO ]]/MaestraLP3[[#This Row],[COSTO OCT]]-1),0) -> 0 | T64: CALZADA | U64: CALZADA | V64: =+VLOOKUP(MaestraLP3[[#This Row],[-]],'[1]BD MES'!$A:$N,14,0) -> 134000 | W64: 134000 | X64: =+(MaestraLP3[[#This Row],[COSTO ]]-MaestraLP3[[#This Row],[COSTO OCT AL 27-10]])/MaestraLP3[[#This Row],[COSTO OCT AL 27-10]] -> 0 | Y64: =++IF(Q64="HASTA AGOTAR STOCK","HASTA AGOTAR STOCK",IF(MaestraLP3[[#This Row],[PRECIO OCT]]=0,"NO PARA LP",IF(MaestraLP3[[#This Row],[PRECIO OCT]]=0,"INCORPORACIÓN",IF(AA64=0,"MANTIENE",IF(AA64<0,"BAJA",IF(AA64>0,"ALZA","")))))) -> NO PARA LP | Z64: 0 | AA64: =IF(Z64=0,"INDICAR PRECIO VTA",Z64-MaestraLP3[[#This Row],[PRECIO OCT]]) -> INDICAR PRECIO VTA | AB64: =+IFERROR((Z64-W64)/Z64,"-") -> - | AC64: =IFERROR(MaestraLP3[[#This Row],[PRECIO]]*MaestraLP3[[#This Row],[%MG UMV]],0) -> 0 | AD64: 13 | AE64: =IFERROR(MaestraLP3[[#This Row],[MARGEN UNITARIO]]/MaestraLP3[[#This Row],[Peso Neto UMV (KG)]],0) -> 0 | AF64: NO | AG64: 1 | AH64: 0 | AI64: 0 | AJ64: SI | AK64: NO
A65: EXCLUSIVOS | B65: 104542970 | C65: =+MaestraLP3[[#This Row],[CÓDIGO]]&MaestraLP3[[#Headers],[-]]&MaestraLP3[[#This Row],[UMV]] -> 104542970-1Q | D65: =+MaestraLP3[[#This Row],[CÓDIGO]]&MaestraLP3[[#Headers],[FS00]] -> 104542970FS00 | E65: MARÍA DE LOS ÁNGELES QUIRÓZ | F65: GIORGIO LEVA | G65: SUMINISTROS | H65: DESECHABLES | I65: VASO PLA TRANSPARENTE CESTSIBON 12 OZ | J65: 1Q | K65: UN | M65: =VLOOKUP(MaestraLP3[[#This Row],[UMV]],VALIDACIONES!J:L,3,0) -> Caja 1000 Unidades | N65: SECO | O65: NFS | P65: 90900 | Q65: NO PARA LP | R65: 0 | S65: =IFERROR((MaestraLP3[[#This Row],[COSTO ]]/MaestraLP3[[#This Row],[COSTO OCT]]-1),0) -> 0 | T65: CALZADA | U65: CALZADA | V65: =+VLOOKUP(MaestraLP3[[#This Row],[-]],'[1]BD MES'!$A:$N,14,0) -> 90900 | W65: 90900 | X65: =+(MaestraLP3[[#This Row],[COSTO ]]-MaestraLP3[[#This Row],[COSTO OCT AL 27-10]])/MaestraLP3[[#This Row],[COSTO OCT AL 27-10]] -> 0 | Y65: =++IF(Q65="HASTA AGOTAR STOCK","HASTA AGOTAR STOCK",IF(MaestraLP3[[#This Row],[PRECIO OCT]]=0,"NO PARA LP",IF(MaestraLP3[[#This Row],[PRECIO OCT]]=0,"INCORPORACIÓN",IF(AA65=0,"MANTIENE",IF(AA65<0,"BAJA",IF(AA65>0,"ALZA","")))))) -> NO PARA LP | Z65: 0 | AA65: =IF(Z65=0,"INDICAR PRECIO VTA",Z65-MaestraLP3[[#This Row],[PRECIO OCT]]) -> INDICAR PRECIO VTA | AB65: =+IFERROR((Z65-W65)/Z65,"-") -> - | AC65: =IFERROR(MaestraLP3[[#This Row],[PRECIO]]*MaestraLP3[[#This Row],[%MG UMV]],0) -> 0 | AD65: 10 | AE65: =IFERROR(MaestraLP3[[#This Row],[MARGEN UNITARIO]]/MaestraLP3[[#This Row],[Peso Neto UMV (KG)]],0) -> 0 | AF65: NO | AG65: 1 | AH65: 0 | AI65: 0 | AK65: NO
A66: EXCLUSIVOS | B66: 104542940 | C66: =+MaestraLP3[[#This Row],[CÓDIGO]]&MaestraLP3[[#Headers],[-]]&MaestraLP3[[#This Row],[UMV]] -> 104542940-1Q | D66: =+MaestraLP3[[#This Row],[CÓDIGO]]&MaestraLP3[[#Headers],[FS00]] -> 104542940FS00 | E66: MARÍA DE LOS ÁNGELES QUIRÓZ | F66: GIORGIO LEVA | G66: SUMINISTROS | H66: DESECHABLES | I66: VASO PLA TRANSPARENTE CESTSIBON 16 OZ | J66: 1Q | K66: UN | M66: =VLOOKUP(MaestraLP3[[#This Row],[UMV]],VALIDACIONES!J:L,3,0) -> Caja 1000 Unidades | N66: SECO | O66: NFS | P66: 101100 | Q66: NO PARA LP | R66: 0 | S66: =IFERROR((MaestraLP3[[#This Row],[COSTO ]]/MaestraLP3[[#This Row],[COSTO OCT]]-1),0) -> 0 | T66: CALZADA | U66: CALZADA | V66: =+VLOOKUP(MaestraLP3[[#This Row],[-]],'[1]BD MES'!$A:$N,14,0) -> 101100 | W66: 101100 | X66: =+(MaestraLP3[[#This Row],[COSTO ]]-MaestraLP3[[#This Row],[COSTO OCT AL 27-10]])/MaestraLP3[[#This Row],[COSTO OCT AL 27-10]] -> 0 | Y66: =++IF(Q66="HASTA AGOTAR STOCK","HASTA AGOTAR STOCK",IF(MaestraLP3[[#This Row],[PRECIO OCT]]=0,"NO PARA LP",IF(MaestraLP3[[#This Row],[PRECIO OCT]]=0,"INCORPORACIÓN",IF(AA66=0,"MANTIENE",IF(AA66<0,"BAJA",IF(AA66>0,"ALZA","")))))) -> NO PARA LP | Z66: 0 | AA66: =IF(Z66=0,"INDICAR PRECIO VTA",Z66-MaestraLP3[[#This Row],[PRECIO OCT]]) -> INDICAR PRECIO VTA | AB66: =+IFERROR((Z66-W66)/Z66,"-") -> - | AC66: =IFERROR(MaestraLP3[[#This Row],[PRECIO]]*MaestraLP3[[#This Row],[%MG UMV]],0) -> 0 | AD66: 12 | AE66: =IFERROR(MaestraLP3[[#This Row],[MARGEN UNITARIO]]/MaestraLP3[[#This Row],[Peso Neto UMV (KG)]],0) -> 0 | AF66: NO | AG66: 1 | AH66: -0.001 | AI66: 0 | AK66: NO
A67: EXCLUSIVOS | B67: 104547430 | C67: =+MaestraLP3[[#This Row],[CÓDIGO]]&MaestraLP3[[#Headers],[-]]&MaestraLP3[[#This Row],[UMV]] -> 104547430-UN | D67: =+MaestraLP3[[#This Row],[CÓDIGO]]&MaestraLP3[[#Headers],[FS00]] -> 104547430FS00 | E67: MARÍA DE LOS ÁNGELES QUIRÓZ | F67: GIORGIO LEVA | G67: SUMINISTROS | H67: DISPENSADORES | I67: DISPENSADOR MANUAL NUTELLA 3KG | J67: UN | K67: UN | M67: =VLOOKUP(MaestraLP3[[#This Row],[UMV]],VALIDACIONES!J:L,3,0) -> Unidad | N67: SECO | O67: IFS | P67: 292358 | Q67: NO PARA LP | R67: 0 | S67: =IFERROR((MaestraLP3[[#This Row],[COSTO ]]/MaestraLP3[[#This Row],[COSTO OCT]]-1),0) -> 0 | T67: CALZADA | U67: CALZADA | V67: =+VLOOKUP(MaestraLP3[[#This Row],[-]],'[1]BD MES'!$A:$N,14,0) -> 292358 | W67: 292358 | X67: =+(MaestraLP3[[#This Row],[COSTO ]]-MaestraLP3[[#This Row],[COSTO OCT AL 27-10]])/MaestraLP3[[#This Row],[COSTO OCT AL 27-10]] -> 0 | Y67: =++IF(Q67="HASTA AGOTAR STOCK","HASTA AGOTAR STOCK",IF(MaestraLP3[[#This Row],[PRECIO OCT]]=0,"NO PARA LP",IF(MaestraLP3[[#This Row],[PRECIO OCT]]=0,"INCORPORACIÓN",IF(AA67=0,"MANTIENE",IF(AA67<0,"BAJA",IF(AA67>0,"ALZA","")))))) -> NO PARA LP | Z67: 0 | AA67: =IF(Z67=0,"INDICAR PRECIO VTA",Z67-MaestraLP3[[#This Row],[PRECIO OCT]]) -> INDICAR PRECIO VTA | AB67: =+IFERROR((Z67-W67)/Z67,"-") -> - | AC67: =IFERROR(MaestraLP3[[#This Row],[PRECIO]]*MaestraLP3[[#This Row],[%MG UMV]],0) -> 0 | AD67: 4.2 | AE67: =IFERROR(MaestraLP3[[#This Row],[MARGEN UNITARIO]]/MaestraLP3[[#This Row],[Peso Neto UMV (KG)]],0) -> 0 | AF67: NO | AG67: 1 | AH67: 0 | AI67: 0 | AK67: NO
A68: EXCLUSIVOS | B68: 104533810 | C68: =+MaestraLP3[[#This Row],[CÓDIGO]]&MaestraLP3[[#Headers],[-]]&MaestraLP3[[#This Row],[UMV]] -> 104533810-KG | D68: =+MaestraLP3[[#This Row],[CÓDIGO]]&MaestraLP3[[#Headers],[FS00]] -> 104533810FS00 | E68: MYRIAM GARIN | F68: CAROLINA SAN MARTÍN | G68: CERDO | H68: CHULETA | I68: TROZO CHULETA DE CERDO CJ 5 KG | J68: KG | K68: KG | M68: =VLOOKUP(MaestraLP3[[#This Row],[UMV]],VALIDACIONES!J:L,3,0) -> Kilogramo | N68: CONGELADOS | O68: NFS | P68: 200 | Q68: MANTIENE | R68: 1290 | S68: =IFERROR((MaestraLP3[[#This Row],[COSTO ]]/MaestraLP3[[#This Row],[COSTO OCT]]-1),0) -> 0 | T68: ACTIVO (M) | V68: =+VLOOKUP(MaestraLP3[[#This Row],[-]],'[1]BD MES'!$A:$N,14,0) -> 200 | W68: 200 | X68: =+(MaestraLP3[[#This Row],[COSTO ]]-MaestraLP3[[#This Row],[COSTO OCT AL 27-10]])/MaestraLP3[[#This Row],[COSTO OCT AL 27-10]] -> 0 | Y68: =++IF(Q68="HASTA AGOTAR STOCK","HASTA AGOTAR STOCK",IF(MaestraLP3[[#This Row],[PRECIO OCT]]=0,"NO PARA LP",IF(MaestraLP3[[#This Row],[PRECIO OCT]]=0,"INCORPORACIÓN",IF(AA68=0,"MANTIENE",IF(AA68<0,"BAJA",IF(AA68>0,"ALZA","")))))) -> MANTIENE | Z68: 1290 | AA68: =IF(Z68=0,"INDICAR PRECIO VTA",Z68-MaestraLP3[[#This Row],[PRECIO OCT]]) -> 0 | AB68: =+IFERROR((Z68-W68)/Z68,"-") -> 0.84496124 | AC68: =IFERROR(MaestraLP3[[#This Row],[PRECIO]]*MaestraLP3[[#This Row],[%MG UMV]],0) -> 1090 | AD68: 1 | AE68: =IFERROR(MaestraLP3[[#This Row],[MARGEN UNITARIO]]/MaestraLP3[[#This Row],[Peso Neto UMV (KG)]],0) -> 1090 | AF68: NO | AG68: 1 | AH68: 0.05 | AI68: 0.08 | AK68: NO
A69: EXCLUSIVOS | B69: 104547530 | C69: =+MaestraLP3[[#This Row],[CÓDIGO]]&MaestraLP3[[#Headers],[-]]&MaestraLP3[[#This Row],[UMV]] -> 104547530-KG | D69: =+MaestraLP3[[#This Row],[CÓDIGO]]&MaestraLP3[[#Headers],[FS00]] -> 104547530FS00 | E69: MYRIAM GARIN | F69: PAZ CARO | G69: HAMBURGUESAS | H69: HAMBURGUESAS CERTIFICADAS | I69: HAMBURGUESA CAB FLOWPACK | J69: KG | K69: KG | M69: =VLOOKUP(MaestraLP3[[#This Row],[UMV]],VALIDACIONES!J:L,3,0) -> Kilogramo | N69: CONGELADOS | O69: NFS | P69: 8315 | Q69: MANTIENE | R69: 10690 | S69: =IFERROR((MaestraLP3[[#This Row],[COSTO ]]/MaestraLP3[[#This Row],[COSTO OCT]]-1),0) -> 0 | T69: ACTIVO (M) | V69: =+VLOOKUP(MaestraLP3[[#This Row],[-]],'[1]BD MES'!$A:$N,14,0) -> 8315 | W69: 8315 | X69: =+(MaestraLP3[[#This Row],[COSTO ]]-MaestraLP3[[#This Row],[COSTO OCT AL 27-10]])/MaestraLP3[[#This Row],[COSTO OCT AL 27-10]] -> 0 | Y69: =++IF(Q69="HASTA AGOTAR STOCK","HASTA AGOTAR STOCK",IF(MaestraLP3[[#This Row],[PRECIO OCT]]=0,"NO PARA LP",IF(MaestraLP3[[#This Row],[PRECIO OCT]]=0,"INCORPORACIÓN",IF(AA69=0,"MANTIENE",IF(AA69<0,"BAJA",IF(AA69>0,"ALZA","")))))) -> MANTIENE | Z69: 10690 | AA69: =IF(Z69=0,"INDICAR PRECIO VTA",Z69-MaestraLP3[[#This Row],[PRECIO OCT]]) -> 0 | AB69: =+IFERROR((Z69-W69)/Z69,"-") -> 0.22217025 | AC69: =IFERROR(MaestraLP3[[#This Row],[PRECIO]]*MaestraLP3[[#This Row],[%MG UMV]],0) -> 2375 | AD69: 1 | AE69: =IFERROR(MaestraLP3[[#This Row],[MARGEN UNITARIO]]/MaestraLP3[[#This Row],[Peso Neto UMV (KG)]],0) -> 2375 | AF69: NO | AG69: 1 | AH69: 0.03 | AI69: 0.05 | AJ69: SI | AK69: NO
A70: EXCLUSIVOS | B70: 104542640 | C70: =+MaestraLP3[[#This Row],[CÓDIGO]]&MaestraLP3[[#Headers],[-]]&MaestraLP3[[#This Row],[UMV]] -> 104542640-C12 | D70: =+MaestraLP3[[#This Row],[CÓDIGO]]&MaestraLP3[[#Headers],[FS00]] -> 104542640FS00 | E70: MYRIAM GARIN | F70: PAZ CARO | G70: HAMBURGUESAS | H70: HAMBURGUESAS CERTIFICADAS | I70: MOLIDA VACUNO 80/20 CAB 3 LBS | J70: C12 | K70: UN | M70: =VLOOKUP(MaestraLP3[[#This Row],[UMV]],VALIDACIONES!J:L,3,0) -> Caja 12 Unidades | N70: CONGELADOS | O70: IFS | P70: 146868 | Q70: MANTIENE | R70: 196900 | S70: =IFERROR((MaestraLP3[[#This Row],[COSTO ]]/MaestraLP3[[#This Row],[COSTO OCT]]-1),0) -> 0 | T70: ACTIVO | V70: =+VLOOKUP(MaestraLP3[[#This Row],[-]],'[1]BD MES'!$A:$N,14,0) -> 146868 | W70: 146868 | X70: =+(MaestraLP3[[#This Row],[COSTO ]]-MaestraLP3[[#This Row],[COSTO OCT AL 27-10]])/MaestraLP3[[#This Row],[COSTO OCT AL 27-10]] -> 0 | Y70: =++IF(Q70="HASTA AGOTAR STOCK","HASTA AGOTAR STOCK",IF(MaestraLP3[[#This Row],[PRECIO OCT]]=0,"NO PARA LP",IF(MaestraLP3[[#This Row],[PRECIO OCT]]=0,"INCORPORACIÓN",IF(AA70=0,"MANTIENE",IF(AA70<0,"BAJA",IF(AA70>0,"ALZA","")))))) -> MANTIENE | Z70: 196900 | AA70: =IF(Z70=0,"INDICAR PRECIO VTA",Z70-MaestraLP3[[#This Row],[PRECIO OCT]]) -> 0 | AB70: =+IFERROR((Z70-W70)/Z70,"-") -> 0.25409853 | AC70: =IFERROR(MaestraLP3[[#This Row],[PRECIO]]*MaestraLP3[[#This Row],[%MG UMV]],0) -> 50032 | AD70: 16.32 | AE70: =IFERROR(MaestraLP3[[#This Row],[MARGEN UNITARIO]]/MaestraLP3[[#This Row],[Peso Neto UMV (KG)]],0) -> 3065.6863 | AF70: SI | AG70: 1 | AH70: 0.03 | AI70: 0.05 | AJ70: SI | AK70: NO
A71: EXCLUSIVOS | B71: 104547560 | C71: =+MaestraLP3[[#This Row],[CÓDIGO]]&MaestraLP3[[#Headers],[-]]&MaestraLP3[[#This Row],[UMV]] -> 104547560-KG | D71: =+MaestraLP3[[#This Row],[CÓDIGO]]&MaestraLP3[[#Headers],[FS00]] -> 104547560FS00 | E71: MYRIAM GARIN | F71: PAZ CARO | G71: HAMBURGUESAS | H71: HAMBURGUESAS CERTIFICADAS | I71: MOLIDA VACUNO ANGUS 81/19 4,5 KG (CAJA | J71: KG | K71: KG | M71: =VLOOKUP(MaestraLP3[[#This Row],[UMV]],VALIDACIONES!J:L,3,0) -> Kilogramo | N71: CONGELADOS | O71: IFS | P71: 7548 | Q71: NO PARA LP | R71: 0 | S71: =IFERROR((MaestraLP3[[#This Row],[COSTO ]]/MaestraLP3[[#This Row],[COSTO OCT]]-1),0) -> 0.028749338 | T71: NPI | V71: =+VLOOKUP(MaestraLP3[[#This Row],[-]],'[1]BD MES'!$A:$N,14,0) -> 7765 | W71: 7765 | X71: =+(MaestraLP3[[#This Row],[COSTO ]]-MaestraLP3[[#This Row],[COSTO OCT AL 27-10]])/MaestraLP3[[#This Row],[COSTO OCT AL 27-10]] -> 0 | Y71: =++IF(Q71="HASTA AGOTAR STOCK","HASTA AGOTAR STOCK",IF(MaestraLP3[[#This Row],[PRECIO OCT]]=0,"NO PARA LP",IF(MaestraLP3[[#This Row],[PRECIO OCT]]=0,"INCORPORACIÓN",IF(AA71=0,"MANTIENE",IF(AA71<0,"BAJA",IF(AA71>0,"ALZA","")))))) -> NO PARA LP | Z71: 0 | AA71: =IF(Z71=0,"INDICAR PRECIO VTA",Z71-MaestraLP3[[#This Row],[PRECIO OCT]]) -> INDICAR PRECIO VTA | AB71: =+IFERROR((Z71-W71)/Z71,"-") -> - | AC71: =IFERROR(MaestraLP3[[#This Row],[PRECIO]]*MaestraLP3[[#This Row],[%MG UMV]],0) -> 0 | AD71: 1 | AE71: =IFERROR(MaestraLP3[[#This Row],[MARGEN UNITARIO]]/MaestraLP3[[#This Row],[Peso Neto UMV (KG)]],0) -> 0 | AF71: NO | AG71: 1 | AH71: 0 | AI71: 0 | AJ71: SI | AK71: NO
A72: EXCLUSIVOS | B72: 104547540 | C72: =+MaestraLP3[[#This Row],[CÓDIGO]]&MaestraLP3[[#Headers],[-]]&MaestraLP3[[#This Row],[UMV]] -> 104547540-C02 | D72: =+MaestraLP3[[#This Row],[CÓDIGO]]&MaestraLP3[[#Headers],[FS00]] -> 104547540FS00 | E72: MYRIAM GARIN | F72: PAZ CARO | G72: JAMONES Y CECINAS | H72: EMBUTIDOS Y FIAMBRES | I72: SALCHICHA FRANK 100% VACUNO | J72: C02 | K72: UN | M72: =VLOOKUP(MaestraLP3[[#This Row],[UMV]],VALIDACIONES!J:L,3,0) -> Caja 2 Unidades | N72: CONGELADOS | O72: IFS | P72: 32596 | Q72: NO PARA LP | R72: 0 | S72: =IFERROR((MaestraLP3[[#This Row],[COSTO ]]/MaestraLP3[[#This Row],[COSTO OCT]]-1),0) -> -0.018836667 | T72: NPI | V72: =+VLOOKUP(MaestraLP3[[#This Row],[-]],'[1]BD MES'!$A:$N,14,0) -> 31982 | W72: 31982 | X72: =+(MaestraLP3[[#This Row],[COSTO ]]-MaestraLP3[[#This Row],[COSTO OCT AL 27-10]])/MaestraLP3[[#This Row],[COSTO OCT AL 27-10]] -> 0 | Y72: =++IF(Q72="HASTA AGOTAR STOCK","HASTA AGOTAR STOCK",IF(MaestraLP3[[#This Row],[PRECIO OCT]]=0,"NO PARA LP",IF(MaestraLP3[[#This Row],[PRECIO OCT]]=0,"INCORPORACIÓN",IF(AA72=0,"MANTIENE",IF(AA72<0,"BAJA",IF(AA72>0,"ALZA","")))))) -> NO PARA LP | Z72: 0 | AA72: =IF(Z72=0,"INDICAR PRECIO VTA",Z72-MaestraLP3[[#This Row],[PRECIO OCT]]) -> INDICAR PRECIO VTA | AB72: =+IFERROR((Z72-W72)/Z72,"-") -> - | AC72: =IFERROR(MaestraLP3[[#This Row],[PRECIO]]*MaestraLP3[[#This Row],[%MG UMV]],0) -> 0 | AD72: 4.54 | AE72: =IFERROR(MaestraLP3[[#This Row],[MARGEN UNITARIO]]/MaestraLP3[[#This Row],[Peso Neto UMV (KG)]],0) -> 0 | AF72: NO | AG72: 1 | AH72: 0 | AI72: 0 | AJ72: SI | AK72: NO
A73: EXCLUSIVOS | B73: 104542790 | C73: =+MaestraLP3[[#This Row],[CÓDIGO]]&MaestraLP3[[#Headers],[-]]&MaestraLP3[[#This Row],[UMV]] -> 104542790-C02 | D73: =+MaestraLP3[[#This Row],[CÓDIGO]]&MaestraLP3[[#Headers],[FS00]] -> 104542790FS00 | E73: MYRIAM GARIN | F73: PAZ CARO | G73: JAMONES Y CECINAS | H73: TOCINOS | I73: TOCINO PIZCAS SUGARDALE 2,27 KG | J73: C02 | K73: UN | M73: =VLOOKUP(MaestraLP3[[#This Row],[UMV]],VALIDACIONES!J:L,3,0) -> Caja 2 Unidades | N73: CONGELADOS | O73: IFS | P73: 56104.308 | Q73: NO PARA LP | S73: =IFERROR((MaestraLP3[[#This Row],[COSTO ]]/MaestraLP3[[#This Row],[COSTO OCT]]-1),0) -> -0.12830224 | T73: NPI | V73: =+VLOOKUP(MaestraLP3[[#This Row],[-]],'[1]BD MES'!$A:$N,14,0) -> 55642 | W73: 48906 | X73: =+(MaestraLP3[[#This Row],[COSTO ]]-MaestraLP3[[#This Row],[COSTO OCT AL 27-10]])/MaestraLP3[[#This Row],[COSTO OCT AL 27-10]] -> -0.12105963 | Y73: =++IF(Q73="HASTA AGOTAR STOCK","HASTA AGOTAR STOCK",IF(MaestraLP3[[#This Row],[PRECIO OCT]]=0,"NO PARA LP",IF(MaestraLP3[[#This Row],[PRECIO OCT]]=0,"INCORPORACIÓN",IF(AA73=0,"MANTIENE",IF(AA73<0,"BAJA",IF(AA73>0,"ALZA","")))))) -> NO PARA LP | AA73: =IF(Z73=0,"INDICAR PRECIO VTA",Z73-MaestraLP3[[#This Row],[PRECIO OCT]]) -> INDICAR PRECIO VTA | AB73: =+IFERROR((Z73-W73)/Z73,"-") -> - | AC73: =IFERROR(MaestraLP3[[#This Row],[PRECIO]]*MaestraLP3[[#This Row],[%MG UMV]],0) -> 0 | AD73: 4.54 | AE73: =IFERROR(MaestraLP3[[#This Row],[MARGEN UNITARIO]]/MaestraLP3[[#This Row],[Peso Neto UMV (KG)]],0) -> 0 | AF73: SI | AG73: 1 | AH73: 0.05 | AI73: 0.07 | AJ73: SI | AK73: NO
A74: EXCLUSIVOS | B74: 104538130 | C74: =+MaestraLP3[[#This Row],[CÓDIGO]]&MaestraLP3[[#Headers],[-]]&MaestraLP3[[#This Row],[UMV]] -> 104538130-KG | D74: =+MaestraLP3[[#This Row],[CÓDIGO]]&MaestraLP3[[#Headers],[FS00]] -> 104538130FS00 | E74: MYRIAM GARIN | F74: PAZ CARO | G74: VACUNO CONGELADO | H74: CARNES CERTIFICADAS | I74: ENTRECOT STEAK CERTIFIED ANGUS BEEF | J74: KG | K74: KG | M74: =VLOOKUP(MaestraLP3[[#This Row],[UMV]],VALIDACIONES!J:L,3,0) -> Kilogramo | N74: CONGELADOS | O74: IFS | P74: 19734.8 | Q74: MANTIENE | R74: 25000 | S74: =IFERROR((MaestraLP3[[#This Row],[COSTO ]]/MaestraLP3[[#This Row],[COSTO OCT]]-1),0) -> -0.10857977 | T74: ACTIVO (M) | V74: =+VLOOKUP(MaestraLP3[[#This Row],[-]],'[1]BD MES'!$A:$N,14,0) -> 18777 | W74: 17592 | X74: =+(MaestraLP3[[#This Row],[COSTO ]]-MaestraLP3[[#This Row],[COSTO OCT AL 27-10]])/MaestraLP3[[#This Row],[COSTO OCT AL 27-10]] -> -0.063109123 | Y74: =++IF(Q74="HASTA AGOTAR STOCK","HASTA AGOTAR STOCK",IF(MaestraLP3[[#This Row],[PRECIO OCT]]=0,"NO PARA LP",IF(MaestraLP3[[#This Row],[PRECIO OCT]]=0,"INCORPORACIÓN",IF(AA74=0,"MANTIENE",IF(AA74<0,"BAJA",IF(AA74>0,"ALZA","")))))) -> MANTIENE | Z74: 25000 | AA74: =IF(Z74=0,"INDICAR PRECIO VTA",Z74-MaestraLP3[[#This Row],[PRECIO OCT]]) -> 0 | AB74: =+IFERROR((Z74-W74)/Z74,"-") -> 0.29632 | AC74: =IFERROR(MaestraLP3[[#This Row],[PRECIO]]*MaestraLP3[[#This Row],[%MG UMV]],0) -> 7408 | AD74: 1 | AE74: =IFERROR(MaestraLP3[[#This Row],[MARGEN UNITARIO]]/MaestraLP3[[#This Row],[Peso Neto UMV (KG)]],0) -> 7408 | AF74: NO | AG74: 1 | AH74: 0 | AI74: 0 | AJ74: SI | AK74: NO
A75: EXCLUSIVOS | B75: 104500540 | C75: =+MaestraLP3[[#This Row],[CÓDIGO]]&MaestraLP3[[#Headers],[-]]&MaestraLP3[[#This Row],[UMV]] -> 104500540-KG | D75: =+MaestraLP3[[#This Row],[CÓDIGO]]&MaestraLP3[[#Headers],[FS00]] -> 104500540FS00 | E75: MYRIAM GARIN | F75: PAZ CARO | G75: VACUNO CONGELADO | H75: CARNES CERTIFICADAS | I75: FILETE CERTIFIED ANGUS BEEF | J75: KG | K75: KG | L75: CJ - UN | M75: =VLOOKUP(MaestraLP3[[#This Row],[UMV]],VALIDACIONES!J:L,3,0) -> Kilogramo | N75: CONGELADOS | O75: IFS | P75: 36000 | Q75: ALZA | R75: 42000 | S75: =IFERROR((MaestraLP3[[#This Row],[COSTO ]]/MaestraLP3[[#This Row],[COSTO OCT]]-1),0) -> -0.13773083 | T75: ACTIVO | V75: =+VLOOKUP(MaestraLP3[[#This Row],[-]],'[1]BD MES'!$A:$N,14,0) -> 34045.51 | W75: 31041.69 | X75: =+(MaestraLP3[[#This Row],[COSTO ]]-MaestraLP3[[#This Row],[COSTO OCT AL 27-10]])/MaestraLP3[[#This Row],[COSTO OCT AL 27-10]] -> -0.088229549 | Y75: =++IF(Q75="HASTA AGOTAR STOCK","HASTA AGOTAR STOCK",IF(MaestraLP3[[#This Row],[PRECIO OCT]]=0,"NO PARA LP",IF(MaestraLP3[[#This Row],[PRECIO OCT]]=0,"INCORPORACIÓN",IF(AA75=0,"MANTIENE",IF(AA75<0,"BAJA",IF(AA75>0,"ALZA","")))))) -> MANTIENE | Z75: 42000 | AA75: =IF(Z75=0,"INDICAR PRECIO VTA",Z75-MaestraLP3[[#This Row],[PRECIO OCT]]) -> 0 | AB75: =+IFERROR((Z75-W75)/Z75,"-") -> 0.26091214 | AC75: =IFERROR(MaestraLP3[[#This Row],[PRECIO]]*MaestraLP3[[#This Row],[%MG UMV]],0) -> 10958.31 | AD75: 1 | AE75: =IFERROR(MaestraLP3[[#This Row],[MARGEN UNITARIO]]/MaestraLP3[[#This Row],[Peso Neto UMV (KG)]],0) -> 10958.31 | AF75: NO | AG75: 1 y 3 | AH75: 0 | AI75: 0 | AJ75: SI | AK75: NO
A76: EXCLUSIVOS | B76: 104500690 | C76: =+MaestraLP3[[#This Row],[CÓDIGO]]&MaestraLP3[[#Headers],[-]]&MaestraLP3[[#This Row],[UMV]] -> 104500690-KG | D76: =+MaestraLP3[[#This Row],[CÓDIGO]]&MaestraLP3[[#Headers],[FS00]] -> 104500690FS00 | E76: MYRIAM GARIN | F76: PAZ CARO | G76: VACUNO CONGELADO | H76: CARNES CERTIFICADAS | I76: LOMO LISO PRIME CERTIFIED ANGUS BEEF | J76: KG | K76: KG | M76: =VLOOKUP(MaestraLP3[[#This Row],[UMV]],VALIDACIONES!J:L,3,0) -> Kilogramo | N76: CONGELADOS | O76: IFS | P76: 30495 | Q76: MANTIENE | R76: 36000 | S76: =IFERROR((MaestraLP3[[#This Row],[COSTO ]]/MaestraLP3[[#This Row],[COSTO OCT]]-1),0) -> -0.0040960813 | T76: ACTIVO | V76: =+VLOOKUP(MaestraLP3[[#This Row],[-]],'[1]BD MES'!$A:$N,14,0) -> 30026.22 | W76: 30370.09 | X76: =+(MaestraLP3[[#This Row],[COSTO ]]-MaestraLP3[[#This Row],[COSTO OCT AL 27-10]])/MaestraLP3[[#This Row],[COSTO OCT AL 27-10]] -> 0.011452324 | Y76: =++IF(Q76="HASTA AGOTAR STOCK","HASTA AGOTAR STOCK",IF(MaestraLP3[[#This Row],[PRECIO OCT]]=0,"NO PARA LP",IF(MaestraLP3[[#This Row],[PRECIO OCT]]=0,"INCORPORACIÓN",IF(AA76=0,"MANTIENE",IF(AA76<0,"BAJA",IF(AA76>0,"ALZA","")))))) -> MANTIENE | Z76: 36000 | AA76: =IF(Z76=0,"INDICAR PRECIO VTA",Z76-MaestraLP3[[#This Row],[PRECIO OCT]]) -> 0 | AB76: =+IFERROR((Z76-W76)/Z76,"-") -> 0.15638639 | AC76: =IFERROR(MaestraLP3[[#This Row],[PRECIO]]*MaestraLP3[[#This Row],[%MG UMV]],0) -> 5629.91 | AD76: 1 | AE76: =IFERROR(MaestraLP3[[#This Row],[MARGEN UNITARIO]]/MaestraLP3[[#This Row],[Peso Neto UMV (KG)]],0) -> 5629.91 | AF76: NO | AG76: 1 | AH76: 0 | AI76: 0 | AJ76: SI | AK76: NO
A77: EXCLUSIVOS | B77: 104533520 | C77: =+MaestraLP3[[#This Row],[CÓDIGO]]&MaestraLP3[[#Headers],[-]]&MaestraLP3[[#This Row],[UMV]] -> 104533520-KG | D77: =+MaestraLP3[[#This Row],[CÓDIGO]]&MaestraLP3[[#Headers],[FS00]] -> 104533520FS00 | E77: MYRIAM GARIN | F77: PAZ CARO | G77: VACUNO CONGELADO | H77: CARNES CERTIFICADAS | I77: LOMO LISO STEAK CERTIFIED ANGUS BEEF | J77: KG | K77: KG | M77: =VLOOKUP(MaestraLP3[[#This Row],[UMV]],VALIDACIONES!J:L,3,0) -> Kilogramo | N77: CONGELADOS | O77: IFS | P77: 26645.07 | Q77: MANTIENE | R77: 35000 | S77: =IFERROR((MaestraLP3[[#This Row],[COSTO ]]/MaestraLP3[[#This Row],[COSTO OCT]]-1),0) -> -0.19249602 | T77: ACTIVO (M) | V77: =+VLOOKUP(MaestraLP3[[#This Row],[-]],'[1]BD MES'!$A:$N,14,0) -> 25646 | W77: 21516 | X77: =+(MaestraLP3[[#This Row],[COSTO ]]-MaestraLP3[[#This Row],[COSTO OCT AL 27-10]])/MaestraLP3[[#This Row],[COSTO OCT AL 27-10]] -> -0.16103876 | Y77: =++IF(Q77="HASTA AGOTAR STOCK","HASTA AGOTAR STOCK",IF(MaestraLP3[[#This Row],[PRECIO OCT]]=0,"NO PARA LP",IF(MaestraLP3[[#This Row],[PRECIO OCT]]=0,"INCORPORACIÓN",IF(AA77=0,"MANTIENE",IF(AA77<0,"BAJA",IF(AA77>0,"ALZA","")))))) -> MANTIENE | Z77: 35000 | AA77: =IF(Z77=0,"INDICAR PRECIO VTA",Z77-MaestraLP3[[#This Row],[PRECIO OCT]]) -> 0 | AB77: =+IFERROR((Z77-W77)/Z77,"-") -> 0.38525714 | AC77: =IFERROR(MaestraLP3[[#This Row],[PRECIO]]*MaestraLP3[[#This Row],[%MG UMV]],0) -> 13484 | AD77: 1 | AE77: =IFERROR(MaestraLP3[[#This Row],[MARGEN UNITARIO]]/MaestraLP3[[#This Row],[Peso Neto UMV (KG)]],0) -> 13484 | AF77: NO | AG77: 1 | AH77: 0 | AI77: 0 | AJ77: SI | AK77: NO
A78: EXCLUSIVOS | B78: 104529950 | C78: =+MaestraLP3[[#This Row],[CÓDIGO]]&MaestraLP3[[#Headers],[-]]&MaestraLP3[[#This Row],[UMV]] -> 104529950-KG | D78: =+MaestraLP3[[#This Row],[CÓDIGO]]&MaestraLP3[[#Headers],[FS00]] -> 104529950FS00 | E78: MYRIAM GARIN | F78: PAZ CARO | G78: VACUNO CONGELADO | H78: CARNES CERTIFICADAS | I78: LOMO VETADO C/H STEAK CAB | J78: KG | K78: KG | M78: =VLOOKUP(MaestraLP3[[#This Row],[UMV]],VALIDACIONES!J:L,3,0) -> Kilogramo | N78: CONGELADOS | O78: IFS | P78: 23820 | Q78: MANTIENE | R78: 32000 | S78: =IFERROR((MaestraLP3[[#This Row],[COSTO ]]/MaestraLP3[[#This Row],[COSTO OCT]]-1),0) -> 0 | T78: ACTIVO (M) | V78: =+VLOOKUP(MaestraLP3[[#This Row],[-]],'[1]BD MES'!$A:$N,14,0) -> 23820 | W78: 23820 | X78: =+(MaestraLP3[[#This Row],[COSTO ]]-MaestraLP3[[#This Row],[COSTO OCT AL 27-10]])/MaestraLP3[[#This Row],[COSTO OCT AL 27-10]] -> 0 | Y78: =++IF(Q78="HASTA AGOTAR STOCK","HASTA AGOTAR STOCK",IF(MaestraLP3[[#This Row],[PRECIO OCT]]=0,"NO PARA LP",IF(MaestraLP3[[#This Row],[PRECIO OCT]]=0,"INCORPORACIÓN",IF(AA78=0,"MANTIENE",IF(AA78<0,"BAJA",IF(AA78>0,"ALZA","")))))) -> MANTIENE | Z78: 32000 | AA78: =IF(Z78=0,"INDICAR PRECIO VTA",Z78-MaestraLP3[[#This Row],[PRECIO OCT]]) -> 0 | AB78: =+IFERROR((Z78-W78)/Z78,"-") -> 0.255625 | AC78: =IFERROR(MaestraLP3[[#This Row],[PRECIO]]*MaestraLP3[[#This Row],[%MG UMV]],0) -> 8180 | AD78: 1 | AE78: =IFERROR(MaestraLP3[[#This Row],[MARGEN UNITARIO]]/MaestraLP3[[#This Row],[Peso Neto UMV (KG)]],0) -> 8180 | AF78: NO | AG78: 1 | AH78: 0.08 | AI78: 0.1 | AK78: NO
A79: EXCLUSIVOS | B79: 104500570 | C79: =+MaestraLP3[[#This Row],[CÓDIGO]]&MaestraLP3[[#Headers],[-]]&MaestraLP3[[#This Row],[UMV]] -> 104500570-KG | D79: =+MaestraLP3[[#This Row],[CÓDIGO]]&MaestraLP3[[#Headers],[FS00]] -> 104500570FS00 | E79: MYRIAM GARIN | F79: PAZ CARO | G79: VACUNO CONGELADO | H79: CARNES CERTIFICADAS | I79: LOMO VETADO PRIME CERTIFIED ANGUS BEEF | J79: KG | K79: KG | M79: =VLOOKUP(MaestraLP3[[#This Row],[UMV]],VALIDACIONES!J:L,3,0) -> Kilogramo | N79: CONGELADOS | O79: IFS | P79: 35911 | Q79: MANTIENE | R79: 44000 | S79: =IFERROR((MaestraLP3[[#This Row],[COSTO ]]/MaestraLP3[[#This Row],[COSTO OCT]]-1),0) -> 0.0033772382 | T79: ACTIVO | V79: =+VLOOKUP(MaestraLP3[[#This Row],[-]],'[1]BD MES'!$A:$N,14,0) -> 35377.79 | W79: 36032.28 | X79: =+(MaestraLP3[[#This Row],[COSTO ]]-MaestraLP3[[#This Row],[COSTO OCT AL 27-10]])/MaestraLP3[[#This Row],[COSTO OCT AL 27-10]] -> 0.018500025 | Y79: =++IF(Q79="HASTA AGOTAR STOCK","HASTA AGOTAR STOCK",IF(MaestraLP3[[#This Row],[PRECIO OCT]]=0,"NO PARA LP",IF(MaestraLP3[[#This Row],[PRECIO OCT]]=0,"INCORPORACIÓN",IF(AA79=0,"MANTIENE",IF(AA79<0,"BAJA",IF(AA79>0,"ALZA","")))))) -> MANTIENE | Z79: 44000 | AA79: =IF(Z79=0,"INDICAR PRECIO VTA",Z79-MaestraLP3[[#This Row],[PRECIO OCT]]) -> 0 | AB79: =+IFERROR((Z79-W79)/Z79,"-") -> 0.18108455 | AC79: =IFERROR(MaestraLP3[[#This Row],[PRECIO]]*MaestraLP3[[#This Row],[%MG UMV]],0) -> 7967.72 | AD79: 1 | AE79: =IFERROR(MaestraLP3[[#This Row],[MARGEN UNITARIO]]/MaestraLP3[[#This Row],[Peso Neto UMV (KG)]],0) -> 7967.72 | AF79: NO | AG79: 1 | AH79: 0 | AI79: 0 | AJ79: SI | AK79: NO
A80: EXCLUSIVOS | B80: 104529960 | C80: =+MaestraLP3[[#This Row],[CÓDIGO]]&MaestraLP3[[#Headers],[-]]&MaestraLP3[[#This Row],[UMV]] -> 104529960-KG | D80: =+MaestraLP3[[#This Row],[CÓDIGO]]&MaestraLP3[[#Headers],[FS00]] -> 104529960FS00 | E80: MYRIAM GARIN | F80: PAZ CARO | G80: VACUNO CONGELADO | H80: CARNES CERTIFICADAS | I80: LOMO VETADO STEAK CERTIFIED ANGUS BEEF | J80: KG | K80: KG | M80: =VLOOKUP(MaestraLP3[[#This Row],[UMV]],VALIDACIONES!J:L,3,0) -> Kilogramo | N80: CONGELADOS | O80: IFS | P80: 27717.3 | Q80: MANTIENE | R80: 36000 | S80: =IFERROR((MaestraLP3[[#This Row],[COSTO ]]/MaestraLP3[[#This Row],[COSTO OCT]]-1),0) -> 0.0074935149 | T80: ACTIVO (M) | V80: =+VLOOKUP(MaestraLP3[[#This Row],[-]],'[1]BD MES'!$A:$N,14,0) -> 26973 | W80: 27925 | X80: =+(MaestraLP3[[#This Row],[COSTO ]]-MaestraLP3[[#This Row],[COSTO OCT AL 27-10]])/MaestraLP3[[#This Row],[COSTO OCT AL 27-10]] -> 0.035294554 | Y80: =++IF(Q80="HASTA AGOTAR STOCK","HASTA AGOTAR STOCK",IF(MaestraLP3[[#This Row],[PRECIO OCT]]=0,"NO PARA LP",IF(MaestraLP3[[#This Row],[PRECIO OCT]]=0,"INCORPORACIÓN",IF(AA80=0,"MANTIENE",IF(AA80<0,"BAJA",IF(AA80>0,"ALZA","")))))) -> MANTIENE | Z80: 36000 | AA80: =IF(Z80=0,"INDICAR PRECIO VTA",Z80-MaestraLP3[[#This Row],[PRECIO OCT]]) -> 0 | AB80: =+IFERROR((Z80-W80)/Z80,"-") -> 0.22430556 | AC80: =IFERROR(MaestraLP3[[#This Row],[PRECIO]]*MaestraLP3[[#This Row],[%MG UMV]],0) -> 8075 | AD80: 1 | AE80: =IFERROR(MaestraLP3[[#This Row],[MARGEN UNITARIO]]/MaestraLP3[[#This Row],[Peso Neto UMV (KG)]],0) -> 8075 | AF80: NO | AG80: 1 | AH80: 0 | AI80: 0 | AJ80: SI | AK80: NO
A81: EXCLUSIVOS | B81: 104538120 | C81: =+MaestraLP3[[#This Row],[CÓDIGO]]&MaestraLP3[[#Headers],[-]]&MaestraLP3[[#This Row],[UMV]] -> 104538120-KG | D81: =+MaestraLP3[[#This Row],[CÓDIGO]]&MaestraLP3[[#Headers],[FS00]] -> 104538120FS00 | E81: MYRIAM GARIN | F81: PAZ CARO | G81: VACUNO CONGELADO | H81: CARNES CERTIFICADAS | I81: TOMAHAWK STEAK CERTIFIED ANGUS BEEF | J81: KG | K81: KG | M81: =VLOOKUP(MaestraLP3[[#This Row],[UMV]],VALIDACIONES!J:L,3,0) -> Kilogramo | N81: CONGELADOS | O81: IFS | P81: 25856 | Q81: MANTIENE | R81: 34000 | S81: =IFERROR((MaestraLP3[[#This Row],[COSTO ]]/MaestraLP3[[#This Row],[COSTO OCT]]-1),0) -> 0 | T81: ACTIVO (M) | V81: =+VLOOKUP(MaestraLP3[[#This Row],[-]],'[1]BD MES'!$A:$N,14,0) -> 25856 | W81: 25856 | X81: =+(MaestraLP3[[#This Row],[COSTO ]]-MaestraLP3[[#This Row],[COSTO OCT AL 27-10]])/MaestraLP3[[#This Row],[COSTO OCT AL 27-10]] -> 0 | Y81: =++IF(Q81="HASTA AGOTAR STOCK","HASTA AGOTAR STOCK",IF(MaestraLP3[[#This Row],[PRECIO OCT]]=0,"NO PARA LP",IF(MaestraLP3[[#This Row],[PRECIO OCT]]=0,"INCORPORACIÓN",IF(AA81=0,"MANTIENE",IF(AA81<0,"BAJA",IF(AA81>0,"ALZA","")))))) -> MANTIENE | Z81: 34000 | AA81: =IF(Z81=0,"INDICAR PRECIO VTA",Z81-MaestraLP3[[#This Row],[PRECIO OCT]]) -> 0 | AB81: =+IFERROR((Z81-W81)/Z81,"-") -> 0.23952941 | AC81: =IFERROR(MaestraLP3[[#This Row],[PRECIO]]*MaestraLP3[[#This Row],[%MG UMV]],0) -> 8144 | AD81: 1 | AE81: =IFERROR(MaestraLP3[[#This Row],[MARGEN UNITARIO]]/MaestraLP3[[#This Row],[Peso Neto UMV (KG)]],0) -> 8144 | AF81: NO | AG81: 1 | AH81: 0 | AI81: 0 | AJ81: SI | AK81: NO
A82: LIQUIDACIÓN | B82: 104529400 | C82: =+MaestraLP3[[#This Row],[CÓDIGO]]&MaestraLP3[[#Headers],[-]]&MaestraLP3[[#This Row],[UMV]] -> 104529400-UN | D82: =+MaestraLP3[[#This Row],[CÓDIGO]]&MaestraLP3[[#Headers],[FS00]] -> 104529400FS00 | E82: BELTRÁN FRANZANI | F82: CAMILA UGARTE | G82: CAFE Y DERIVADOS | H82: ACCESORIOS | I82: 20002356 RESERVA DE TIERRA ESPRESSO CUP | J82: UN | K82: UN | M82: =VLOOKUP(MaestraLP3[[#This Row],[UMV]],VALIDACIONES!J:L,3,0) -> Unidad | N82: SECO | O82: IFS | P82: 2656 | Q82: NO PARA LP | R82: 0 | S82: =IFERROR((MaestraLP3[[#This Row],[COSTO ]]/MaestraLP3[[#This Row],[COSTO OCT]]-1),0) -> 0 | T82: VIAS DESCONTINUACION | V82: =+VLOOKUP(MaestraLP3[[#This Row],[-]],'[1]BD MES'!$A:$N,14,0) -> 2656 | W82: 2656 | X82: =+(MaestraLP3[[#This Row],[COSTO ]]-MaestraLP3[[#This Row],[COSTO OCT AL 27-10]])/MaestraLP3[[#This Row],[COSTO OCT AL 27-10]] -> 0 | Y82: =++IF(Q82="HASTA AGOTAR STOCK","HASTA AGOTAR STOCK",IF(MaestraLP3[[#This Row],[PRECIO OCT]]=0,"NO PARA LP",IF(MaestraLP3[[#This Row],[PRECIO OCT]]=0,"INCORPORACIÓN",IF(AA82=0,"MANTIENE",IF(AA82<0,"BAJA",IF(AA82>0,"ALZA","")))))) -> NO PARA LP | Z82: 0 | AA82: =IF(Z82=0,"INDICAR PRECIO VTA",Z82-MaestraLP3[[#This Row],[PRECIO OCT]]) -> INDICAR PRECIO VTA | AB82: =+IFERROR((Z82-W82)/Z82,"-") -> - | AC82: =IFERROR(MaestraLP3[[#This Row],[PRECIO]]*MaestraLP3[[#This Row],[%MG UMV]],0) -> 0 | AD82: 36 | AE82: =IFERROR(MaestraLP3[[#This Row],[MARGEN UNITARIO]]/MaestraLP3[[#This Row],[Peso Neto UMV (KG)]],0) -> 0 | AF82: NO | AG82: 1 | AH82: 0 | AI82: 0 | AK82: NO
A83: LIQUIDACIÓN | B83: 104518200 | C83: =+MaestraLP3[[#This Row],[CÓDIGO]]&MaestraLP3[[#Headers],[-]]&MaestraLP3[[#This Row],[UMV]] -> 104518200-C06 | D83: =+MaestraLP3[[#This Row],[CÓDIGO]]&MaestraLP3[[#Headers],[FS00]] -> 104518200FS00 | E83: BELTRÁN FRANZANI | F83: CAMILA UGARTE | G83: CAFE Y DERIVADOS | H83: ACCESORIOS | I83: TAZA Y PLATO CAPPUCCINO PREMIUM LAVAZZA | J83: C06 | K83: UN | M83: =VLOOKUP(MaestraLP3[[#This Row],[UMV]],VALIDACIONES!J:L,3,0) -> Caja 6 Unidades | N83: SECO | O83: IFS | P83: 17140.92 | Q83: MANTIENE | R83: 25700 | S83: =IFERROR((MaestraLP3[[#This Row],[COSTO ]]/MaestraLP3[[#This Row],[COSTO OCT]]-1),0) -> 0 | T83: VIAS DESCONTINUACION | V83: =+VLOOKUP(MaestraLP3[[#This Row],[-]],'[1]BD MES'!$A:$N,14,0) -> 17140.92 | W83: 17140.92 | X83: =+(MaestraLP3[[#This Row],[COSTO ]]-MaestraLP3[[#This Row],[COSTO OCT AL 27-10]])/MaestraLP3[[#This Row],[COSTO OCT AL 27-10]] -> 0 | Y83: =++IF(Q83="HASTA AGOTAR STOCK","HASTA AGOTAR STOCK",IF(MaestraLP3[[#This Row],[PRECIO OCT]]=0,"NO PARA LP",IF(MaestraLP3[[#This Row],[PRECIO OCT]]=0,"INCORPORACIÓN",IF(AA83=0,"MANTIENE",IF(AA83<0,"BAJA",IF(AA83>0,"ALZA","")))))) -> MANTIENE | Z83: 25700 | AA83: =IF(Z83=0,"INDICAR PRECIO VTA",Z83-MaestraLP3[[#This Row],[PRECIO OCT]]) -> 0 | AB83: =+IFERROR((Z83-W83)/Z83,"-") -> 0.33303813 | AC83: =IFERROR(MaestraLP3[[#This Row],[PRECIO]]*MaestraLP3[[#This Row],[%MG UMV]],0) -> 8559.08 | AD83: 2.1 | AE83: =IFERROR(MaestraLP3[[#This Row],[MARGEN UNITARIO]]/MaestraLP3[[#This Row],[Peso Neto UMV (KG)]],0) -> 4075.7524 | AF83: NO | AG83: 1 | AH83: 0.1 | AI83: 0.1 | AK83: NO
A84: LIQUIDACIÓN | B84: 104518180 | C84: =+MaestraLP3[[#This Row],[CÓDIGO]]&MaestraLP3[[#Headers],[-]]&MaestraLP3[[#This Row],[UMV]] -> 104518180-C12 | D84: =+MaestraLP3[[#This Row],[CÓDIGO]]&MaestraLP3[[#Headers],[FS00]] -> 104518180FS00 | E84: BELTRÁN FRANZANI | F84: CAMILA UGARTE | G84: CAFE Y DERIVADOS | H84: ACCESORIOS | I84: TAZA Y PLATO ESPRESSO PREMIUM LAVAZZA | J84: C12 | K84: UN | M84: =VLOOKUP(MaestraLP3[[#This Row],[UMV]],VALIDACIONES!J:L,3,0) -> Caja 12 Unidades | N84: SECO | O84: IFS | P84: 27440.04 | Q84: MANTIENE | R84: 40000 | S84: =IFERROR((MaestraLP3[[#This Row],[COSTO ]]/MaestraLP3[[#This Row],[COSTO OCT]]-1),0) -> 0 | T84: VIAS DESCONTINUACION | V84: =+VLOOKUP(MaestraLP3[[#This Row],[-]],'[1]BD MES'!$A:$N,14,0) -> 27440.04 | W84: 27440.04 | X84: =+(MaestraLP3[[#This Row],[COSTO ]]-MaestraLP3[[#This Row],[COSTO OCT AL 27-10]])/MaestraLP3[[#This Row],[COSTO OCT AL 27-10]] -> 0 | Y84: =++IF(Q84="HASTA AGOTAR STOCK","HASTA AGOTAR STOCK",IF(MaestraLP3[[#This Row],[PRECIO OCT]]=0,"NO PARA LP",IF(MaestraLP3[[#This Row],[PRECIO OCT]]=0,"INCORPORACIÓN",IF(AA84=0,"MANTIENE",IF(AA84<0,"BAJA",IF(AA84>0,"ALZA","")))))) -> MANTIENE | Z84: 40000 | AA84: =IF(Z84=0,"INDICAR PRECIO VTA",Z84-MaestraLP3[[#This Row],[PRECIO OCT]]) -> 0 | AB84: =+IFERROR((Z84-W84)/Z84,"-") -> 0.313999 | AC84: =IFERROR(MaestraLP3[[#This Row],[PRECIO]]*MaestraLP3[[#This Row],[%MG UMV]],0) -> 12559.96 | AD84: 2.4 | AE84: =IFERROR(MaestraLP3[[#This Row],[MARGEN UNITARIO]]/MaestraLP3[[#This Row],[Peso Neto UMV (KG)]],0) -> 5233.3167 | AF84: NO | AG84: 1 | AH84: 0.1 | AI84: 0.1 | AK84: NO
A85: LIQUIDACIÓN | B85: 104542670 | C85: =+MaestraLP3[[#This Row],[CÓDIGO]]&MaestraLP3[[#Headers],[-]]&MaestraLP3[[#This Row],[UMV]] -> 104542670-C20 | D85: =+MaestraLP3[[#This Row],[CÓDIGO]]&MaestraLP3[[#Headers],[FS00]] -> 104542670FS00 | E85: BELTRÁN FRANZANI | F85: CAMILA UGARTE | G85: CAFE Y DERIVADOS | H85: CAFES DE GRANO MOLIDO | I85: CAFE MOL FILTRO CLASSICO LAVAZZA 226 g | J85: C20 | K85: UN | M85: =VLOOKUP(MaestraLP3[[#This Row],[UMV]],VALIDACIONES!J:L,3,0) -> Caja 20 Unidades | N85: SECO | O85: IFS | P85: 38570.4 | Q85: MANTIENE | R85: 119596 | S85: =IFERROR((MaestraLP3[[#This Row],[COSTO ]]/MaestraLP3[[#This Row],[COSTO OCT]]-1),0) -> 0 | T85: VIAS DESCONTINUACION | V85: =+VLOOKUP(MaestraLP3[[#This Row],[-]],'[1]BD MES'!$A:$N,14,0) -> 38570.4 | W85: 38570.4 | X85: =+(MaestraLP3[[#This Row],[COSTO ]]-MaestraLP3[[#This Row],[COSTO OCT AL 27-10]])/MaestraLP3[[#This Row],[COSTO OCT AL 27-10]] -> 0 | Y85: =++IF(Q85="HASTA AGOTAR STOCK","HASTA AGOTAR STOCK",IF(MaestraLP3[[#This Row],[PRECIO OCT]]=0,"NO PARA LP",IF(MaestraLP3[[#This Row],[PRECIO OCT]]=0,"INCORPORACIÓN",IF(AA85=0,"MANTIENE",IF(AA85<0,"BAJA",IF(AA85>0,"ALZA","")))))) -> MANTIENE | Z85: 119596 | AA85: =IF(Z85=0,"INDICAR PRECIO VTA",Z85-MaestraLP3[[#This Row],[PRECIO OCT]]) -> 0 | AB85: =+IFERROR((Z85-W85)/Z85,"-") -> 0.67749423 | AC85: =IFERROR(MaestraLP3[[#This Row],[PRECIO]]*MaestraLP3[[#This Row],[%MG UMV]],0) -> 81025.6 | AD85: 4.52 | AE85: =IFERROR(MaestraLP3[[#This Row],[MARGEN UNITARIO]]/MaestraLP3[[#This Row],[Peso Neto UMV (KG)]],0) -> 17926.018 | AF85: SI | AG85: 1 | AH85: 0.1 | AI85: 0 | AJ85: SI | AK85: SI
A86: LIQUIDACIÓN | B86: 104528970 | C86: =+MaestraLP3[[#This Row],[CÓDIGO]]&MaestraLP3[[#Headers],[-]]&MaestraLP3[[#This Row],[UMV]] -> 104528970-C06 | D86: =+MaestraLP3[[#This Row],[CÓDIGO]]&MaestraLP3[[#Headers],[FS00]] -> 104528970FS00 | E86: BELTRÁN FRANZANI | F86: CAMILA UGARTE | G86: CAFE Y DERIVADOS | H86: CAFES DE GRANO MOLIDO | I86: CAFE MOLIDO FILTRO CLASICO LAVAZZA 1 kg | J86: C06 | K86: UN | M86: =VLOOKUP(MaestraLP3[[#This Row],[UMV]],VALIDACIONES!J:L,3,0) -> Caja 6 Unidades | N86: SECO | O86: IFS | P86: 42000 | Q86: MANTIENE | R86: 112390 | S86: =IFERROR((MaestraLP3[[#This Row],[COSTO ]]/MaestraLP3[[#This Row],[COSTO OCT]]-1),0) -> 0 | T86: VIAS DESCONTINUACION | V86: =+VLOOKUP(MaestraLP3[[#This Row],[-]],'[1]BD MES'!$A:$N,14,0) -> 42000 | W86: 42000 | X86: =+(MaestraLP3[[#This Row],[COSTO ]]-MaestraLP3[[#This Row],[COSTO OCT AL 27-10]])/MaestraLP3[[#This Row],[COSTO OCT AL 27-10]] -> 0 | Y86: =++IF(Q86="HASTA AGOTAR STOCK","HASTA AGOTAR STOCK",IF(MaestraLP3[[#This Row],[PRECIO OCT]]=0,"NO PARA LP",IF(MaestraLP3[[#This Row],[PRECIO OCT]]=0,"INCORPORACIÓN",IF(AA86=0,"MANTIENE",IF(AA86<0,"BAJA",IF(AA86>0,"ALZA","")))))) -> MANTIENE | Z86: 112390 | AA86: =IF(Z86=0,"INDICAR PRECIO VTA",Z86-MaestraLP3[[#This Row],[PRECIO OCT]]) -> 0 | AB86: =+IFERROR((Z86-W86)/Z86,"-") -> 0.62630127 | AC86: =IFERROR(MaestraLP3[[#This Row],[PRECIO]]*MaestraLP3[[#This Row],[%MG UMV]],0) -> 70390 | AD86: 6 | AE86: =IFERROR(MaestraLP3[[#This Row],[MARGEN UNITARIO]]/MaestraLP3[[#This Row],[Peso Neto UMV (KG)]],0) -> 11731.667 | AF86: SI | AG86: 1 | AH86: 0.1 | AI86: 0 | AJ86: SI | AK86: SI
A87: LIQUIDACIÓN | B87: 104523790 | C87: =+MaestraLP3[[#This Row],[CÓDIGO]]&MaestraLP3[[#Headers],[-]]&MaestraLP3[[#This Row],[UMV]] -> 104523790-Z00 | D87: =+MaestraLP3[[#This Row],[CÓDIGO]]&MaestraLP3[[#Headers],[FS00]] -> 104523790FS00 | E87: BELTRÁN FRANZANI | F87: CAMILA UGARTE | G87: CAFE Y DERIVADOS | H87: CAPSULAS Y PODS | I87: CAPSULA DOBLE ESP GOLD SEL LAVAZZA 16 g | J87: Z00 | K87: UN | M87: =VLOOKUP(MaestraLP3[[#This Row],[UMV]],VALIDACIONES!J:L,3,0) -> Caja 100 Unidades | N87: SECO | O87: IFS | P87: 35140 | Q87: BAJA | R87: 63000 | S87: =IFERROR((MaestraLP3[[#This Row],[COSTO ]]/MaestraLP3[[#This Row],[COSTO OCT]]-1),0) -> 0 | T87: VIAS DESCONTINUACION | V87: =+VLOOKUP(MaestraLP3[[#This Row],[-]],'[1]BD MES'!$A:$N,14,0) -> 35140 | W87: 35140 | X87: =+(MaestraLP3[[#This Row],[COSTO ]]-MaestraLP3[[#This Row],[COSTO OCT AL 27-10]])/MaestraLP3[[#This Row],[COSTO OCT AL 27-10]] -> 0 | Y87: =++IF(Q87="HASTA AGOTAR STOCK","HASTA AGOTAR STOCK",IF(MaestraLP3[[#This Row],[PRECIO OCT]]=0,"NO PARA LP",IF(MaestraLP3[[#This Row],[PRECIO OCT]]=0,"INCORPORACIÓN",IF(AA87=0,"MANTIENE",IF(AA87<0,"BAJA",IF(AA87>0,"ALZA","")))))) -> ALZA | Z87: 65000 | AA87: =IF(Z87=0,"INDICAR PRECIO VTA",Z87-MaestraLP3[[#This Row],[PRECIO OCT]]) -> 2000 | AB87: =+IFERROR((Z87-W87)/Z87,"-") -> 0.45938462 | AC87: =IFERROR(MaestraLP3[[#This Row],[PRECIO]]*MaestraLP3[[#This Row],[%MG UMV]],0) -> 29860 | AD87: 1.1 | AE87: =IFERROR(MaestraLP3[[#This Row],[MARGEN UNITARIO]]/MaestraLP3[[#This Row],[Peso Neto UMV (KG)]],0) -> 27145.455 | AF87: NO | AG87: 2 | AH87: 0.1 | AI87: 0 | AJ87: SI | AK87: SI
A88: LIQUIDACIÓN | B88: 104523840 | C88: =+MaestraLP3[[#This Row],[CÓDIGO]]&MaestraLP3[[#Headers],[-]]&MaestraLP3[[#This Row],[UMV]] -> 104523840-Z00 | D88: =+MaestraLP3[[#This Row],[CÓDIGO]]&MaestraLP3[[#Headers],[FS00]] -> 104523840FS00 | E88: BELTRÁN FRANZANI | F88: CAMILA UGARTE | G88: CAFE Y DERIVADOS | H88: CAPSULAS Y PODS | I88: CAPSULA DOBLE ESP TOP CLASS LAVAZZA 16 g | J88: Z00 | K88: UN | M88: =VLOOKUP(MaestraLP3[[#This Row],[UMV]],VALIDACIONES!J:L,3,0) -> Caja 100 Unidades | N88: SECO | O88: IFS | P88: 35645 | Q88: BAJA | R88: 63000 | S88: =IFERROR((MaestraLP3[[#This Row],[COSTO ]]/MaestraLP3[[#This Row],[COSTO OCT]]-1),0) -> 0 | T88: VIAS DESCONTINUACION | V88: =+VLOOKUP(MaestraLP3[[#This Row],[-]],'[1]BD MES'!$A:$N,14,0) -> 35645 | W88: 35645 | X88: =+(MaestraLP3[[#This Row],[COSTO ]]-MaestraLP3[[#This Row],[COSTO OCT AL 27-10]])/MaestraLP3[[#This Row],[COSTO OCT AL 27-10]] -> 0 | Y88: =++IF(Q88="HASTA AGOTAR STOCK","HASTA AGOTAR STOCK",IF(MaestraLP3[[#This Row],[PRECIO OCT]]=0,"NO PARA LP",IF(MaestraLP3[[#This Row],[PRECIO OCT]]=0,"INCORPORACIÓN",IF(AA88=0,"MANTIENE",IF(AA88<0,"BAJA",IF(AA88>0,"ALZA","")))))) -> ALZA | Z88: 65000 | AA88: =IF(Z88=0,"INDICAR PRECIO VTA",Z88-MaestraLP3[[#This Row],[PRECIO OCT]]) -> 2000 | AB88: =+IFERROR((Z88-W88)/Z88,"-") -> 0.45161538 | AC88: =IFERROR(MaestraLP3[[#This Row],[PRECIO]]*MaestraLP3[[#This Row],[%MG UMV]],0) -> 29355 | AD88: 1.1 | AE88: =IFERROR(MaestraLP3[[#This Row],[MARGEN UNITARIO]]/MaestraLP3[[#This Row],[Peso Neto UMV (KG)]],0) -> 26686.364 | AF88: NO | AG88: 2 | AH88: 0.1 | AI88: 0 | AJ88: SI | AK88: SI
A89: LIQUIDACIÓN | B89: 104523800 | C89: =+MaestraLP3[[#This Row],[CÓDIGO]]&MaestraLP3[[#Headers],[-]]&MaestraLP3[[#This Row],[UMV]] -> 104523800-Z00 | D89: =+MaestraLP3[[#This Row],[CÓDIGO]]&MaestraLP3[[#Headers],[FS00]] -> 104523800FS00 | E89: BELTRÁN FRANZANI | F89: CAMILA UGARTE | G89: CAFE Y DERIVADOS | H89: CAPSULAS Y PODS | I89: CAPSULA ESPRESSO GOLD SELECT LAVAZZA 8 g | J89: Z00 | K89: UN | M89: =VLOOKUP(MaestraLP3[[#This Row],[UMV]],VALIDACIONES!J:L,3,0) -> Caja 100 Unidades | N89: SECO | O89: IFS | P89: 24146 | Q89: BAJA | R89: 37800 | S89: =IFERROR((MaestraLP3[[#This Row],[COSTO ]]/MaestraLP3[[#This Row],[COSTO OCT]]-1),0) -> 0 | T89: VIAS DESCONTINUACION | V89: =+VLOOKUP(MaestraLP3[[#This Row],[-]],'[1]BD MES'!$A:$N,14,0) -> 24146 | W89: 24146 | X89: =+(MaestraLP3[[#This Row],[COSTO ]]-MaestraLP3[[#This Row],[COSTO OCT AL 27-10]])/MaestraLP3[[#This Row],[COSTO OCT AL 27-10]] -> 0 | Y89: =++IF(Q89="HASTA AGOTAR STOCK","HASTA AGOTAR STOCK",IF(MaestraLP3[[#This Row],[PRECIO OCT]]=0,"NO PARA LP",IF(MaestraLP3[[#This Row],[PRECIO OCT]]=0,"INCORPORACIÓN",IF(AA89=0,"MANTIENE",IF(AA89<0,"BAJA",IF(AA89>0,"ALZA","")))))) -> ALZA | Z89: 39500 | AA89: =IF(Z89=0,"INDICAR PRECIO VTA",Z89-MaestraLP3[[#This Row],[PRECIO OCT]]) -> 1700 | AB89: =+IFERROR((Z89-W89)/Z89,"-") -> 0.38870886 | AC89: =IFERROR(MaestraLP3[[#This Row],[PRECIO]]*MaestraLP3[[#This Row],[%MG UMV]],0) -> 15354 | AD89: 0.8 | AE89: =IFERROR(MaestraLP3[[#This Row],[MARGEN UNITARIO]]/MaestraLP3[[#This Row],[Peso Neto UMV (KG)]],0) -> 19192.5 | AF89: NO | AG89: 2 | AH89: 0.1 | AI89: 0 | AJ89: SI | AK89: SI
A90: LIQUIDACIÓN | B90: 104523850 | C90: =+MaestraLP3[[#This Row],[CÓDIGO]]&MaestraLP3[[#Headers],[-]]&MaestraLP3[[#This Row],[UMV]] -> 104523850-Z00 | D90: =+MaestraLP3[[#This Row],[CÓDIGO]]&MaestraLP3[[#Headers],[FS00]] -> 104523850FS00 | E90: BELTRÁN FRANZANI | F90: CAMILA UGARTE | G90: CAFE Y DERIVADOS | H90: CAPSULAS Y PODS | I90: CAPSULA ESPRESSO TOP CLASS LAVAZZA 8 g | J90: Z00 | K90: UN | M90: =VLOOKUP(MaestraLP3[[#This Row],[UMV]],VALIDACIONES!J:L,3,0) -> Caja 100 Unidades | N90: SECO | O90: IFS | P90: 20544 | Q90: BAJA | R90: 37800 | S90: =IFERROR((MaestraLP3[[#This Row],[COSTO ]]/MaestraLP3[[#This Row],[COSTO OCT]]-1),0) -> 0 | T90: VIAS DESCONTINUACION | V90: =+VLOOKUP(MaestraLP3[[#This Row],[-]],'[1]BD MES'!$A:$N,14,0) -> 20544 | W90: 20544 | X90: =+(MaestraLP3[[#This Row],[COSTO ]]-MaestraLP3[[#This Row],[COSTO OCT AL 27-10]])/MaestraLP3[[#This Row],[COSTO OCT AL 27-10]] -> 0 | Y90: =++IF(Q90="HASTA AGOTAR STOCK","HASTA AGOTAR STOCK",IF(MaestraLP3[[#This Row],[PRECIO OCT]]=0,"NO PARA LP",IF(MaestraLP3[[#This Row],[PRECIO OCT]]=0,"INCORPORACIÓN",IF(AA90=0,"MANTIENE",IF(AA90<0,"BAJA",IF(AA90>0,"ALZA","")))))) -> ALZA | Z90: 39500 | AA90: =IF(Z90=0,"INDICAR PRECIO VTA",Z90-MaestraLP3[[#This Row],[PRECIO OCT]]) -> 1700 | AB90: =+IFERROR((Z90-W90)/Z90,"-") -> 0.47989873 | AC90: =IFERROR(MaestraLP3[[#This Row],[PRECIO]]*MaestraLP3[[#This Row],[%MG UMV]],0) -> 18956 | AD90: 0.8 | AE90: =IFERROR(MaestraLP3[[#This Row],[MARGEN UNITARIO]]/MaestraLP3[[#This Row],[Peso Neto UMV (KG)]],0) -> 23695 | AF90: NO | AG90: 2 | AH90: 0.1 | AI90: 0 | AJ90: SI | AK90: SI
A91: LIQUIDACIÓN | B91: 101710005 | C91: =+MaestraLP3[[#This Row],[CÓDIGO]]&MaestraLP3[[#Headers],[-]]&MaestraLP3[[#This Row],[UMV]] -> 101710005-C10 | D91: =+MaestraLP3[[#This Row],[CÓDIGO]]&MaestraLP3[[#Headers],[FS00]] -> 101710005FS00 | E91: BELTRÁN FRANZANI | F91: CAMILA UGARTE | G91: CAFE Y DERIVADOS | H91: DESCONTINUADOS | I91: **D**TE CLUB PREMIUM CEYLON 100BLS | J91: C10 | K91: UN | M91: =VLOOKUP(MaestraLP3[[#This Row],[UMV]],VALIDACIONES!J:L,3,0) -> Caja 10 Unidades | N91: SECO | O91: NFS | P91: 11764.9 | Q91: NO PARA LP | R91: 0 | S91: =IFERROR((MaestraLP3[[#This Row],[COSTO ]]/MaestraLP3[[#This Row],[COSTO OCT]]-1),0) -> 0 | T91: VIAS DESCONTINUACION | V91: =+VLOOKUP(MaestraLP3[[#This Row],[-]],'[1]BD MES'!$A:$N,14,0) -> 11764.9 | W91: 11764.9 | X91: =+(MaestraLP3[[#This Row],[COSTO ]]-MaestraLP3[[#This Row],[COSTO OCT AL 27-10]])/MaestraLP3[[#This Row],[COSTO OCT AL 27-10]] -> 0 | Y91: =++IF(Q91="HASTA AGOTAR STOCK","HASTA AGOTAR STOCK",IF(MaestraLP3[[#This Row],[PRECIO OCT]]=0,"NO PARA LP",IF(MaestraLP3[[#This Row],[PRECIO OCT]]=0,"INCORPORACIÓN",IF(AA91=0,"MANTIENE",IF(AA91<0,"BAJA",IF(AA91>0,"ALZA","")))))) -> NO PARA LP | Z91: 0 | AA91: =IF(Z91=0,"INDICAR PRECIO VTA",Z91-MaestraLP3[[#This Row],[PRECIO OCT]]) -> INDICAR PRECIO VTA | AB91: =+IFERROR((Z91-W91)/Z91,"-") -> - | AC91: =IFERROR(MaestraLP3[[#This Row],[PRECIO]]*MaestraLP3[[#This Row],[%MG UMV]],0) -> 0 | AD91: 1.7 | AE91: =IFERROR(MaestraLP3[[#This Row],[MARGEN UNITARIO]]/MaestraLP3[[#This Row],[Peso Neto UMV (KG)]],0) -> 0 | AF91: NO | AG91: 1 | AH91: 0 | AI91: 0 | AK91: NO
A92: LIQUIDACIÓN | B92: 104518430 | C92: =+MaestraLP3[[#This Row],[CÓDIGO]]&MaestraLP3[[#Headers],[-]]&MaestraLP3[[#This Row],[UMV]] -> 104518430-C12 | D92: =+MaestraLP3[[#This Row],[CÓDIGO]]&MaestraLP3[[#Headers],[FS00]] -> 104518430FS00 | E92: BELTRÁN FRANZANI | F92: CAMILA UGARTE | G92: CAFE Y DERIVADOS | H92: DESCONTINUADOS | I92: MUG LAVAZZA | J92: C12 | K92: UN | M92: =VLOOKUP(MaestraLP3[[#This Row],[UMV]],VALIDACIONES!J:L,3,0) -> Caja 12 Unidades | N92: SECO | O92: IFS | P92: 15791.4 | Q92: NO PARA LP | R92: 0 | S92: =IFERROR((MaestraLP3[[#This Row],[COSTO ]]/MaestraLP3[[#This Row],[COSTO OCT]]-1),0) -> 0 | T92: VIAS DESCONTINUACION | V92: =+VLOOKUP(MaestraLP3[[#This Row],[-]],'[1]BD MES'!$A:$N,14,0) -> 15791.4 | W92: 15791.4 | X92: =+(MaestraLP3[[#This Row],[COSTO ]]-MaestraLP3[[#This Row],[COSTO OCT AL 27-10]])/MaestraLP3[[#This Row],[COSTO OCT AL 27-10]] -> 0 | Y92: =++IF(Q92="HASTA AGOTAR STOCK","HASTA AGOTAR STOCK",IF(MaestraLP3[[#This Row],[PRECIO OCT]]=0,"NO PARA LP",IF(MaestraLP3[[#This Row],[PRECIO OCT]]=0,"INCORPORACIÓN",IF(AA92=0,"MANTIENE",IF(AA92<0,"BAJA",IF(AA92>0,"ALZA","")))))) -> NO PARA LP | Z92: 0 | AA92: =IF(Z92=0,"INDICAR PRECIO VTA",Z92-MaestraLP3[[#This Row],[PRECIO OCT]]) -> INDICAR PRECIO VTA | AB92: =+IFERROR((Z92-W92)/Z92,"-") -> - | AC92: =IFERROR(MaestraLP3[[#This Row],[PRECIO]]*MaestraLP3[[#This Row],[%MG UMV]],0) -> 0 | AD92: 0.6 | AE92: =IFERROR(MaestraLP3[[#This Row],[MARGEN UNITARIO]]/MaestraLP3[[#This Row],[Peso Neto UMV (KG)]],0) -> 0 | AF92: NO | AG92: 1 | AH92: 0 | AI92: 0 | AJ92: SI | AK92: NO
A93: LIQUIDACIÓN | B93: 968200370 | C93: =+MaestraLP3[[#This Row],[CÓDIGO]]&MaestraLP3[[#Headers],[-]]&MaestraLP3[[#This Row],[UMV]] -> 968200370-C06 | D93: =+MaestraLP3[[#This Row],[CÓDIGO]]&MaestraLP3[[#Headers],[FS00]] -> 968200370FS00 | E93: BELTRÁN FRANZANI | F93: CAMILA UGARTE | G93: CAFE Y DERIVADOS | H93: DESCONTINUADOS | I93: TAZA Y PLATO CHOCOLATE ERACLEA | J93: C06 | K93: C06 | M93: =VLOOKUP(MaestraLP3[[#This Row],[UMV]],VALIDACIONES!J:L,3,0) -> Caja 6 Unidades | N93: SECO | O93: IFS | P93: 26224.05 | Q93: NO PARA LP | R93: 0 | S93: =IFERROR((MaestraLP3[[#This Row],[COSTO ]]/MaestraLP3[[#This Row],[COSTO OCT]]-1),0) -> 0 | T93: VIAS DESCONTINUACION | V93: =+VLOOKUP(MaestraLP3[[#This Row],[-]],'[1]BD MES'!$A:$N,14,0) -> 26224.05 | W93: 26224.05 | X93: =+(MaestraLP3[[#This Row],[COSTO ]]-MaestraLP3[[#This Row],[COSTO OCT AL 27-10]])/MaestraLP3[[#This Row],[COSTO OCT AL 27-10]] -> 0 | Y93: =++IF(Q93="HASTA AGOTAR STOCK","HASTA AGOTAR STOCK",IF(MaestraLP3[[#This Row],[PRECIO OCT]]=0,"NO PARA LP",IF(MaestraLP3[[#This Row],[PRECIO OCT]]=0,"INCORPORACIÓN",IF(AA93=0,"MANTIENE",IF(AA93<0,"BAJA",IF(AA93>0,"ALZA","")))))) -> NO PARA LP | Z93: 0 | AA93: =IF(Z93=0,"INDICAR PRECIO VTA",Z93-MaestraLP3[[#This Row],[PRECIO OCT]]) -> INDICAR PRECIO VTA | AB93: =+IFERROR((Z93-W93)/Z93,"-") -> - | AC93: =IFERROR(MaestraLP3[[#This Row],[PRECIO]]*MaestraLP3[[#This Row],[%MG UMV]],0) -> 0 | AD93: 2.5 | AE93: =IFERROR(MaestraLP3[[#This Row],[MARGEN UNITARIO]]/MaestraLP3[[#This Row],[Peso Neto UMV (KG)]],0) -> 0 | AF93: NO | AG93: 1 | AH93: 0 | AI93: 0 | AK93: NO
A94: LIQUIDACIÓN | B94: 968200380 | C94: =+MaestraLP3[[#This Row],[CÓDIGO]]&MaestraLP3[[#Headers],[-]]&MaestraLP3[[#This Row],[UMV]] -> 968200380-C04 | D94: =+MaestraLP3[[#This Row],[CÓDIGO]]&MaestraLP3[[#Headers],[FS00]] -> 968200380FS00 | E94: BELTRÁN FRANZANI | F94: CAMILA UGARTE | G94: CAFE Y DERIVADOS | H94: DESCONTINUADOS | I94: TAZA Y PLATO TE WHITTINGTON | J94: C04 | K94: C04 | M94: =VLOOKUP(MaestraLP3[[#This Row],[UMV]],VALIDACIONES!J:L,3,0) -> Caja 4 Unidades | N94: SECO | O94: IFS | P94: 17327.22 | Q94: NO PARA LP | R94: 0 | S94: =IFERROR((MaestraLP3[[#This Row],[COSTO ]]/MaestraLP3[[#This Row],[COSTO OCT]]-1),0) -> 0 | T94: VIAS DESCONTINUACION | V94: =+VLOOKUP(MaestraLP3[[#This Row],[-]],'[1]BD MES'!$A:$N,14,0) -> 17327.22 | W94: 17327.22 | X94: =+(MaestraLP3[[#This Row],[COSTO ]]-MaestraLP3[[#This Row],[COSTO OCT AL 27-10]])/MaestraLP3[[#This Row],[COSTO OCT AL 27-10]] -> 0 | Y94: =++IF(Q94="HASTA AGOTAR STOCK","HASTA AGOTAR STOCK",IF(MaestraLP3[[#This Row],[PRECIO OCT]]=0,"NO PARA LP",IF(MaestraLP3[[#This Row],[PRECIO OCT]]=0,"INCORPORACIÓN",IF(AA94=0,"MANTIENE",IF(AA94<0,"BAJA",IF(AA94>0,"ALZA","")))))) -> NO PARA LP | Z94: 0 | AA94: =IF(Z94=0,"INDICAR PRECIO VTA",Z94-MaestraLP3[[#This Row],[PRECIO OCT]]) -> INDICAR PRECIO VTA | AB94: =+IFERROR((Z94-W94)/Z94,"-") -> - | AC94: =IFERROR(MaestraLP3[[#This Row],[PRECIO]]*MaestraLP3[[#This Row],[%MG UMV]],0) -> 0 | AD94: 2.5 | AE94: =IFERROR(MaestraLP3[[#This Row],[MARGEN UNITARIO]]/MaestraLP3[[#This Row],[Peso Neto UMV (KG)]],0) -> 0 | AF94: NO | AG94: 1 | AH94: 0.05 | AI94: 0.05 | AK94: NO
A95: LIQUIDACIÓN | B95: 101710002 | C95: =+MaestraLP3[[#This Row],[CÓDIGO]]&MaestraLP3[[#Headers],[-]]&MaestraLP3[[#This Row],[UMV]] -> 101710002-C50 | D95: =+MaestraLP3[[#This Row],[CÓDIGO]]&MaestraLP3[[#Headers],[FS00]] -> 101710002FS00 | E95: BELTRÁN FRANZANI | F95: CAMILA UGARTE | G95: CAFE Y DERIVADOS | H95: DESCONTINUADOS | I95: TE CLUB ORIGINAL 20BLS | J95: C50 | K95: UN | M95: =VLOOKUP(MaestraLP3[[#This Row],[UMV]],VALIDACIONES!J:L,3,0) -> Caja 50 Unidades | N95: SECO | O95: NFS | P95: 14213 | Q95: NO PARA LP | R95: 0 | S95: =IFERROR((MaestraLP3[[#This Row],[COSTO ]]/MaestraLP3[[#This Row],[COSTO OCT]]-1),0) -> 0 | T95: VIAS DESCONTINUACION | V95: =+VLOOKUP(MaestraLP3[[#This Row],[-]],'[1]BD MES'!$A:$N,14,0) -> 14213 | W95: 14213 | X95: =+(MaestraLP3[[#This Row],[COSTO ]]-MaestraLP3[[#This Row],[COSTO OCT AL 27-10]])/MaestraLP3[[#This Row],[COSTO OCT AL 27-10]] -> 0 | Y95: =++IF(Q95="HASTA AGOTAR STOCK","HASTA AGOTAR STOCK",IF(MaestraLP3[[#This Row],[PRECIO OCT]]=0,"NO PARA LP",IF(MaestraLP3[[#This Row],[PRECIO OCT]]=0,"INCORPORACIÓN",IF(AA95=0,"MANTIENE",IF(AA95<0,"BAJA",IF(AA95>0,"ALZA","")))))) -> NO PARA LP | Z95: 0 | AA95: =IF(Z95=0,"INDICAR PRECIO VTA",Z95-MaestraLP3[[#This Row],[PRECIO OCT]]) -> INDICAR PRECIO VTA | AB95: =+IFERROR((Z95-W95)/Z95,"-") -> - | AC95: =IFERROR(MaestraLP3[[#This Row],[PRECIO]]*MaestraLP3[[#This Row],[%MG UMV]],0) -> 0 | AD95: 1.7 | AE95: =IFERROR(MaestraLP3[[#This Row],[MARGEN UNITARIO]]/MaestraLP3[[#This Row],[Peso Neto UMV (KG)]],0) -> 0 | AF95: NO | AG95: 1 | AH95: 0 | AI95: 0 | AK95: NO
A96: LIQUIDACIÓN | B96: 968200390 | C96: =+MaestraLP3[[#This Row],[CÓDIGO]]&MaestraLP3[[#Headers],[-]]&MaestraLP3[[#This Row],[UMV]] -> 968200390-UN | D96: =+MaestraLP3[[#This Row],[CÓDIGO]]&MaestraLP3[[#Headers],[FS00]] -> 968200390FS00 | E96: BELTRÁN FRANZANI | F96: CAMILA UGARTE | G96: CAFE Y DERIVADOS | H96: DESCONTINUADOS | I96: TETERA WHITTINGTON | J96: UN | K96: UN | M96: =VLOOKUP(MaestraLP3[[#This Row],[UMV]],VALIDACIONES!J:L,3,0) -> Unidad | N96: SECO | O96: IFS | P96: 8718.28 | Q96: NO PARA LP | R96: 0 | S96: =IFERROR((MaestraLP3[[#This Row],[COSTO ]]/MaestraLP3[[#This Row],[COSTO OCT]]-1),0) -> 0 | T96: VIAS DESCONTINUACION | V96: =+VLOOKUP(MaestraLP3[[#This Row],[-]],'[1]BD MES'!$A:$N,14,0) -> 8718.28 | W96: 8718.28 | X96: =+(MaestraLP3[[#This Row],[COSTO ]]-MaestraLP3[[#This Row],[COSTO OCT AL 27-10]])/MaestraLP3[[#This Row],[COSTO OCT AL 27-10]] -> 0 | Y96: =++IF(Q96="HASTA AGOTAR STOCK","HASTA AGOTAR STOCK",IF(MaestraLP3[[#This Row],[PRECIO OCT]]=0,"NO PARA LP",IF(MaestraLP3[[#This Row],[PRECIO OCT]]=0,"INCORPORACIÓN",IF(AA96=0,"MANTIENE",IF(AA96<0,"BAJA",IF(AA96>0,"ALZA","")))))) -> NO PARA LP | Z96: 0 | AA96: =IF(Z96=0,"INDICAR PRECIO VTA",Z96-MaestraLP3[[#This Row],[PRECIO OCT]]) -> INDICAR PRECIO VTA | AB96: =+IFERROR((Z96-W96)/Z96,"-") -> - | AC96: =IFERROR(MaestraLP3[[#This Row],[PRECIO]]*MaestraLP3[[#This Row],[%MG UMV]],0) -> 0 | AD96: 0.6 | AE96: =IFERROR(MaestraLP3[[#This Row],[MARGEN UNITARIO]]/MaestraLP3[[#This Row],[Peso Neto UMV (KG)]],0) -> 0 | AF96: NO | AG96: 1 | AH96: 0.1 | AI96: 0.1 | AK96: NO
A97: LIQUIDACIÓN | B97: 104518210 | C97: =+MaestraLP3[[#This Row],[CÓDIGO]]&MaestraLP3[[#Headers],[-]]&MaestraLP3[[#This Row],[UMV]] -> 104518210-C06 | D97: =+MaestraLP3[[#This Row],[CÓDIGO]]&MaestraLP3[[#Headers],[FS00]] -> 104518210FS00 | E97: BELTRÁN FRANZANI | F97: CAMILA UGARTE | G97: CAFE Y DERIVADOS | H97: DESCONTINUADOS | I97: VASO DOBLE FONDO LAVAZZA 140 cc | J97: C06 | K97: UN | M97: =VLOOKUP(MaestraLP3[[#This Row],[UMV]],VALIDACIONES!J:L,3,0) -> Caja 6 Unidades | N97: SECO | O97: IFS | P97: 8186.64 | Q97: NO PARA LP | R97: 0 | S97: =IFERROR((MaestraLP3[[#This Row],[COSTO ]]/MaestraLP3[[#This Row],[COSTO OCT]]-1),0) -> 0 | T97: VIAS DESCONTINUACION | V97: =+VLOOKUP(MaestraLP3[[#This Row],[-]],'[1]BD MES'!$A:$N,14,0) -> 8186.64 | W97: 8186.64 | X97: =+(MaestraLP3[[#This Row],[COSTO ]]-MaestraLP3[[#This Row],[COSTO OCT AL 27-10]])/MaestraLP3[[#This Row],[COSTO OCT AL 27-10]] -> 0 | Y97: =++IF(Q97="HASTA AGOTAR STOCK","HASTA AGOTAR STOCK",IF(MaestraLP3[[#This Row],[PRECIO OCT]]=0,"NO PARA LP",IF(MaestraLP3[[#This Row],[PRECIO OCT]]=0,"INCORPORACIÓN",IF(AA97=0,"MANTIENE",IF(AA97<0,"BAJA",IF(AA97>0,"ALZA","")))))) -> NO PARA LP | Z97: 0 | AA97: =IF(Z97=0,"INDICAR PRECIO VTA",Z97-MaestraLP3[[#This Row],[PRECIO OCT]]) -> INDICAR PRECIO VTA | AB97: =+IFERROR((Z97-W97)/Z97,"-") -> - | AC97: =IFERROR(MaestraLP3[[#This Row],[PRECIO]]*MaestraLP3[[#This Row],[%MG UMV]],0) -> 0 | AD97: 1.2 | AE97: =IFERROR(MaestraLP3[[#This Row],[MARGEN UNITARIO]]/MaestraLP3[[#This Row],[Peso Neto UMV (KG)]],0) -> 0 | AF97: NO | AG97: 1 | AH97: 0.05 | AI97: 0.05 | AJ97: SI | AK97: NO
A98: LIQUIDACIÓN | B98: 104517040 | C98: =+MaestraLP3[[#This Row],[CÓDIGO]]&MaestraLP3[[#Headers],[-]]&MaestraLP3[[#This Row],[UMV]] -> 104517040-C20 | D98: =+MaestraLP3[[#This Row],[CÓDIGO]]&MaestraLP3[[#Headers],[FS00]] -> 104517040FS00 | E98: BELTRÁN FRANZANI | F98: CAMILA UGARTE | G98: CAFE Y DERIVADOS | H98: INSUMOS VENDING | I98: LECHE EN POLVO VENDING RISTORA 500 g | J98: C20 | K98: UN | M98: =VLOOKUP(MaestraLP3[[#This Row],[UMV]],VALIDACIONES!J:L,3,0) -> Caja 20 Unidades | N98: SECO | O98: NFS | P98: 87550 | Q98: MANTIENE | R98: 155000 | S98: =IFERROR((MaestraLP3[[#This Row],[COSTO ]]/MaestraLP3[[#This Row],[COSTO OCT]]-1),0) -> 0 | T98: VIAS DESCONTINUACION | V98: =+VLOOKUP(MaestraLP3[[#This Row],[-]],'[1]BD MES'!$A:$N,14,0) -> 87550 | W98: 87550 | X98: =+(MaestraLP3[[#This Row],[COSTO ]]-MaestraLP3[[#This Row],[COSTO OCT AL 27-10]])/MaestraLP3[[#This Row],[COSTO OCT AL 27-10]] -> 0 | Y98: =++IF(Q98="HASTA AGOTAR STOCK","HASTA AGOTAR STOCK",IF(MaestraLP3[[#This Row],[PRECIO OCT]]=0,"NO PARA LP",IF(MaestraLP3[[#This Row],[PRECIO OCT]]=0,"INCORPORACIÓN",IF(AA98=0,"MANTIENE",IF(AA98<0,"BAJA",IF(AA98>0,"ALZA","")))))) -> MANTIENE | Z98: 155000 | AA98: =IF(Z98=0,"INDICAR PRECIO VTA",Z98-MaestraLP3[[#This Row],[PRECIO OCT]]) -> 0 | AB98: =+IFERROR((Z98-W98)/Z98,"-") -> 0.43516129 | AC98: =IFERROR(MaestraLP3[[#This Row],[PRECIO]]*MaestraLP3[[#This Row],[%MG UMV]],0) -> 67450 | AD98: 10 | AE98: =IFERROR(MaestraLP3[[#This Row],[MARGEN UNITARIO]]/MaestraLP3[[#This Row],[Peso Neto UMV (KG)]],0) -> 6745 | AF98: SI | AG98: 1 | AH98: 0.1 | AI98: 0 | AK98: NO
A99: LIQUIDACIÓN | B99: 150000186 | C99: =+MaestraLP3[[#This Row],[CÓDIGO]]&MaestraLP3[[#Headers],[-]]&MaestraLP3[[#This Row],[UMV]] -> 150000186-D16 | D99: =+MaestraLP3[[#This Row],[CÓDIGO]]&MaestraLP3[[#Headers],[FS00]] -> 150000186FS00 | E99: BELTRÁN FRANZANI | F99: CAMILA UGARTE | G99: CAFE Y DERIVADOS | H99: TE Y OTRAS BEBIDAS CALIENTES | I99: TE ROYAL CEYLAN LIPTON 100 uds. | J99: D16 | K99: UN | M99: =VLOOKUP(MaestraLP3[[#This Row],[UMV]],VALIDACIONES!J:L,3,0) -> Display 16 Unidades | N99: SECO | O99: NFS | P99: 78915.2 | Q99: MANTIENE | R99: 132000 | S99: =IFERROR((MaestraLP3[[#This Row],[COSTO ]]/MaestraLP3[[#This Row],[COSTO OCT]]-1),0) -> 0 | T99: VIAS DESCONTINUACION | V99: =+VLOOKUP(MaestraLP3[[#This Row],[-]],'[1]BD MES'!$A:$N,14,0) -> 78915.2 | W99: 78915.2 | X99: =+(MaestraLP3[[#This Row],[COSTO ]]-MaestraLP3[[#This Row],[COSTO OCT AL 27-10]])/MaestraLP3[[#This Row],[COSTO OCT AL 27-10]] -> 0 | Y99: =++IF(Q99="HASTA AGOTAR STOCK","HASTA AGOTAR STOCK",IF(MaestraLP3[[#This Row],[PRECIO OCT]]=0,"NO PARA LP",IF(MaestraLP3[[#This Row],[PRECIO OCT]]=0,"INCORPORACIÓN",IF(AA99=0,"MANTIENE",IF(AA99<0,"BAJA",IF(AA99>0,"ALZA","")))))) -> MANTIENE | Z99: 132000 | AA99: =IF(Z99=0,"INDICAR PRECIO VTA",Z99-MaestraLP3[[#This Row],[PRECIO OCT]]) -> 0 | AB99: =+IFERROR((Z99-W99)/Z99,"-") -> 0.40215758 | AC99: =IFERROR(MaestraLP3[[#This Row],[PRECIO]]*MaestraLP3[[#This Row],[%MG UMV]],0) -> 53084.8 | AD99: 5.296 | AE99: =IFERROR(MaestraLP3[[#This Row],[MARGEN UNITARIO]]/MaestraLP3[[#This Row],[Peso Neto UMV (KG)]],0) -> 10023.565 | AF99: SI | AG99: 1 | AH99: 0.1 | AI99: 0.1 | AK99: SI
A100: LIQUIDACIÓN | B100: 150000188 | C100: =+MaestraLP3[[#This Row],[CÓDIGO]]&MaestraLP3[[#Headers],[-]]&MaestraLP3[[#This Row],[UMV]] -> 150000188-D16 | D100: =+MaestraLP3[[#This Row],[CÓDIGO]]&MaestraLP3[[#Headers],[FS00]] -> 150000188FS00 | E100: BELTRÁN FRANZANI | F100: CAMILA UGARTE | G100: CAFE Y DERIVADOS | H100: TE Y OTRAS BEBIDAS CALIENTES | I100: TE YELLOW LABEL LIPTON 100 uds. | J100: D16 | K100: UN | M100: =VLOOKUP(MaestraLP3[[#This Row],[UMV]],VALIDACIONES!J:L,3,0) -> Display 16 Unidades | N100: SECO | O100: NFS | P100: 75420.96 | Q100: MANTIENE | R100: 125000 | S100: =IFERROR((MaestraLP3[[#This Row],[COSTO ]]/MaestraLP3[[#This Row],[COSTO OCT]]-1),0) -> 0 | T100: VIAS DESCONTINUACION | V100: =+VLOOKUP(MaestraLP3[[#This Row],[-]],'[1]BD MES'!$A:$N,14,0) -> 75420.96 | W100: 75420.96 | X100: =+(MaestraLP3[[#This Row],[COSTO ]]-MaestraLP3[[#This Row],[COSTO OCT AL 27-10]])/MaestraLP3[[#This Row],[COSTO OCT AL 27-10]] -> 0 | Y100: =++IF(Q100="HASTA AGOTAR STOCK","HASTA AGOTAR STOCK",IF(MaestraLP3[[#This Row],[PRECIO OCT]]=0,"NO PARA LP",IF(MaestraLP3[[#This Row],[PRECIO OCT]]=0,"INCORPORACIÓN",IF(AA100=0,"MANTIENE",IF(AA100<0,"BAJA",IF(AA100>0,"ALZA","")))))) -> MANTIENE | Z100: 125000 | AA100: =IF(Z100=0,"INDICAR PRECIO VTA",Z100-MaestraLP3[[#This Row],[PRECIO OCT]]) -> 0 | AB100: =+IFERROR((Z100-W100)/Z100,"-") -> 0.39663232 | AC100: =IFERROR(MaestraLP3[[#This Row],[PRECIO]]*MaestraLP3[[#This Row],[%MG UMV]],0) -> 49579.04 | AD100: 5.616 | AE100: =IFERROR(MaestraLP3[[#This Row],[MARGEN UNITARIO]]/MaestraLP3[[#This Row],[Peso Neto UMV (KG)]],0) -> 8828.1766 | AF100: SI | AG100: 1 | AH100: 0.1 | AI100: 0.1 | AK100: SI
A101: LIQUIDACIÓN | B101: 104517980 | C101: =+MaestraLP3[[#This Row],[CÓDIGO]]&MaestraLP3[[#Headers],[-]]&MaestraLP3[[#This Row],[UMV]] -> 104517980-C10 | D101: =+MaestraLP3[[#This Row],[CÓDIGO]]&MaestraLP3[[#Headers],[FS00]] -> 104517980FS00 | E101: BELTRÁN FRANZANI | F101: CAMILA UGARTE | G101: MAQUINAS Y REPUESTOS | H101: ACCESORIOS | I101: PAELLERAS 37 cm | J101: C10 | K101: UN | M101: =VLOOKUP(MaestraLP3[[#This Row],[UMV]],VALIDACIONES!J:L,3,0) -> Caja 10 Unidades | N101: SECO | O101: IFS | P101: 56522.1 | Q101: ALZA | R101: 82220 | S101: =IFERROR((MaestraLP3[[#This Row],[COSTO ]]/MaestraLP3[[#This Row],[COSTO OCT]]-1),0) -> 0 | T101: VIAS DESCONTINUACION | V101: =+VLOOKUP(MaestraLP3[[#This Row],[-]],'[1]BD MES'!$A:$N,14,0) -> 56522.1 | W101: 56522.1 | X101: =+(MaestraLP3[[#This Row],[COSTO ]]-MaestraLP3[[#This Row],[COSTO OCT AL 27-10]])/MaestraLP3[[#This Row],[COSTO OCT AL 27-10]] -> 0 | Y101: =++IF(Q101="HASTA AGOTAR STOCK","HASTA AGOTAR STOCK",IF(MaestraLP3[[#This Row],[PRECIO OCT]]=0,"NO PARA LP",IF(MaestraLP3[[#This Row],[PRECIO OCT]]=0,"INCORPORACIÓN",IF(AA101=0,"MANTIENE",IF(AA101<0,"BAJA",IF(AA101>0,"ALZA","")))))) -> MANTIENE | Z101: 82220 | AA101: =IF(Z101=0,"INDICAR PRECIO VTA",Z101-MaestraLP3[[#This Row],[PRECIO OCT]]) -> 0 | AB101: =+IFERROR((Z101-W101)/Z101,"-") -> 0.31255047 | AC101: =IFERROR(MaestraLP3[[#This Row],[PRECIO]]*MaestraLP3[[#This Row],[%MG UMV]],0) -> 25697.9 | AD101: 40 | AE101: =IFERROR(MaestraLP3[[#This Row],[MARGEN UNITARIO]]/MaestraLP3[[#This Row],[Peso Neto UMV (KG)]],0) -> 642.4475 | AF101: NO | AG101: 1 | AH101: 0 | AI101: 0 | AK101: NO
A102: LIQUIDACIÓN | B102: 104517800 | C102: =+MaestraLP3[[#This Row],[CÓDIGO]]&MaestraLP3[[#Headers],[-]]&MaestraLP3[[#This Row],[UMV]] -> 104517800-UN | D102: =+MaestraLP3[[#This Row],[CÓDIGO]]&MaestraLP3[[#Headers],[FS00]] -> 104517800FS00 | E102: BELTRÁN FRANZANI | F102: CAMILA UGARTE | G102: MAQUINAS Y REPUESTOS | H102: DESCONTINUADOS | I102: DOSIFICADOR SALSA CHOCOLATE 1,89 l MONIN | J102: UN | K102: UN | M102: =VLOOKUP(MaestraLP3[[#This Row],[UMV]],VALIDACIONES!J:L,3,0) -> Unidad | N102: SECO | O102: IFS | P102: 2241.5 | Q102: NO PARA LP | R102: 0 | S102: =IFERROR((MaestraLP3[[#This Row],[COSTO ]]/MaestraLP3[[#This Row],[COSTO OCT]]-1),0) -> 0 | T102: VIAS DESCONTINUACION | V102: =+VLOOKUP(MaestraLP3[[#This Row],[-]],'[1]BD MES'!$A:$N,14,0) -> 2241.5 | W102: 2241.5 | X102: =+(MaestraLP3[[#This Row],[COSTO ]]-MaestraLP3[[#This Row],[COSTO OCT AL 27-10]])/MaestraLP3[[#This Row],[COSTO OCT AL 27-10]] -> 0 | Y102: =++IF(Q102="HASTA AGOTAR STOCK","HASTA AGOTAR STOCK",IF(MaestraLP3[[#This Row],[PRECIO OCT]]=0,"NO PARA LP",IF(MaestraLP3[[#This Row],[PRECIO OCT]]=0,"INCORPORACIÓN",IF(AA102=0,"MANTIENE",IF(AA102<0,"BAJA",IF(AA102>0,"ALZA","")))))) -> NO PARA LP | Z102: 0 | AA102: =IF(Z102=0,"INDICAR PRECIO VTA",Z102-MaestraLP3[[#This Row],[PRECIO OCT]]) -> INDICAR PRECIO VTA | AB102: =+IFERROR((Z102-W102)/Z102,"-") -> - | AC102: =IFERROR(MaestraLP3[[#This Row],[PRECIO]]*MaestraLP3[[#This Row],[%MG UMV]],0) -> 0 | AD102: 0.01 | AE102: =IFERROR(MaestraLP3[[#This Row],[MARGEN UNITARIO]]/MaestraLP3[[#This Row],[Peso Neto UMV (KG)]],0) -> 0 | AF102: NO | AG102: 1 | AH102: 0 | AI102: 0 | AK102: NO
A103: LIQUIDACIÓN | B103: 104517780 | C103: =+MaestraLP3[[#This Row],[CÓDIGO]]&MaestraLP3[[#Headers],[-]]&MaestraLP3[[#This Row],[UMV]] -> 104517780-UN | D103: =+MaestraLP3[[#This Row],[CÓDIGO]]&MaestraLP3[[#Headers],[FS00]] -> 104517780FS00 | E103: BELTRÁN FRANZANI | F103: CAMILA UGARTE | G103: MAQUINAS Y REPUESTOS | H103: DESCONTINUADOS | I103: DOSIFICADOR SYRUP 750 ml MONIN | J103: UN | K103: UN | M103: =VLOOKUP(MaestraLP3[[#This Row],[UMV]],VALIDACIONES!J:L,3,0) -> Unidad | N103: SECO | O103: IFS | P103: 1467 | Q103: NO PARA LP | R103: 0 | S103: =IFERROR((MaestraLP3[[#This Row],[COSTO ]]/MaestraLP3[[#This Row],[COSTO OCT]]-1),0) -> 0 | T103: VIAS DESCONTINUACION | V103: =+VLOOKUP(MaestraLP3[[#This Row],[-]],'[1]BD MES'!$A:$N,14,0) -> 1467 | W103: 1467 | X103: =+(MaestraLP3[[#This Row],[COSTO ]]-MaestraLP3[[#This Row],[COSTO OCT AL 27-10]])/MaestraLP3[[#This Row],[COSTO OCT AL 27-10]] -> 0 | Y103: =++IF(Q103="HASTA AGOTAR STOCK","HASTA AGOTAR STOCK",IF(MaestraLP3[[#This Row],[PRECIO OCT]]=0,"NO PARA LP",IF(MaestraLP3[[#This Row],[PRECIO OCT]]=0,"INCORPORACIÓN",IF(AA103=0,"MANTIENE",IF(AA103<0,"BAJA",IF(AA103>0,"ALZA","")))))) -> NO PARA LP | Z103: 0 | AA103: =IF(Z103=0,"INDICAR PRECIO VTA",Z103-MaestraLP3[[#This Row],[PRECIO OCT]]) -> INDICAR PRECIO VTA | AB103: =+IFERROR((Z103-W103)/Z103,"-") -> - | AC103: =IFERROR(MaestraLP3[[#This Row],[PRECIO]]*MaestraLP3[[#This Row],[%MG UMV]],0) -> 0 | AD103: 0.01 | AE103: =IFERROR(MaestraLP3[[#This Row],[MARGEN UNITARIO]]/MaestraLP3[[#This Row],[Peso Neto UMV (KG)]],0) -> 0 | AF103: NO | AG103: 1 | AH103: 0 | AI103: 0 | AK103: NO
A104: LIQUIDACIÓN | B104: 40009381 | C104: =+MaestraLP3[[#This Row],[CÓDIGO]]&MaestraLP3[[#Headers],[-]]&MaestraLP3[[#This Row],[UMV]] -> 40009381-UN | D104: =+MaestraLP3[[#This Row],[CÓDIGO]]&MaestraLP3[[#Headers],[FS00]] -> 40009381FS00 | E104: BELTRÁN FRANZANI | F104: CAMILA UGARTE | G104: MAQUINAS Y REPUESTOS | H104: DESCONTINUADOS | I104: FABRICA DE HIELO 220-240 v 50 hz 370 w | J104: UN | K104: UN | M104: =VLOOKUP(MaestraLP3[[#This Row],[UMV]],VALIDACIONES!J:L,3,0) -> Unidad | N104: SECO | O104: IFS | P104: 556114 | Q104: NO PARA LP | R104: 0 | S104: =IFERROR((MaestraLP3[[#This Row],[COSTO ]]/MaestraLP3[[#This Row],[COSTO OCT]]-1),0) -> 0 | T104: VIAS DESCONTINUACION | V104: =+VLOOKUP(MaestraLP3[[#This Row],[-]],'[1]BD MES'!$A:$N,14,0) -> 556114 | W104: 556114 | X104: =+(MaestraLP3[[#This Row],[COSTO ]]-MaestraLP3[[#This Row],[COSTO OCT AL 27-10]])/MaestraLP3[[#This Row],[COSTO OCT AL 27-10]] -> 0 | Y104: =++IF(Q104="HASTA AGOTAR STOCK","HASTA AGOTAR STOCK",IF(MaestraLP3[[#This Row],[PRECIO OCT]]=0,"NO PARA LP",IF(MaestraLP3[[#This Row],[PRECIO OCT]]=0,"INCORPORACIÓN",IF(AA104=0,"MANTIENE",IF(AA104<0,"BAJA",IF(AA104>0,"ALZA","")))))) -> NO PARA LP | Z104: 0 | AA104: =IF(Z104=0,"INDICAR PRECIO VTA",Z104-MaestraLP3[[#This Row],[PRECIO OCT]]) -> INDICAR PRECIO VTA | AB104: =+IFERROR((Z104-W104)/Z104,"-") -> - | AC104: =IFERROR(MaestraLP3[[#This Row],[PRECIO]]*MaestraLP3[[#This Row],[%MG UMV]],0) -> 0 | AD104: 48 | AE104: =IFERROR(MaestraLP3[[#This Row],[MARGEN UNITARIO]]/MaestraLP3[[#This Row],[Peso Neto UMV (KG)]],0) -> 0 | AF104: NO | AG104: 1 | AH104: 0 | AI104: 0 | AK104: NO
A105: LIQUIDACIÓN | B105: 40002120 | C105: =+MaestraLP3[[#This Row],[CÓDIGO]]&MaestraLP3[[#Headers],[-]]&MaestraLP3[[#This Row],[UMV]] -> 40002120-UN | D105: =+MaestraLP3[[#This Row],[CÓDIGO]]&MaestraLP3[[#Headers],[FS00]] -> 40002120FS00 | E105: BELTRÁN FRANZANI | F105: CAMILA UGARTE | G105: MAQUINAS Y REPUESTOS | H105: DESCONTINUADOS | I105: FILTRO PAPEL TITAN BUNN | J105: UN | K105: UN | M105: =VLOOKUP(MaestraLP3[[#This Row],[UMV]],VALIDACIONES!J:L,3,0) -> Unidad | N105: SECO | O105: IFS | P105: 13562.41 | Q105: NO PARA LP | R105: 0 | S105: =IFERROR((MaestraLP3[[#This Row],[COSTO ]]/MaestraLP3[[#This Row],[COSTO OCT]]-1),0) -> 0 | T105: VIAS DESCONTINUACION | V105: =+VLOOKUP(MaestraLP3[[#This Row],[-]],'[1]BD MES'!$A:$N,14,0) -> 13562.41 | W105: 13562.41 | X105: =+(MaestraLP3[[#This Row],[COSTO ]]-MaestraLP3[[#This Row],[COSTO OCT AL 27-10]])/MaestraLP3[[#This Row],[COSTO OCT AL 27-10]] -> 0 | Y105: =++IF(Q105="HASTA AGOTAR STOCK","HASTA AGOTAR STOCK",IF(MaestraLP3[[#This Row],[PRECIO OCT]]=0,"NO PARA LP",IF(MaestraLP3[[#This Row],[PRECIO OCT]]=0,"INCORPORACIÓN",IF(AA105=0,"MANTIENE",IF(AA105<0,"BAJA",IF(AA105>0,"ALZA","")))))) -> NO PARA LP | Z105: 0 | AA105: =IF(Z105=0,"INDICAR PRECIO VTA",Z105-MaestraLP3[[#This Row],[PRECIO OCT]]) -> INDICAR PRECIO VTA | AB105: =+IFERROR((Z105-W105)/Z105,"-") -> - | AC105: =IFERROR(MaestraLP3[[#This Row],[PRECIO]]*MaestraLP3[[#This Row],[%MG UMV]],0) -> 0 | AD105: 0.24 | AE105: =IFERROR(MaestraLP3[[#This Row],[MARGEN UNITARIO]]/MaestraLP3[[#This Row],[Peso Neto UMV (KG)]],0) -> 0 | AF105: NO | AG105: 1 | AH105: 0 | AI105: 0 | AK105: NO
A106: LIQUIDACIÓN | B106: 40522160 | C106: =+MaestraLP3[[#This Row],[CÓDIGO]]&MaestraLP3[[#Headers],[-]]&MaestraLP3[[#This Row],[UMV]] -> 40522160-UN | D106: =+MaestraLP3[[#This Row],[CÓDIGO]]&MaestraLP3[[#Headers],[FS00]] -> 40522160FS00 | E106: BELTRÁN FRANZANI | F106: CAMILA UGARTE | G106: MAQUINAS Y REPUESTOS | H106: DESCONTINUADOS | I106: HORNO CONVECCION 4 BANDEJAS ALFA43XEH | J106: UN | K106: UN | M106: =VLOOKUP(MaestraLP3[[#This Row],[UMV]],VALIDACIONES!J:L,3,0) -> Unidad | N106: SECO | O106: IFS | P106: 2970108 | Q106: NO PARA LP | R106: 0 | S106: =IFERROR((MaestraLP3[[#This Row],[COSTO ]]/MaestraLP3[[#This Row],[COSTO OCT]]-1),0) -> 0 | T106: VIAS DESCONTINUACION | V106: =+VLOOKUP(MaestraLP3[[#This Row],[-]],'[1]BD MES'!$A:$N,14,0) -> 2970108 | W106: 2970108 | X106: =+(MaestraLP3[[#This Row],[COSTO ]]-MaestraLP3[[#This Row],[COSTO OCT AL 27-10]])/MaestraLP3[[#This Row],[COSTO OCT AL 27-10]] -> 0 | Y106: =++IF(Q106="HASTA AGOTAR STOCK","HASTA AGOTAR STOCK",IF(MaestraLP3[[#This Row],[PRECIO OCT]]=0,"NO PARA LP",IF(MaestraLP3[[#This Row],[PRECIO OCT]]=0,"INCORPORACIÓN",IF(AA106=0,"MANTIENE",IF(AA106<0,"BAJA",IF(AA106>0,"ALZA","")))))) -> NO PARA LP | Z106: 0 | AA106: =IF(Z106=0,"INDICAR PRECIO VTA",Z106-MaestraLP3[[#This Row],[PRECIO OCT]]) -> INDICAR PRECIO VTA | AB106: =+IFERROR((Z106-W106)/Z106,"-") -> - | AC106: =IFERROR(MaestraLP3[[#This Row],[PRECIO]]*MaestraLP3[[#This Row],[%MG UMV]],0) -> 0 | AD106: 19 | AE106: =IFERROR(MaestraLP3[[#This Row],[MARGEN UNITARIO]]/MaestraLP3[[#This Row],[Peso Neto UMV (KG)]],0) -> 0 | AF106: NO | AG106: 1 | AH106: 0 | AI106: 0 | AK106: NO
A107: LIQUIDACIÓN | B107: 40522152 | C107: =+MaestraLP3[[#This Row],[CÓDIGO]]&MaestraLP3[[#Headers],[-]]&MaestraLP3[[#This Row],[UMV]] -> 40522152-UN | D107: =+MaestraLP3[[#This Row],[CÓDIGO]]&MaestraLP3[[#Headers],[FS00]] -> 40522152FS00 | E107: BELTRÁN FRANZANI | F107: CAMILA UGARTE | G107: MAQUINAS Y REPUESTOS | H107: DESCONTINUADOS | I107: HORNO ESPECIAL PARA PAELLAS | J107: UN | K107: UN | M107: =VLOOKUP(MaestraLP3[[#This Row],[UMV]],VALIDACIONES!J:L,3,0) -> Unidad | N107: SECO | O107: NFS | P107: 179302.75 | Q107: NO PARA LP | R107: 0 | S107: =IFERROR((MaestraLP3[[#This Row],[COSTO ]]/MaestraLP3[[#This Row],[COSTO OCT]]-1),0) -> 0 | T107: VIAS DESCONTINUACION | V107: =+VLOOKUP(MaestraLP3[[#This Row],[-]],'[1]BD MES'!$A:$N,14,0) -> 179302.75 | W107: 179302.75 | X107: =+(MaestraLP3[[#This Row],[COSTO ]]-MaestraLP3[[#This Row],[COSTO OCT AL 27-10]])/MaestraLP3[[#This Row],[COSTO OCT AL 27-10]] -> 0 | Y107: =++IF(Q107="HASTA AGOTAR STOCK","HASTA AGOTAR STOCK",IF(MaestraLP3[[#This Row],[PRECIO OCT]]=0,"NO PARA LP",IF(MaestraLP3[[#This Row],[PRECIO OCT]]=0,"INCORPORACIÓN",IF(AA107=0,"MANTIENE",IF(AA107<0,"BAJA",IF(AA107>0,"ALZA","")))))) -> NO PARA LP | Z107: 0 | AA107: =IF(Z107=0,"INDICAR PRECIO VTA",Z107-MaestraLP3[[#This Row],[PRECIO OCT]]) -> INDICAR PRECIO VTA | AB107: =+IFERROR((Z107-W107)/Z107,"-") -> - | AC107: =IFERROR(MaestraLP3[[#This Row],[PRECIO]]*MaestraLP3[[#This Row],[%MG UMV]],0) -> 0 | AD107: 4 | AE107: =IFERROR(MaestraLP3[[#This Row],[MARGEN UNITARIO]]/MaestraLP3[[#This Row],[Peso Neto UMV (KG)]],0) -> 0 | AF107: NO | AG107: 1 | AH107: 0 | AI107: 0 | AK107: NO
A108: LIQUIDACIÓN | B108: 92009233 | C108: =+MaestraLP3[[#This Row],[CÓDIGO]]&MaestraLP3[[#Headers],[-]]&MaestraLP3[[#This Row],[UMV]] -> 92009233-UN | D108: =+MaestraLP3[[#This Row],[CÓDIGO]]&MaestraLP3[[#Headers],[FS00]] -> 92009233FS00 | E108: BELTRÁN FRANZANI | F108: CAMILA UGARTE | G108: MAQUINAS Y REPUESTOS | H108: DESCONTINUADOS | I108: Maq, Te Bunn Single | J108: UN | K108: UN | M108: =VLOOKUP(MaestraLP3[[#This Row],[UMV]],VALIDACIONES!J:L,3,0) -> Unidad | N108: SECO | O108: IFS | P108: 541578 | Q108: NO PARA LP | R108: 0 | S108: =IFERROR((MaestraLP3[[#This Row],[COSTO ]]/MaestraLP3[[#This Row],[COSTO OCT]]-1),0) -> 0 | T108: VIAS DESCONTINUACION | V108: =+VLOOKUP(MaestraLP3[[#This Row],[-]],'[1]BD MES'!$A:$N,14,0) -> 541578 | W108: 541578 | X108: =+(MaestraLP3[[#This Row],[COSTO ]]-MaestraLP3[[#This Row],[COSTO OCT AL 27-10]])/MaestraLP3[[#This Row],[COSTO OCT AL 27-10]] -> 0 | Y108: =++IF(Q108="HASTA AGOTAR STOCK","HASTA AGOTAR STOCK",IF(MaestraLP3[[#This Row],[PRECIO OCT]]=0,"NO PARA LP",IF(MaestraLP3[[#This Row],[PRECIO OCT]]=0,"INCORPORACIÓN",IF(AA108=0,"MANTIENE",IF(AA108<0,"BAJA",IF(AA108>0,"ALZA","")))))) -> NO PARA LP | Z108: 0 | AA108: =IF(Z108=0,"INDICAR PRECIO VTA",Z108-MaestraLP3[[#This Row],[PRECIO OCT]]) -> INDICAR PRECIO VTA | AB108: =+IFERROR((Z108-W108)/Z108,"-") -> - | AC108: =IFERROR(MaestraLP3[[#This Row],[PRECIO]]*MaestraLP3[[#This Row],[%MG UMV]],0) -> 0 | AD108: 20 | AE108: =IFERROR(MaestraLP3[[#This Row],[MARGEN UNITARIO]]/MaestraLP3[[#This Row],[Peso Neto UMV (KG)]],0) -> 0 | AF108: NO | AG108: 1 | AH108: 0 | AI108: 0 | AK108: NO
A109: LIQUIDACIÓN | B109: 40002150 | C109: =+MaestraLP3[[#This Row],[CÓDIGO]]&MaestraLP3[[#Headers],[-]]&MaestraLP3[[#This Row],[UMV]] -> 40002150-UN | D109: =+MaestraLP3[[#This Row],[CÓDIGO]]&MaestraLP3[[#Headers],[FS00]] -> 40002150FS00 | E109: BELTRÁN FRANZANI | F109: CAMILA UGARTE | G109: MAQUINAS Y REPUESTOS | H109: DESCONTINUADOS | I109: MAQUINA CAFE CAPS LB 4200 LAVAZZA | J109: UN | K109: UN | M109: =VLOOKUP(MaestraLP3[[#This Row],[UMV]],VALIDACIONES!J:L,3,0) -> Unidad | N109: SECO | O109: IFS | P109: 1273934.2 | Q109: NO PARA LP | R109: 0 | S109: =IFERROR((MaestraLP3[[#This Row],[COSTO ]]/MaestraLP3[[#This Row],[COSTO OCT]]-1),0) -> 0 | T109: VIAS DESCONTINUACION | V109: =+VLOOKUP(MaestraLP3[[#This Row],[-]],'[1]BD MES'!$A:$N,14,0) -> 1273934.2 | W109: 1273934.2 | X109: =+(MaestraLP3[[#This Row],[COSTO ]]-MaestraLP3[[#This Row],[COSTO OCT AL 27-10]])/MaestraLP3[[#This Row],[COSTO OCT AL 27-10]] -> 0 | Y109: =++IF(Q109="HASTA AGOTAR STOCK","HASTA AGOTAR STOCK",IF(MaestraLP3[[#This Row],[PRECIO OCT]]=0,"NO PARA LP",IF(MaestraLP3[[#This Row],[PRECIO OCT]]=0,"INCORPORACIÓN",IF(AA109=0,"MANTIENE",IF(AA109<0,"BAJA",IF(AA109>0,"ALZA","")))))) -> NO PARA LP | Z109: 0 | AA109: =IF(Z109=0,"INDICAR PRECIO VTA",Z109-MaestraLP3[[#This Row],[PRECIO OCT]]) -> INDICAR PRECIO VTA | AB109: =+IFERROR((Z109-W109)/Z109,"-") -> - | AC109: =IFERROR(MaestraLP3[[#This Row],[PRECIO]]*MaestraLP3[[#This Row],[%MG UMV]],0) -> 0 | AD109: 57 | AE109: =IFERROR(MaestraLP3[[#This Row],[MARGEN UNITARIO]]/MaestraLP3[[#This Row],[Peso Neto UMV (KG)]],0) -> 0 | AF109: NO | AG109: 1 | AH109: 0 | AI109: 0 | AK109: NO
... A117: LIQUIDACIÓN | B117: 92009363 | C117: =+MaestraLP3[[#This Row],[CÓDIGO]]&MaestraLP3[[#Headers],[-]]&MaestraLP3[[#This Row],[UMV]] -> 92009363-UN | D117: =+MaestraLP3[[#This Row],[CÓDIGO]]&MaestraLP3[[#Headers],[FS00]] -> 92009363FS00 | E117: BELTRÁN FRANZANI | F117: CAMILA UGARTE | G117: MAQUINAS Y REPUESTOS | H117: OTRAS MAQUINAS | I117: HORNO 4 B SMEG | J117: UN | K117: UN | M117: =VLOOKUP(MaestraLP3[[#This Row],[UMV]],VALIDACIONES!J:L,3,0) -> Unidad | N117: SECO | O117: IFS | P117: 274346.44 | Q117: MANTIENE | R117: 452441 | S117: =IFERROR((MaestraLP3[[#This Row],[COSTO ]]/MaestraLP3[[#This Row],[COSTO OCT]]-1),0) -> 0 | T117: VIAS DESCONTINUACION | V117: =+VLOOKUP(MaestraLP3[[#This Row],[-]],'[1]BD MES'!$A:$N,14,0) -> 274346.44 | W117: 274346.44 | X117: =+(MaestraLP3[[#This Row],[COSTO ]]-MaestraLP3[[#This Row],[COSTO OCT AL 27-10]])/MaestraLP3[[#This Row],[COSTO OCT AL 27-10]] -> 0 | Y117: =++IF(Q117="HASTA AGOTAR STOCK","HASTA AGOTAR STOCK",IF(MaestraLP3[[#This Row],[PRECIO OCT]]=0,"NO PARA LP",IF(MaestraLP3[[#This Row],[PRECIO OCT]]=0,"INCORPORACIÓN",IF(AA117=0,"MANTIENE",IF(AA117<0,"BAJA",IF(AA117>0,"ALZA","")))))) -> BAJA | Z117: 450000 | AA117: =IF(Z117=0,"INDICAR PRECIO VTA",Z117-MaestraLP3[[#This Row],[PRECIO OCT]]) -> -2441 | AB117: =+IFERROR((Z117-W117)/Z117,"-") -> 0.39034124 | AC117: =IFERROR(MaestraLP3[[#This Row],[PRECIO]]*MaestraLP3[[#This Row],[%MG UMV]],0) -> 175653.56 | AD117: 32 | AE117: =IFERROR(MaestraLP3[[#This Row],[MARGEN UNITARIO]]/MaestraLP3[[#This Row],[Peso Neto UMV (KG)]],0) -> 5489.1737 | AF117: NO | AG117: 1 | AH117: 0 | AI117: 0 | AK117: NO
A118: LIQUIDACIÓN | B118: 104521710 | C118: =+MaestraLP3[[#This Row],[CÓDIGO]]&MaestraLP3[[#Headers],[-]]&MaestraLP3[[#This Row],[UMV]] -> 104521710-C48 | D118: =+MaestraLP3[[#This Row],[CÓDIGO]]&MaestraLP3[[#Headers],[FS00]] -> 104521710FS00 | E118: BERNARDITA UNDURRAGA | F118: BERNARDITA UNDURRAGA | G118: BOLLERIA | H118: BOLLERÍA LISTA PARA COMER | I118: DONUT RELLENA DULCE LECHE POPPIES 66 g | J118: C48 | K118: UN | M118: =VLOOKUP(MaestraLP3[[#This Row],[UMV]],VALIDACIONES!J:L,3,0) -> Caja 48 Unidades | N118: CONGELADOS | O118: IFS | P118: 17040 | Q118: MANTIENE | R118: 29900 | S118: =IFERROR((MaestraLP3[[#This Row],[COSTO ]]/MaestraLP3[[#This Row],[COSTO OCT]]-1),0) -> 0 | T118: VIAS DESCONTINUACION | U118: VIAS DESCONTINUACION | V118: =+VLOOKUP(MaestraLP3[[#This Row],[-]],'[1]BD MES'!$A:$N,14,0) -> 17184 | W118: 17040 | X118: =+(MaestraLP3[[#This Row],[COSTO ]]-MaestraLP3[[#This Row],[COSTO OCT AL 27-10]])/MaestraLP3[[#This Row],[COSTO OCT AL 27-10]] -> -0.0083798883 | Y118: =++IF(Q118="HASTA AGOTAR STOCK","HASTA AGOTAR STOCK",IF(MaestraLP3[[#This Row],[PRECIO OCT]]=0,"NO PARA LP",IF(MaestraLP3[[#This Row],[PRECIO OCT]]=0,"INCORPORACIÓN",IF(AA118=0,"MANTIENE",IF(AA118<0,"BAJA",IF(AA118>0,"ALZA","")))))) -> MANTIENE | Z118: 29900 | AA118: =IF(Z118=0,"INDICAR PRECIO VTA",Z118-MaestraLP3[[#This Row],[PRECIO OCT]]) -> 0 | AB118: =+IFERROR((Z118-W118)/Z118,"-") -> 0.43010033 | AC118: =IFERROR(MaestraLP3[[#This Row],[PRECIO]]*MaestraLP3[[#This Row],[%MG UMV]],0) -> 12860 | AD118: 3.168 | AE118: =IFERROR(MaestraLP3[[#This Row],[MARGEN UNITARIO]]/MaestraLP3[[#This Row],[Peso Neto UMV (KG)]],0) -> 4059.3434 | AF118: NO | AG118: 1 | AH118: 0.15 | AI118: 0.2 | AJ118: SI | AK118: SI
A119: LIQUIDACIÓN | B119: 104539870 | C119: =+MaestraLP3[[#This Row],[CÓDIGO]]&MaestraLP3[[#Headers],[-]]&MaestraLP3[[#This Row],[UMV]] -> 104539870-C45 | D119: =+MaestraLP3[[#This Row],[CÓDIGO]]&MaestraLP3[[#Headers],[FS00]] -> 104539870FS00 | E119: BERNARDITA UNDURRAGA | F119: BERNARDITA UNDURRAGA | G119: BOLLERIA | H119: BOLLERÍA LISTA PARA COMER | I119: REJILLA DAMASCO POPPIES 75 g | J119: C45 | K119: UN | M119: =VLOOKUP(MaestraLP3[[#This Row],[UMV]],VALIDACIONES!J:L,3,0) -> Caja 45 Unidades | N119: CONGELADOS | O119: IFS | P119: 25245 | Q119: MANTIENE | R119: 28900 | S119: =IFERROR((MaestraLP3[[#This Row],[COSTO ]]/MaestraLP3[[#This Row],[COSTO OCT]]-1),0) -> 0 | T119: VIAS DESCONTINUACION | U119: VIAS DESCONTINUACION | V119: =+VLOOKUP(MaestraLP3[[#This Row],[-]],'[1]BD MES'!$A:$N,14,0) -> 26100 | W119: 25245 | X119: =+(MaestraLP3[[#This Row],[COSTO ]]-MaestraLP3[[#This Row],[COSTO OCT AL 27-10]])/MaestraLP3[[#This Row],[COSTO OCT AL 27-10]] -> -0.032758621 | Y119: =++IF(Q119="HASTA AGOTAR STOCK","HASTA AGOTAR STOCK",IF(MaestraLP3[[#This Row],[PRECIO OCT]]=0,"NO PARA LP",IF(MaestraLP3[[#This Row],[PRECIO OCT]]=0,"INCORPORACIÓN",IF(AA119=0,"MANTIENE",IF(AA119<0,"BAJA",IF(AA119>0,"ALZA","")))))) -> MANTIENE | Z119: 28900 | AA119: =IF(Z119=0,"INDICAR PRECIO VTA",Z119-MaestraLP3[[#This Row],[PRECIO OCT]]) -> 0 | AB119: =+IFERROR((Z119-W119)/Z119,"-") -> 0.12647059 | AC119: =IFERROR(MaestraLP3[[#This Row],[PRECIO]]*MaestraLP3[[#This Row],[%MG UMV]],0) -> 3655 | AD119: 3.6 | AE119: =IFERROR(MaestraLP3[[#This Row],[MARGEN UNITARIO]]/MaestraLP3[[#This Row],[Peso Neto UMV (KG)]],0) -> 1015.2778 | AF119: NO | AG119: 1 | AH119: 0.12 | AI119: 0.2 | AJ119: SI | AK119: SI
A120: LIQUIDACIÓN | B120: 104534600 | C120: =+MaestraLP3[[#This Row],[CÓDIGO]]&MaestraLP3[[#Headers],[-]]&MaestraLP3[[#This Row],[UMV]] -> 104534600-Z20 | D120: =+MaestraLP3[[#This Row],[CÓDIGO]]&MaestraLP3[[#Headers],[FS00]] -> 104534600FS00 | E120: BERNARDITA UNDURRAGA | F120: BERNARDITA UNDURRAGA | G120: BOLLERIA | H120: BOLLERIA PARA HORNEAR | I120: MEDIALUNA PLUS 40 gr PAGNIFIQUE 120 uds. | J120: Z20 | K120: UN | M120: =VLOOKUP(MaestraLP3[[#This Row],[UMV]],VALIDACIONES!J:L,3,0) -> Caja 120 Unidades | N120: CONGELADOS | O120: IFS | P120: 12360 | Q120: NO PARA LP | R120: 0 | S120: =IFERROR((MaestraLP3[[#This Row],[COSTO ]]/MaestraLP3[[#This Row],[COSTO OCT]]-1),0) -> 0 | T120: VIAS DESCONTINUACION | U120: VIAS DESCONTINUACION | V120: =+VLOOKUP(MaestraLP3[[#This Row],[-]],'[1]BD MES'!$A:$N,14,0) -> 12360 | W120: 12360 | X120: =+(MaestraLP3[[#This Row],[COSTO ]]-MaestraLP3[[#This Row],[COSTO OCT AL 27-10]])/MaestraLP3[[#This Row],[COSTO OCT AL 27-10]] -> 0 | Y120: =++IF(Q120="HASTA AGOTAR STOCK","HASTA AGOTAR STOCK",IF(MaestraLP3[[#This Row],[PRECIO OCT]]=0,"NO PARA LP",IF(MaestraLP3[[#This Row],[PRECIO OCT]]=0,"INCORPORACIÓN",IF(AA120=0,"MANTIENE",IF(AA120<0,"BAJA",IF(AA120>0,"ALZA","")))))) -> NO PARA LP | Z120: 0 | AA120: =IF(Z120=0,"INDICAR PRECIO VTA",Z120-MaestraLP3[[#This Row],[PRECIO OCT]]) -> INDICAR PRECIO VTA | AB120: =+IFERROR((Z120-W120)/Z120,"-") -> - | AC120: =IFERROR(MaestraLP3[[#This Row],[PRECIO]]*MaestraLP3[[#This Row],[%MG UMV]],0) -> 0 | AD120: 4.8 | AE120: =IFERROR(MaestraLP3[[#This Row],[MARGEN UNITARIO]]/MaestraLP3[[#This Row],[Peso Neto UMV (KG)]],0) -> 0 | AF120: NO | AG120: 1 | AH120: 0 | AI120: 0 | AK120: SI
A121: LIQUIDACIÓN | B121: 104254040 | C121: =+MaestraLP3[[#This Row],[CÓDIGO]]&MaestraLP3[[#Headers],[-]]&MaestraLP3[[#This Row],[UMV]] -> 104254040-C35 | D121: =+MaestraLP3[[#This Row],[CÓDIGO]]&MaestraLP3[[#Headers],[FS00]] -> 104254040FS00 | E121: BERNARDITA UNDURRAGA | F121: BERNARDITA UNDURRAGA | G121: BOLLERIA | H121: PANES PARA HORNEAR | I121: PAN CIABATTA PAGNIFIQUE 129 g | J121: C35 | K121: C35 | M121: =VLOOKUP(MaestraLP3[[#This Row],[UMV]],VALIDACIONES!J:L,3,0) -> Caja 35 Unidades | N121: CONGELADOS | O121: IFS | P121: 15037.21 | Q121: MANTIENE | R121: 22900 | S121: =IFERROR((MaestraLP3[[#This Row],[COSTO ]]/MaestraLP3[[#This Row],[COSTO OCT]]-1),0) -> 0 | T121: VIAS DESCONTINUACION | U121: VIAS DESCONTINUACION | V121: =+VLOOKUP(MaestraLP3[[#This Row],[-]],'[1]BD MES'!$A:$N,14,0) -> 14842.12 | W121: 15037.21 | X121: =+(MaestraLP3[[#This Row],[COSTO ]]-MaestraLP3[[#This Row],[COSTO OCT AL 27-10]])/MaestraLP3[[#This Row],[COSTO OCT AL 27-10]] -> 0.013144349 | Y121: =++IF(Q121="HASTA AGOTAR STOCK","HASTA AGOTAR STOCK",IF(MaestraLP3[[#This Row],[PRECIO OCT]]=0,"NO PARA LP",IF(MaestraLP3[[#This Row],[PRECIO OCT]]=0,"INCORPORACIÓN",IF(AA121=0,"MANTIENE",IF(AA121<0,"BAJA",IF(AA121>0,"ALZA","")))))) -> MANTIENE | Z121: 22900 | AA121: =IF(Z121=0,"INDICAR PRECIO VTA",Z121-MaestraLP3[[#This Row],[PRECIO OCT]]) -> 0 | AB121: =+IFERROR((Z121-W121)/Z121,"-") -> 0.34335328 | AC121: =IFERROR(MaestraLP3[[#This Row],[PRECIO]]*MaestraLP3[[#This Row],[%MG UMV]],0) -> 7862.79 | AD121: 4.515 | AE121: =IFERROR(MaestraLP3[[#This Row],[MARGEN UNITARIO]]/MaestraLP3[[#This Row],[Peso Neto UMV (KG)]],0) -> 1741.4817 | AF121: NO | AG121: 1 | AH121: 0.1 | AI121: 0.15 | AK121: SI
A122: LIQUIDACIÓN | B122: 104539450 | C122: =+MaestraLP3[[#This Row],[CÓDIGO]]&MaestraLP3[[#Headers],[-]]&MaestraLP3[[#This Row],[UMV]] -> 104539450-C12 | D122: =+MaestraLP3[[#This Row],[CÓDIGO]]&MaestraLP3[[#Headers],[FS00]] -> 104539450FS00 | E122: MARÍA DE LOS ÁNGELES QUIRÓZ | F122: ELIZABETH MILLAPAN | G122: ACEITES Y VINAGRES | H122: ACEITES DE OLIVA | I122: ACEITE OLIVA E/VIRGEN OLIVE&CO 250 ml | J122: C12 | K122: UN | M122: =VLOOKUP(MaestraLP3[[#This Row],[UMV]],VALIDACIONES!J:L,3,0) -> Caja 12 Unidades | N122: SECO | O122: NFS | P122: 42936 | Q122: BAJA | R122: 63000 | S122: =IFERROR((MaestraLP3[[#This Row],[COSTO ]]/MaestraLP3[[#This Row],[COSTO OCT]]-1),0) -> 0 | T122: VIAS DESCONTINUACION | U122: VIAS DESCONTINUACION | V122: =+VLOOKUP(MaestraLP3[[#This Row],[-]],'[1]BD MES'!$A:$N,14,0) -> 42948 | W122: 42936 | X122: =+(MaestraLP3[[#This Row],[COSTO ]]-MaestraLP3[[#This Row],[COSTO OCT AL 27-10]])/MaestraLP3[[#This Row],[COSTO OCT AL 27-10]] -> -0.00027940766 | Y122: =++IF(Q122="HASTA AGOTAR STOCK","HASTA AGOTAR STOCK",IF(MaestraLP3[[#This Row],[PRECIO OCT]]=0,"NO PARA LP",IF(MaestraLP3[[#This Row],[PRECIO OCT]]=0,"INCORPORACIÓN",IF(AA122=0,"MANTIENE",IF(AA122<0,"BAJA",IF(AA122>0,"ALZA","")))))) -> MANTIENE | Z122: 63000 | AA122: =IF(Z122=0,"INDICAR PRECIO VTA",Z122-MaestraLP3[[#This Row],[PRECIO OCT]]) -> 0 | AB122: =+IFERROR((Z122-W122)/Z122,"-") -> 0.31847619 | AC122: =IFERROR(MaestraLP3[[#This Row],[PRECIO]]*MaestraLP3[[#This Row],[%MG UMV]],0) -> 20064 | AD122: 3 | AE122: =IFERROR(MaestraLP3[[#This Row],[MARGEN UNITARIO]]/MaestraLP3[[#This Row],[Peso Neto UMV (KG)]],0) -> 6688 | AF122: SI | AG122: 1 | AH122: 0.15 | AI122: 0.15 | AJ122: SI | AK122: SI
...

Sheet MAQUINAS Y REPUESTOS
A1: BASE | B1: CÓDIGO | C1: - | D1: FS00 | E1: CATEGORY | F1: JEFE CATEGORÍA | G1: CATEGORÍA | H1: FAMILIA | I1: DESCRIPCIÓN | J1: UMV | K1: UMB | L1: DESCRIPCION UMV | M1: T° | N1: ORIGEN | O1: COSTO SEP | P1: ESTADO SEP | Q1: PRECIO SEP | R1: Columna1 | S1: Columna2 | T1: Dif. COSTOS MESES | U1: CAT. MANUAL al 08-09 | V1: S. PROPUESTO LP OCT | W1: STOCK AL 08-09 | X1: COSTO OCT AL 27-08 | Y1: COSTO | Z1: DIF EN COSTOS MES | AA1: ESTADO | AB1: PRECIO UMV | AC1: PRECIO UMB | AD1: DIFERENCIAS | AE1: %MG UMV | AF1: MARGEN UNITARIO UMV | AG1: Peso Neto UMV (KG) | AH1: Contribución x KG | AI1: VENTA X UNIDAD | AJ1: D. AUTÓNOMO | AK1: DA MEDIOCAMPO | AL1: PRODUCTO FOCO
A2: NACIONAL | B2: 40642100 | C2: 40642100-C01 | D2: 40642100FS00 | E2: MARLENE SCHWANER | F2: MARLENE SCHWANER | G2: MAQUINAS Y REPUESTOS | H2: REPUESTOS | I2: REPUESTOS LA SPAZIALE | J2: C01 | K2: UN | L2: Caja 1 Unidad | M2: SECO | N2: IFS | O2: 7803 | P2: NO PARA LP | Q2: 65000 | R2: #N/A | S2: #N/A | T2: -1 | U2: CALZADA | W2: 0 | X2: 7802.54 | Z2: -1 | AA2: NO PARA LP | AD2: INDICAR PRECIO VTA | AE2: - | AF2: 0 | AG2: 0.115 | AH2: 0 | AI2: NO | AJ2: 0 | AK2: 0
A3: NACIONAL | B3: 104516230 | C3: 104516230-C01 | D3: 104516230FS00 | E3: MARLENE SCHWANER | F3: MARLENE SCHWANER | G3: MAQUINAS Y REPUESTOS | H3: REPUESTOS | I3: REPUESTOS LAVAZZA | J3: C01 | K3: UN | L3: Caja 1 Unidad | M3: SECO | N3: IFS | O3: 27635 | P3: NO PARA LP | Q3: 280000 | R3: #N/A | S3: #N/A | T3: -1 | U3: CALZADA | W3: 0 | X3: 27635.04 | Z3: -1 | AA3: NO PARA LP | AD3: INDICAR PRECIO VTA | AE3: - | AF3: 0 | AG3: 0.115 | AH3: 0 | AI3: NO | AJ3: 0 | AK3: 0
A4: NO PARA LP | B4: 105201010 | C4: 105201010-UN | D4: 105201010FS00 | E4: MARLENE SCHWANER | F4: MARLENE SCHWANER | G4: MAQUINAS Y REPUESTOS | H4: ACCESORIOS | I4: BANDEJA PARA HORNOS 440X320 MM LISA (UNIDAD) | J4: UN | K4: UN | L4: Unidad | M4: SECO | N4: IFS | O4: 0 | P4: NO PARA LP | Q4: 0 | R4: #N/A | S4: #N/A | T4: 0 | U4: CALZADA | W4: 0 | X4: 5569.14 | Z4: -1 | AA4: NO PARA LP | AD4: INDICAR PRECIO VTA | AE4: - | AF4: 0 | AG4: 1 | AH4: 0 | AI4: NO | AJ4: 0 | AK4: 0
B5: 104523560 | C5: 104523560-ST | D5: 104523560FS00 | G5: MAQUINAS Y REPUESTOS | H5: REPUESTOS | I5: REPUESTO IVI (UNIDAD) | J5: ST | K5: C | L5: #N/A | M5: SECO | N5: IFS | S5: 0 | T5: 0 | U5: CALZADA | W5: 0 | X5: #N/A | Z5: #N/A | AA5: NO PARA LP | AD5: INDICAR PRECIO VTA | AE5: - | AF5: 0 | AH5: 0
B6: 104535700 | C6: 104535700-ST | D6: 104535700FS00 | G6: MAQUINAS Y REPUESTOS | H6: REPUESTOS | I6: 27370.0002 - VALVULA DE AGUA CALIENTE (UNIDAD) | J6: ST | K6: C | L6: #N/A | N6: IFS | S6: 0 | T6: 0 | U6: CALZADA | W6: 0 | X6: #N/A | Z6: #N/A | AA6: NO PARA LP | AD6: INDICAR PRECIO VTA | AE6: - | AF6: 0 | AH6: 0
B7: 104536070 | C7: 104536070-ST | D7: 104536070FS00 | G7: MAQUINAS Y REPUESTOS | H7: REPUESTOS | I7: 34202.0004 - VALVULA DIESPENSADO (UNIDAD) | J7: ST | K7: C | L7: #N/A | N7: IFS | S7: 0 | T7: 0 | U7: CALZADA | W7: 0 | X7: #N/A | Z7: #N/A | AA7: NO PARA LP | AD7: INDICAR PRECIO VTA | AE7: - | AF7: 0 | AH7: 0
B8: 104536080 | C8: 104536080-ST | D8: 104536080FS00 | G8: MAQUINAS Y REPUESTOS | H8: REPUESTOS | I8: 219 - GUARNIZIONE OR 102 VITON (UNIDAD) | J8: ST | K8: C | L8: #N/A | N8: IFS | S8: 0 | T8: 0 | U8: CALZADA | W8: 0 | X8: #N/A | Z8: #N/A | AA8: NO PARA LP | AD8: INDICAR PRECIO VTA | AE8: - | AF8: 0 | AH8: 0
B9: 104536090 | C9: 104536090-ST | D9: 104536090FS00 | G9: MAQUINAS Y REPUESTOS | H9: REPUESTOS | I9: 220 - ASTA RUBINETTO (UNIDAD) | J9: ST | K9: C | L9: #N/A | N9: IFS | S9: 0 | T9: 0 | U9: CALZADA | W9: 0 | X9: #N/A | Z9: #N/A | AA9: NO PARA LP | AD9: INDICAR PRECIO VTA | AE9: - | AF9: 0 | AH9: 0
B10: 104536110 | C10: 104536110-ST | D10: 104536110FS00 | G10: MAQUINAS Y REPUESTOS | H10: REPUESTOS | I10: 222 - PORTA GUARNIZIONE (UNIDAD) | J10: ST | K10: C | L10: #N/A | N10: IFS | S10: 0 | T10: 0 | U10: CALZADA | W10: 0 | X10: #N/A | Z10: #N/A | AA10: NO PARA LP | AD10: INDICAR PRECIO VTA | AE10: - | AF10: 0 | AH10: 0
B11: 104536270 | C11: 104536270-ST | D11: 104536270FS00 | G11: MAQUINAS Y REPUESTOS | H11: REPUESTOS | I11: 643 - VITE TE 5X25 INOX (UNIDAD) | J11: ST | K11: C | L11: #N/A | N11: IFS | S11: 0 | T11: 0 | U11: CALZADA | W11: 0 | X11: #N/A | Z11: #N/A | AA11: NO PARA LP | AD11: INDICAR PRECIO VTA | AE11: - | AF11: 0 | AH11: 0
B12: 104536280 | C12: 104536280-ST | D12: 104536280FS00 | G12: MAQUINAS Y REPUESTOS | H12: REPUESTOS | I12: 645 - FILTRO 2 CAFFE (UNIDAD) | J12: ST | K12: C | L12: #N/A | N12: IFS | S12: 0 | T12: 0 | U12: CALZADA | W12: 0 | X12: #N/A | Z12: #N/A | AA12: NO PARA LP | AD12: INDICAR PRECIO VTA | AE12: - | AF12: 0 | AH12: 0
B13: 104536480 | C13: 104536480-ST | D13: 104536480FS00 | G13: MAQUINAS Y REPUESTOS | H13: REPUESTOS | I13: 5505 - RESISTENZA 3 GR. 220V/3800W NICHE (UNIDAD) | J13: ST | K13: C | L13: #N/A | N13: IFS | S13: 0 | T13: 0 | U13: CALZADA | W13: 0 | X13: #N/A | Z13: #N/A | AA13: NO PARA LP | AD13: INDICAR PRECIO VTA | AE13: - | AF13: 0 | AH13: 0
B14: 104536500 | C14: 104536500-ST | D14: 104536500FS00 | G14: MAQUINAS Y REPUESTOS | H14: REPUESTOS | I14: 6139 - GIUNTINO POMPA (UNIDAD) | J14: ST | K14: C | L14: #N/A | N14: IFS | S14: 0 | T14: 0 | U14: CALZADA | W14: 0 | X14: #N/A | Z14: #N/A | AA14: NO PARA LP | AD14: INDICAR PRECIO VTA | AE14: - | AF14: 0 | AH14: 0
B15: 104536510 | C15: 104536510-ST | D15: 104536510FS00 | G15: MAQUINAS Y REPUESTOS | H15: REPUESTOS | I15: 7580 - GUARNIZIONE OR 12,10X 2,7 EPDM (UNIDAD) | J15: ST | K15: C | L15: #N/A | N15: IFS | S15: 0 | T15: 0 | U15: CALZADA | W15: 0 | X15: #N/A | Z15: #N/A | AA15: NO PARA LP | AD15: INDICAR PRECIO VTA | AE15: - | AF15: 0 | AH15: 0
B16: 104536530 | C16: 104536530-ST | D16: 104536530FS00 | G16: MAQUINAS Y REPUESTOS | H16: REPUESTOS | I16: 8256 - GUAINA GOMMA PER TUBO VAPORE (UNIDAD) | J16: ST | K16: C | L16: #N/A | N16: IFS | S16: 0 | T16: 0 | U16: CALZADA | W16: 0 | X16: #N/A | Z16: #N/A | AA16: NO PARA LP | AD16: INDICAR PRECIO VTA | AE16: - | AF16: 0 | AH16: 0
B17: 104536540 | C17: 104536540-ST | D17: 104536540FS00 | G17: MAQUINAS Y REPUESTOS | H17: REPUESTOS | I17: 8333 - ASTA PER VITONE FILETTATA L=43.5 (UNIDAD) | J17: ST | K17: C | L17: #N/A | N17: IFS | S17: 0 | T17: 0 | U17: CALZADA | W17: 0 | X17: #N/A | Z17: #N/A | AA17: NO PARA LP | AD17: INDICAR PRECIO VTA | AE17: - | AF17: 0 | AH17: 0
... B33: 104537280 | C33: 104537280-ST | D33: 104537280FS00 | G33: MAQUINAS Y REPUESTOS | H33: REPUESTOS | I33: 257105 - TUBO SIN ANILLO VERSION 24 V (UNIDAD) | J33: ST | K33: C | L33: #N/A | N33: NFS | S33: 0 | T33: 0 | U33: CALZADA | W33: 0 | X33: #N/A | Z33: #N/A | AA33: NO PARA LP | AD33: INDICAR PRECIO VTA | AE33: - | AF33: 0 | AH33: 0
B34: 104544880 | C34: 104544880-ST | D34: 104544880FS00 | G34: MAQUINAS Y REPUESTOS | H34: REPUESTOS | I34: REPUESTOS EUROVENDING (UNIDAD) | J34: ST | K34: C | L34: #N/A | M34: SECO | N34: NFS | S34: 0 | T34: 0 | U34: CALZADA | W34: 0 | X34: #N/A | Z34: #N/A | AA34: NO PARA LP | AD34: INDICAR PRECIO VTA | AE34: - | AF34: 0 | AH34: 0
B35: 105201660 | C35: 105201660-ST | D35: 105201660FS00 | G35: MAQUINAS Y REPUESTOS | H35: REPUESTOS | I35: SUBCONJUNTO PORTARRODILLO IZQUIERDO ALFA (UNIDAD) | J35: ST | K35: C | L35: #N/A | M35: SECO | N35: IFS | S35: 0 | T35: 0 | U35: CALZADA | W35: 0 | X35: #N/A | Z35: #N/A | AA35: NO PARA LP | AD35: INDICAR PRECIO VTA | AE35: - | AF35: 0 | AH35: 0
B36: 105201680 | C36: 105201680-ST | D36: 105201680FS00 | G36: MAQUINAS Y REPUESTOS | H36: REPUESTOS | I36: RELOJ 90MINUTI BPL ALFA 11 (UNIDAD) | J36: ST | K36: C | L36: #N/A | M36: SECO | N36: IFS | S36: 0 | T36: 0 | U36: CALZADA | W36: 0 | X36: #N/A | Z36: #N/A | AA36: NO PARA LP | AD36: INDICAR PRECIO VTA | AE36: - | AF36: 0 | AH36: 0
B37: 105201700 | C37: 105201700-ST | D37: 105201700FS00 | G37: MAQUINAS Y REPUESTOS | H37: REPUESTOS | I37: DADO M6X1 H7 NICH SINISTRO (UNIDAD) | J37: ST | K37: C | L37: #N/A | M37: SECO | N37: IFS | S37: 0 | T37: 0 | U37: CALZADA | W37: 0 | X37: #N/A | Z37: #N/A | AA37: NO PARA LP | AD37: INDICAR PRECIO VTA | AE37: - | AF37: 0 | AH37: 0
B38: 105201730 | C38: 105201730-ST | D38: 105201730FS00 | G38: MAQUINAS Y REPUESTOS | H38: REPUESTOS | I38: SUBCONJUNTO PORTARRODILLO DERECHO ALFA 2 (UNIDAD) | J38: ST | K38: C | L38: #N/A | M38: SECO | N38: IFS | S38: 0 | T38: 0 | U38: CALZADA | W38: 0 | X38: #N/A | Z38: #N/A | AA38: NO PARA LP | AD38: INDICAR PRECIO VTA | AE38: - | AF38: 0 | AH38: 0
B39: 105201740 | C39: 105201740-ST | D39: 105201740FS00 | G39: MAQUINAS Y REPUESTOS | H39: REPUESTOS | I39: RESISTENCIA VNLA 2700W ALFA 41 (UNIDAD) | J39: ST | K39: C | L39: #N/A | M39: SECO | N39: IFS | S39: 0 | T39: 0 | U39: CALZADA | W39: 0 | X39: #N/A | Z39: #N/A | AA39: NO PARA LP | AD39: INDICAR PRECIO VTA | AE39: - | AF39: 0 | AH39: 0
B40: 105201760 | C40: 105201760-ST | D40: 105201760FS00 | G40: MAQUINAS Y REPUESTOS | H40: REPUESTOS | I40: MANILLA RELOJ ALFA11 (UNIDAD) | J40: ST | K40: C | L40: #N/A | M40: SECO | N40: IFS | S40: 0 | T40: 0 | U40: CALZADA | W40: 0 | X40: #N/A | Z40: #N/A | AA40: NO PARA LP | AD40: INDICAR PRECIO VTA | AE40: - | AF40: 0 | AH40: 0
B41: 105201780 | C41: 105201780-ST | D41: 105201780FS00 | G41: MAQUINAS Y REPUESTOS | H41: REPUESTOS | I41: BISAGRA PUERTA HORNO S400 ALFA 43 (UNIDAD) | J41: ST | K41: C | L41: #N/A | M41: SECO | N41: IFS | S41: 0 | T41: 0 | U41: CALZADA | W41: 0 | X41: #N/A | Z41: #N/A | AA41: NO PARA LP | AD41: INDICAR PRECIO VTA | AE41: - | AF41: 0 | AH41: 0
B42: 105201790 | C42: 105201790-ST | D42: 105201790FS00 | G42: MAQUINAS Y REPUESTOS | H42: REPUESTOS | I42: MOTOR V.220-240 ALFA41 (UNIDAD) | J42: ST | K42: C | L42: #N/A | M42: SECO | N42: IFS | S42: 0 | T42: 0 | U42: CALZADA | W42: 0 | X42: #N/A | Z42: #N/A | AA42: NO PARA LP | AD42: INDICAR PRECIO VTA | AE42: - | AF42: 0 | AH42: 0
B43: 40009390 | C43: 40009390-ST | D43: 40009390FS00 | G43: MAQUINAS Y REPUESTOS | H43: REPUESTOS | I43: TORNILLO FIJACION HORNO ALFA 43 (UNIDAD) | J43: ST | K43: C | L43: #N/A | M43: SECO | N43: IFS | S43: 0 | T43: 0 | U43: CALZADA | W43: 0 | X43: #N/A | Z43: #N/A | AA43: NO PARA LP | AD43: INDICAR PRECIO VTA | AE43: - | AF43: 0 | AH43: 0
B44: 40009410 | C44: 40009410-ST | D44: 40009410FS00 | G44: MAQUINAS Y REPUESTOS | H44: REPUESTOS | I44: MOTOR HORNO BASTAGO LARGO ALFA 43 (UNIDAD) | J44: ST | K44: C | L44: #N/A | M44: SECO | N44: IFS | S44: 0 | T44: 0 | U44: CALZADA | W44: 0 | X44: #N/A | Z44: #N/A | AA44: NO PARA LP | AD44: INDICAR PRECIO VTA | AE44: - | AF44: 0 | AH44: 0
B45: 40009430 | C45: 40009430-ST | D45: 40009430FS00 | G45: MAQUINAS Y REPUESTOS | H45: REPUESTOS | I45: LAMPARA ALTA DE TEMPERATURA 25W/230V/300 (UNIDAD) | J45: ST | K45: C | L45: #N/A | M45: SECO | N45: IFS | S45: 0 | T45: 0 | U45: CALZADA | W45: 0 | X45: #N/A | Z45: #N/A | AA45: NO PARA LP | AD45: INDICAR PRECIO VTA | AE45: - | AF45: 0 | AH45: 0
... B47: 40009450 | C47: 40009450-ST | D47: 40009450FS00 | G47: MAQUINAS Y REPUESTOS | H47: REPUESTOS | I47: VIDRIO INTERIORHORNO ALFA 43 (UNIDAD) | J47: ST | K47: C | L47: #N/A | M47: SECO | N47: IFS | S47: 0 | T47: 0 | U47: CALZADA | W47: 0 | X47: #N/A | Z47: #N/A | AA47: NO PARA LP | AD47: INDICAR PRECIO VTA | AE47: - | AF47: 0 | AH47: 0

Sheet AFOODS
A1: CÓDIGO | B1: AF01 | C1: ENCARGADO CATEGORÍA | D1: JEFE CATEGORÍA | E1: CATEGORÍA | F1: FAMILIA | G1: DESCRIPCIÓN | H1: UMV | I1: UMB | J1: DESCRIPCION UMV | K1: T° | L1: ORIGEN | M1: COSTO SEP | N1: PRECIO SEP | O1: Diferencia | P1: COSTO 08-10 | Q1: COSTO | R1: PRECIO | S1: MG | T1: VENTA X UNIDAD | U1: DESCUENTO AUTÓNOMO
A2: 104518450 | B2: 104518450AF01 | C2: MYRIAM GARIN | D2: CAROLINA SAN MARTÍN | E2: QUESOS Y MANTEQUILLA | F2: QUESOS SEMI DUROS | G2: QUESO GAUDA AMMERLAND 3 KG | H2: KG | I2: KG | J2: Kilogramo | K2: FRIO | L2: IFS | M2: 4917 | N2: 6990 | O2: =+IFERROR((Q2/M2-1),0) -> 0.0085417938 | P2: 4959 | Q2: 4959 | R2: 6990 | S2: =+IFERROR((R2-Q2)/R2,"-") -> 0.29055794 | T2: NO | U2: 0
A3: 104519930 | B3: 104519930AF01 | C3: MYRIAM GARIN | D3: CAROLINA SAN MARTÍN | E3: QUESOS Y MANTEQUILLA | F3: QUESOS SEMI DUROS | G3: QUESO GAUDA MOLFINO 3,9 kg (Caja) | H3: KG | I3: KG | J3: Kilogramo | K3: FRIO | L3: IFS | M3: 4639.29 | N3: 7590 | O3: =+IFERROR((Q3/M3-1),0) -> 0 | P3: 4639.29 | Q3: 4639.29 | R3: 7590 | S3: =+IFERROR((R3-Q3)/R3,"-") -> 0.38876285 | T3: SI | U3: 0
A4: 104522620 | B4: 104522620AF01 | C4: MYRIAM GARIN | D4: CAROLINA SAN MARTÍN | E4: POLLO | F4: TRUTROS | G4: TRUTRO ALA POLLO INTERF BRASIL 15 KG | H4: CJ | I4: KG | J4: Caja | K4: CONGELADOS | L4: IFS | M4: 32500 | N4: 63000 | O4: =+IFERROR((Q4/M4-1),0) -> -0.064 | P4: 30420 | Q4: 30420 | R4: 46800 | S4: =+IFERROR((R4-Q4)/R4,"-") -> 0.35 | T4: NO | U4: 0
A5: 104524330 | B5: 104524330AF01 | C5: MYRIAM GARIN | D5: CAROLINA SAN MARTÍN | E5: POLLO | F5: PECHUGAS | G5: PECHUGA POLLO MARINADA DESH BRASIL 2 KG | H5: C06 | I5: UN | J5: Caja 6 Unidades | K5: CONGELADOS | L5: IFS | M5: 35300 | N5: 69600 | O5: =+IFERROR((Q5/M5-1),0) -> -0.0043195467 | P5: 35147.52 | Q5: 35147.52 | R5: 61200 | S5: =+IFERROR((R5-Q5)/R5,"-") -> 0.42569412 | T5: SI | U5: 0
A6: 104524530 | B6: 104524530AF01 | C6: MYRIAM GARIN | D6: CAROLINA SAN MARTÍN | E6: POLLO | F6: TRUTROS | G6: TRUTRO ALA IQF BRASIL 1 KG | H6: C12 | I6: KG | J6: Kilogramo | K6: CONGELADOS | L6: IFS | M6: 24120 | N6: 42000 | O6: =+IFERROR((Q6/M6-1),0) -> 0 | P6: 24120 | Q6: 24120 | R6: 46800 | S6: =+IFERROR((R6-Q6)/R6,"-") -> 0.48461538 | T6: NO | U6: 0
A7: 104524940 | B7: 104524940AF01 | C7: MYRIAM GARIN | D7: PAZ CARO | E7: VACUNO CONGELADO | F7: SUBPRODUCTOS | G7: GUATA CALLO VACUNO PARAGUAY | H7: KG | I7: KG | J7: Kilogramo | K7: CONGELADOS | L7: IFS | M7: 2567 | N7: 3690 | O7: =+IFERROR((Q7/M7-1),0) -> -0.040124659 | P7: 2464 | Q7: 2464 | R7: 3690 | S7: =+IFERROR((R7-Q7)/R7,"-") -> 0.33224932 | T7: NO | U7: 0
A8: 104524980 | B8: 104524980AF01 | C8: MYRIAM GARIN | D8: PAZ CARO | E8: VACUNO CONGELADO | F8: POSTA ROSADA | G8: POSTA ROSADA CAT U CONGELADA COL | H8: KG | I8: KG | J8: Kilogramo | K8: CONGELADOS | L8: IFS | M8: 5807 | N8: 8990 | O8: =+IFERROR((Q8/M8-1),0) -> 0 | P8: 5807 | Q8: 5807 | R8: 8990 | S8: =+IFERROR((R8-Q8)/R8,"-") -> 0.35406007 | T8: NO | U8: 0
A9: 104524990 | B9: =+A9&$B$1 -> 104524990AF01 | C9: MYRIAM GARIN | D9: PAZ CARO | E9: VACUNO CONGELADO | F9: POSTA ROSADA | G9: POSTA ROSADA CAT C CONGELADA BRASIL | H9: KG | I9: KG | J9: Kilogramo | K9: CONGELADOS | L9: IFS | M9: 5760 | N9: 8990 | O9: =+IFERROR((Q9/M9-1),0) -> 0 | P9: 5760 | Q9: 5760 | R9: 8990 | S9: =+IFERROR((R9-Q9)/R9,"-") -> 0.3592881 | T9: NO | U9: 0
A10: 104525000 | B10: 104525000AF01 | C10: MYRIAM GARIN | D10: PAZ CARO | E10: VACUNO CONGELADO | F10: POSTA ROSADA | G10: POSTA ROSADA CAT V CONGELADA COL | H10: KG | I10: KG | J10: Kilogramo | K10: CONGELADOS | L10: IFS | M10: 5494 | N10: 8990 | O10: =+IFERROR((Q10/M10-1),0) -> 0 | P10: 5494 | Q10: 5494 | R10: 8990 | S10: =+IFERROR((R10-Q10)/R10,"-") -> 0.38887653 | T10: NO | U10: 0
A11: 104526890 | B11: 104526890AF01 | C11: MYRIAM GARIN | D11: PAZ CARO | E11: VACUNO CONGELADO | F11: POSTA ROSADA | G11: POSTA ROSADA CAT V CONG PRY | H11: KG | I11: KG | J11: Kilogramo | K11: CONGELADOS | L11: IFS | M11: 5986 | N11: 8990 | O11: =+IFERROR((Q11/M11-1),0) -> 0.010357501 | P11: 6048 | Q11: 6048 | R11: 8990 | S11: =+IFERROR((R11-Q11)/R11,"-") -> 0.3272525 | T11: NO | U11: 0
A12: 104539990 | B12: 104539990AF01 | C12: MYRIAM GARIN | D12: CAROLINA SAN MARTÍN | E12: QUESOS Y MANTEQUILLA | F12: QUESOS SEMI DUROS | G12: QUESO GOUDA LAMINADO AMMERLAND 1 KG | H12: C06 | I12: UN | J12: Caja 6 Unidades | K12: FRIO | L12: IFS | M12: 35364 | N12: 38000 | O12: =+IFERROR((Q12/M12-1),0) -> 0.0039022735 | P12: 35502 | Q12: 35502 | R12: 38000 | S12: =+IFERROR((R12-Q12)/R12,"-") -> 0.065736842 | T12: SI | U12: 0
A13: 150001947 | B13: 150001947AF01 | C13: MYRIAM GARIN | D13: PAZ CARO | E13: VACUNO CONGELADO | F13: SUBPRODUCTOS | G13: HIGADO VACUNO USA | H13: KG | I13: KG | J13: Kilogramo | K13: CONGELADOS | L13: IFS | M13: 2000 | N13: 3290 | O13: =+IFERROR((Q13/M13-1),0) -> 0 | P13: 2000 | Q13: 2000 | R13: 3290 | S13: =+IFERROR((R13-Q13)/R13,"-") -> 0.39209726 | T13: NO | U13: 0
A14: 150001952 | B14: 150001952AF01 | C14: MYRIAM GARIN | D14: PAZ CARO | E14: VACUNO CONGELADO | F14: POSTA ROSADA | G14: POSTA ROSADA CAT V CONG BRASIL | H14: KG | I14: KG | J14: Kilogramo | K14: CONGELADOS | L14: IFS | M14: 5802 | N14: 8990 | O14: =+IFERROR((Q14/M14-1),0) -> 0 | P14: 5802 | Q14: 5802 | R14: 8990 | S14: =+IFERROR((R14-Q14)/R14,"-") -> 0.35461624 | T14: NO | U14: 0
A15: 150001986 | B15: 150001986AF01 | C15: MYRIAM GARIN | D15: CAROLINA SAN MARTÍN | E15: CERDO | F15: PORCIONADOS | G15: CHULETA CERDO CENTRO ENTERA BRASIL 18 KG | H15: KG | I15: KG | J15: Kilogramo | K15: CONGELADOS | L15: IFS | M15: 2364 | N15: 4290 | O15: =+IFERROR((Q15/M15-1),0) -> -0.01607445 | P15: 2326 | Q15: 2326 | R15: 4290 | S15: =+IFERROR((R15-Q15)/R15,"-") -> 0.45780886 | T15: NO | U15: 0
A16: 150001987 | B16: 150001987AF01 | C16: MYRIAM GARIN | D16: CAROLINA SAN MARTÍN | E16: CERDO | F16: PORCIONADOS | G16: CHULETA CERDO VETADA ENTERA BRASIL 18 KG | H16: KG | I16: KG | J16: Kilogramo | K16: CONGELADOS | L16: IFS | M16: 2489 | N16: 4380 | O16: =+IFERROR((Q16/M16-1),0) -> -0.024909602 | P16: 2427 | Q16: 2427 | R16: 4380 | S16: =+IFERROR((R16-Q16)/R16,"-") -> 0.44589041 | T16: NO | U16: 0
A17: 150001995 | B17: 150001995AF01 | C17: MYRIAM GARIN | D17: CAROLINA SAN MARTÍN | E17: CERDO | F17: PULPAS | G17: PULPA PIERNA 1/8 IMP 21 KG | H17: KG | I17: KG | J17: Kilogramo | K17: CONGELADOS | L17: IFS | M17: 2926 | N17: 4590 | O17: =+IFERROR((Q17/M17-1),0) -> -0.10082023 | P17: 2631 | Q17: 2631 | R17: 4590 | S17: =+IFERROR((R17-Q17)/R17,"-") -> 0.42679739 | T17: NO | U17: 0

Sheet DELETE
A1: BASE | B1: CÓDIGO | C1: - | D1: FS00 | E1: CATEGORY | F1: JEFE CATEGORÍA | G1: CATEGORÍA | H1: FAMILIA | I1: DESCRIPCIÓN | J1: UMV | K1: UMB | L1: DESCRIPCION UMV | M1: T° | N1: ORIGEN | O1: COSTO JUN | P1: ELIMINACIÓN | Q1: PRECIO JUN | R1: Diferencia | S1: CAT. MANUAL al 18-06 | T1: S. PROPUESTO LP JUL | U1: COSTO JUL AL 18-06 | V1: COSTO JUL | W1: DIF EN COSTOS | X1: ESTADO JULIO | Y1: PRECIO | Z1: DIFERENCIAS | AA1: %MG | AB1: MARGEN UNITARIO | AC1: Peso Neto UMV (KG) | AD1: Contribución x KG | AE1: VENTA X UNIDAD | AF1: D. AUTÓNOMO | AG1: DA MEDIOCAMPO | AH1: PRODUCTO FOCO
A2: NACIONAL | B2: 150002033 | E2: MYRIAM GARIN | G2: JAMONES Y CECINAS | H2: EMBUTIDOS Y FIAMBRES | I2: CHORIZO WINTER 1 KG | J2: UN | K2: UN | M2: FRIO
A3: NACIONAL | B3: 104542730 | E3: MARÍA DE LOS ÁNGELES QUIRÓZ | G3: APERITIVOS | H3: OTROS APERITIVOS | I3: JALAPENO NACHO CHEESE BITES 1 KG | J3: C05 | K3: UN | M3: CONGELADOS
A4: NACIONAL | B4: 104528570 | E4: MARÍA DE LOS ÁNGELES QUIRÓZ | G4: BOLLERIA Y REPOSTERIA | H4: HELADOS | I4: HELADO TRISABOR FRUGELE 1 L | J4: C06 | K4: UN | M4: CONGELADOS
A5: NACIONAL | B5: 201700245 | E5: MARÍA DE LOS ÁNGELES QUIRÓZ | G5: SNACKS Y FRUTOS SECOS | H5: PAPAS FRITAS | I5: PAPAS FRITAS C.A LIMON MARCO POLO 200 G | J5: C12 | K5: UN | M5: SECO
A6: NACIONAL | B6: 101310103 | E6: MARÍA DE LOS ÁNGELES QUIRÓZ | G6: SNACKS Y FRUTOS SECOS | H6: PAPAS FRITAS | I6: PAPAS FRITAS INFERNO SPICY CHEDDAR 175G | J6: C12 | K6: UN | M6: SECO
A7: LIQUIDACIÓN | B7: 104534890 | E7: MYRIAM GARIN | G7: PESCADOS Y MARISCOS | H7: PESCADOS | I7: ATUN STEAK 170-220G CJ 5 KG IMPORTADO | J7: CJ | K7: KG | M7: CONGELADOS
A8: LIQUIDACIÓN | B8: 104539610 | E8: MYRIAM GARIN | G8: QUESOS Y MANTEQUILLA | H8: QUESOS BLANDOS | I8: QUESO CREMA CALIFORNIA IMP 1,36 KG | J8: UN | K8: UN | M8: FRIO
A9: LIQUIDACIÓN | B9: 104541760 | E9: MYRIAM GARIN | G9: QUESOS Y MANTEQUILLA | H9: QUESOS BLANDOS | I9: QUESO CREMA RENY PICOT IMP 1,36 kg | J9: UN | K9: UN | M9: FRIO
A10: LIQUIDACIÓN | B10: 104525480 | E10: MYRIAM GARIN | G10: QUESOS Y MANTEQUILLA | H10: QUESOS SEMI DUROS | I10: QUESO GAUDA LAMINADO 500 GR | J10: C08 | K10: UN | M10: FRIO
A11: LIQUIDACIÓN | B11: 104532620 | E11: MARÍA DE LOS ÁNGELES QUIRÓZ | G11: ACEITES Y VINAGRES | H11: ACEITES DE OLIVA | I11: ACEITE DE OLIVA MAGNUM J.LLORENS 1,5 LT | J11: C03 | K11: UN | M11: SECO
A12: LIQUIDACIÓN | B12: 150000473 | E12: MARÍA DE LOS ÁNGELES QUIRÓZ | G12: BOLLERIA Y REPOSTERIA | H12: CREMAS | I12: CREMA CHANTILLY SOPROLE 250 ML | J12: C12 | K12: UN | M12: FRIO
A13: LIQUIDACIÓN | B13: 201130895 | E13: MARÍA DE LOS ÁNGELES QUIRÓZ | G13: BOLLERIA Y REPOSTERIA | H13: INGREDIENTES REPOSTERIA | I13: *D*ESENCIA DE VAINILLA MP 500ML | J13: C12 | K13: UN | M13: SECO
... A50: LIQUIDACIÓN | B50: 201700037 | E50: MARÍA DE LOS ÁNGELES QUIRÓZ | G50: SNACKS Y FRUTOS SECOS | H50: OTROS SNACKS | I50: TERRA TORTILLA MAIZ MORADO 12X180G | J50: C12 | K50: UN | M50: SECO
B51: 104532390 | E51: MARÍA DE LOS ÁNGELES QUIRÓZ | G51: LICORES | H51: SYRUPS | I51: LICOR BOT 700CC GRANADINA DON VITO | J51: C12 | P51: LP OCTUBRE 2024
B52: 104528290 | E52: MARÍA DE LOS ÁNGELES QUIRÓZ | G52: SALSAS Y ADEREZOS | H52: MINI PORCIONES | I52: MAYONESA MINI DELI HELLMANNS 7 G | J52: V28 | P52: LP OCTUBRE 2024
B53: 104539530 | E53: MARÍA DE LOS ÁNGELES QUIRÓZ | G53: BOLLERIA Y REPOSTERIA | H53: HARINAS Y SEMOLAS | I53: ALMIDON DE MAIZ CAMSA 1 KG | J53: C10 | P53: LP OCTUBRE 2024
B54: 104524270 | E54: MARÍA DE LOS ÁNGELES QUIRÓZ | G54: SALSAS Y ADEREZOS | H54: MINI PORCIONES | I54: MOSTAZA MINI HELLMANNS 8 G | J54: V28 | P54: LP OCTUBRE 2024
B55: 150000880 | E55: MARÍA DE LOS ÁNGELES QUIRÓZ | G55: CONSERVAS | H55: FRUTAS | I55: PAPAYA AL JUGO FRASCO QUIMEY 1 KG | J55: C12 | P55: LP OCTUBRE 2024
B56: 150000592 | E56: MARÍA DE LOS ÁNGELES QUIRÓZ | G56: SUMINISTROS | H56: PRODUCTOS DE LIMPIEZA | I56: ALCOHOL DESINFECTANTE 1 L | J56: C12 | P56: LP OCTUBRE 2024
B57: 104523930 | E57: MARÍA DE LOS ÁNGELES QUIRÓZ | G57: SUMINISTROS | H57: SUMINISTROS | I57: DESCONTINUADOS | J57: UN | P57: LP JUNIO 2024
B58: 150000881 | E58: MARÍA DE LOS ÁNGELES QUIRÓZ | G58: CONSERVAS | H58: PESCADOS | I58: ANCHOAS EN ACEITE MARBELLA 90 G | J58: C12 | P58: LP OCTUBRE 2024
B59: 104524700 | E59: MARÍA DE LOS ÁNGELES QUIRÓZ | G59: SUMINISTROS | H59: DESCONTINUADOS | I59: 40722 TOALLA 2H EXCELLENCE 200 M | J59: UN | P59: LP MAYO 2024
B60: 105201180 | E60: MARÍA DE LOS ÁNGELES QUIRÓZ | G60: SUMINISTROS | H60: DESCONTINUADOS | I60: 81221 SERV COCTEL CINEPLANET 24X24 CM | J60: UN | P60: LP AGOSTO 2024
B61: 104534260 | E61: MARÍA DE LOS ÁNGELES QUIRÓZ | G61: SUMINISTROS | H61: PRODUCTOS TISSUE | I61: 40702 TOALLA 1H PLUS 300 M | J61: C02 | P61: LP SEPTIEMBRE 2024
B62: 104538070 | E62: MYRIAM GARIN | G62: SALSAS Y ADEREZOS | H62: SALSAS Y TOPPINGS | I62: SALSA CHILIS BOLSA 1 KG | J62: C06 | P62: LP SEPTIEMBRE 2024
... B704: 150001936 | E704: MYRIAM GARIN | G704: PESCADOS Y MARISCOS | H704: MARISCOS Y MOLUSCOS | I704: ANILLOS CALAMAR IQF 1KG IMPORTADO | J704: C10 | P704: LP NOVIEMBRE 2024
B705: 40009376
B706: 40009377
B707: 40009378
B708: 150001930
B709: 104343100
B710: 40005008
B711: 92009365
B712: 40002159
B713: 40004996
B714: 40522152
B715: 96820032
B716: 92009271
... B725: 40522160
B726: 104539480 | E726: RODRIGO GUAJARDO | G726: POLLO | H726: PECHUGAS | I726: PECHUGA C/HUESO MARINADA LP 15 KG BRASIL | J726: CJ | P726: LP JUNIO 2024
B727: 104528000 | E727: RODRIGO GUAJARDO | G727: POLLO | H727: TRUTROS | I727: TRUTRO ALA POLLO IQF BRASIL 10 KG | J727: CJ | P727: LP JUNIO 2024
B728: 150001989 | E728: RODRIGO GUAJARDO | G728: CERDO | H728: PORCIONADOS | I728: COSTILLAR CERDO USA UN IVP CJ 10 KG | J728: KG | P728: LP JUNIO 2024
A729: LIQUIDACIÓN | B729: 104532030 | C729: 104532030-C12 | D729: 104532030FS00 | E729: MARÍA DE LOS ÁNGELES QUIRÓZ | G729: LICORES | H729: VINO | I729: VINO VAR. SAUVIGNON B. BAKUS 12,5° 750CC | J729: C12 | K729: UN | L729: Caja 12 Unidades | M729: SECO | N729: NFS | O729: 20640 | P729: ELIMINAR LP SEPTIEMBRE 2024 | Q729: 30000 | R729: 0 | S729: VIAS DESCONTINUACION | T729: VIAS DESCONTINUACION | U729: 20640 | V729: 20640 | W729: 0 | X729: ELIMINAR LP | Y729: 0 | Z729: INDICAR PRECIO VTA | AA729: - | AB729: #VALUE! | AC729: 13.44 | AD729: #VALUE! | AE729: NO
A730: LIQUIDACIÓN | B730: 102202050 | C730: 102202050-C24 | D730: 102202050FS00 | E730: MARÍA DE LOS ÁNGELES QUIRÓZ | G730: OTROS ABARROTES | H730: PASTAS | I730: CABELLOS DE ANGEL DON VITTORIO 400 G | J730: C24 | K730: UN | L730: Caja 24 Unidades | M730: SECO | N730: IFS | O730: 9344.73 | P730: ELIMINAR LP SEPTIEMBRE 2024 | Q730: 17000 | R730: 1.712195e-05 | S730: DESCONTINUADO | T730: DESCONTINUADO | U730: 9344.89 | V730: 9344.89 | W730: 0 | X730: ELIMINAR LP | Y730: 0 | Z730: INDICAR PRECIO VTA | AA730: - | AB730: #VALUE! | AC730: 9.6 | AD730: #VALUE! | AE730: SI
A731: LIQUIDACIÓN | B731: 104528560 | C731: 104528560-C04 | D731: 104528560FS00 | E731: MARÍA DE LOS ÁNGELES QUIRÓZ | G731: BOLLERIA Y REPOSTERIA | H731: HELADOS | I731: HELADO PIÑA BRESLER 2,4 L | J731: C04 | K731: UN | L731: Caja 4 Unidades | M731: CONGELADOS | N731: NFS | O731: 13776 | P731: ELIMINAR LP SEPTIEMBRE 2024 | Q731: 18500 | R731: 0 | S731: DESCONTINUADO | T731: DESCONTINUADO | U731: 13776 | V731: 13776 | W731: 0 | X731: ELIMINAR LP | Y731: 0 | Z731: INDICAR PRECIO VTA | AA731: - | AB731: #VALUE! | AC731: 5.76 | AD731: #VALUE! | AE731: Si
A732: LIQUIDACIÓN | B732: 150001861 | C732: 150001861-C12 | D732: 150001861FS00 | E732: MARÍA DE LOS ÁNGELES QUIRÓZ | G732: ACEITES Y VINAGRES | H732: ACEITES VEGETALES | I732: ACEITE MARAVILLA BONANZA 900 ML | J732: C12 | K732: UN | L732: Caja 12 Unidades | M732: SECO | N732: NFS | O732: 13810.8 | P732: ELIMINAR LP SEPTIEMBRE 2024 | Q732: 22000 | R732: 0.0001998436 | S732: DESCONTINUADO | T732: DESCONTINUADO | U732: 13813.56 | V732: 13813.56 | W732: 0 | X732: ELIMINAR LP | Y732: 0 | Z732: INDICAR PRECIO VTA | AA732: - | AB732: #VALUE! | AC732: 9.888 | AD732: #VALUE! | AE732: SI
A733: LIQUIDACIÓN | B733: 104532580 | C733: 104532580-C06 | D733: 104532580FS00 | E733: MARÍA DE LOS ÁNGELES QUIRÓZ | G733: LICORES | H733: ESPUMANTE | I733: VINO 750CC R NEGRA G RVA CARMENERE 13.5° | J733: C06 | K733: UN | L733: Caja 6 Unidades | M733: SECO | N733: NFS | O733: 19314 | P733: ELIMINAR LP SEPTIEMBRE 2024 | Q733: 27758 | R733: 0 | S733: DESCONTINUADO | T733: DESCONTINUADO | U733: 19314 | V733: 19314 | W733: 0 | X733: ELIMINAR LP | Y733: 0 | Z733: INDICAR PRECIO VTA | AA733: - | AB733: #VALUE! | AC733: 9.12 | AD733: #VALUE! | AE733: NO
A734: LIQUIDACIÓN | B734: 104532590 | C734: 104532590-C06 | D734: 104532590FS00 | E734: MARÍA DE LOS ÁNGELES QUIRÓZ | G734: LICORES | H734: ESPUMANTE | I734: VINO 750CC R NEGRA G RVA CHARDONNAY 13° | J734: C06 | K734: UN | L734: Caja 6 Unidades | M734: SECO | N734: NFS | O734: 19314 | P734: ELIMINAR LP SEPTIEMBRE 2024 | Q734: 27758 | R734: 0 | S734: VIAS DESCONTINUACION | T734: VIAS DESCONTINUACION | U734: 19314 | V734: 19314 | W734: 0 | X734: ELIMINAR LP | Y734: 0 | Z734: INDICAR PRECIO VTA | AA734: - | AB734: #VALUE! | AC734: 7.98 | AD734: #VALUE! | AE734: NO
A735: LIQUIDACIÓN | B735: 104538220 | C735: 104538220-C76 | D735: 104538220FS00 | E735: MARÍA DE LOS ÁNGELES QUIRÓZ | G735: BOLLERIA Y REPOSTERIA | H735: PANES PRE HORNEADOS | I735: MEDIA BAGUETTE 110 G | J735: C76 | K735: UN | L735: Caja 76 Unidades | M735: CONGELADOS | N735: IFS | O735: 15276 | P735: ELIMINAR LP SEPTIEMBRE 2024 | Q735: 25000 | R735: 0 | S735: VIAS DESCONTINUACION | T735: VIAS DESCONTINUACION | U735: 15276 | V735: 15276 | W735: 0 | X735: ELIMINAR LP | Y735: 0 | Z735: INDICAR PRECIO VTA | AA735: - | AB735: #VALUE! | AC735: 8.36 | AD735: #VALUE! | AE735: NO
A736: LIQUIDACIÓN | B736: 104537960 | C736: 104537960-C22 | D736: 104537960FS00 | E736: MARÍA DE LOS ÁNGELES QUIRÓZ | G736: CONSERVAS | H736: FRUTAS | I736: PAPAYA AL JUGO FRASCO SAN AMBROSIO 1 KG | J736: C22 | K736: UN | L736: Caja 22 Unidades | M736: SECO | N736: NFS | O736: 84700 | P736: ELIMINAR LP SEPTIEMBRE 2024 | Q736: 119167 | R736: 0 | S736: VIAS DESCONTINUACION | T736: VIAS DESCONTINUACION | U736: 84700 | V736: 84700 | W736: 0 | X736: ELIMINAR LP | Y736: 0 | Z736: INDICAR PRECIO VTA | AA736: - | AB736: #VALUE! | AC736: 22 | AD736: #VALUE! | AE736: SI
A737: LIQUIDACIÓN | B737: 104532050 | C737: 104532050-C12 | D737: 104532050FS00 | E737: MARÍA DE LOS ÁNGELES QUIRÓZ | G737: LICORES | H737: WHISKY | I737: WHISKY BLACK EVAN WILLIAMS 43° 750CC | J737: C12 | K737: UN | L737: Caja 12 Unidades | M737: SECO | N737: NFS | O737: 99636 | P737: ELIMINAR LP SEPTIEMBRE 2024 | Q737: 130000 | R737: 0 | S737: DESCONTINUADO | T737: DESCONTINUADO | U737: 99636 | V737: 99636 | W737: 0 | X737: ELIMINAR LP | Y737: 0 | Z737: INDICAR PRECIO VTA | AA737: - | AB737: #VALUE! | AC737: 13.44 | AD737: #VALUE! | AE737: SI
A738: #N/A | B738: 101600020 | C738: #REF! | D738: #REF! | E738: MARLENE SCHWANER | G738: CAFE Y DERIVADOS | H738: CAFES DE GRANO MOLIDO | I738: CAFE CREMA E GUSTO TARRO LAVAZZA 250 G | J738: #N/A | K738: #N/A | L738: #REF! | M738: SECO | N738: IFS | O738: 31005 | P738: ELIMINAR LP SEPTIEMBRE 2024 | Q738: 58850 | R738: #REF! | S738: ACTIVO | T738: #N/A | U738: #REF! | V738: 30974 | W738: #REF! | X738: #N/A | Y738: #N/A | Z738: #N/A | AA738: - | AB738: #REF! | AC738: #N/A | AD738: #REF! | AE738: #REF! | AF738: #N/A
A739: #N/A | B739: 101600050 | C739: #REF! | D739: #REF! | E739: MARLENE SCHWANER | G739: CAFE Y DERIVADOS | H739: CAFES DE GRANO MOLIDO | I739: QUALITA ORO TARRO LAVAZZA 250 G | J739: #N/A | K739: #N/A | L739: #REF! | M739: SECO | N739: IFS | O739: 33709 | P739: ELIMINAR LP SEPTIEMBRE 2024 | Q739: 62060 | R739: #REF! | S739: ACTIVO | T739: #N/A | U739: #REF! | V739: 33739 | W739: #REF! | X739: #N/A | Y739: #N/A | Z739: #N/A | AA739: - | AB739: #REF! | AC739: #N/A | AD739: #REF! | AE739: #REF! | AF739: #N/A
A740: #N/A | B740: 101600070 | C740: #REF! | D740: #REF! | E740: MARLENE SCHWANER | G740: CAFE Y DERIVADOS | H740: CAFES SOLUBLES | I740: CAFE PRONTISSIMO CLASI LATA LAVAZZA 95 G | J740: #N/A | K740: #N/A | L740: #REF! | M740: SECO | N740: IFS | O740: 15953 | P740: ELIMINAR LP SEPTIEMBRE 2024 | Q740: 28890 | R740: #REF! | S740: ACTIVO | T740: #N/A | U740: #REF! | V740: 15997 | W740: #REF! | X740: #N/A | Y740: #N/A | Z740: #N/A | AA740: - | AB740: #REF! | AC740: #N/A | AD740: #REF! | AE740: #REF! | AF740: #N/A
A741: #N/A | B741: 101600001 | C741: #REF! | D741: #REF! | E741: MARLENE SCHWANER | G741: CAFE Y DERIVADOS | H741: CAPSULAS Y PODS | I741: CAPSULA ESPRESSO ARMONICO LAVAZZA 50 G | J741: #N/A | K741: #N/A | L741: #REF! | M741: SECO | N741: IFS | O741: 19916 | P741: ELIMINAR LP SEPTIEMBRE 2024 | Q741: 44940 | R741: #REF! | S741: DESCONTINUADO | T741: #N/A | U741: #REF! | V741: 19916 | W741: #REF! | X741: #N/A | Y741: #N/A | Z741: #N/A | AA741: - | AB741: #REF! | AC741: #N/A | AD741: #REF! | AE741: #REF! | AF741: #N/A
A742: #N/A | B742: 101600041 | C742: #REF! | D742: #REF! | E742: MARLENE SCHWANER | G742: CAFE Y DERIVADOS | H742: CAPSULAS Y PODS | I742: CAPSULA ESPRESSO CLASSICO LAVAZZA 58 G | J742: #N/A | K742: #N/A | L742: #REF! | M742: SECO | N742: IFS | O742: 20922.57 | P742: ELIMINAR LP SEPTIEMBRE 2024 | Q742: 52323 | R742: #REF! | S742: ACTIVO | T742: #N/A | U742: #REF! | V742: 20922.53 | W742: #REF! | X742: #N/A | Y742: #N/A | Z742: #N/A | AA742: - | AB742: #REF! | AC742: #N/A | AD742: #REF! | AE742: #REF! | AF742: #N/A
A743: #N/A | B743: 101600006 | C743: #REF! | D743: #REF! | E743: MARLENE SCHWANER | G743: CAFE Y DERIVADOS | H743: CAPSULAS Y PODS | I743: CAPSULA ESPRESSO DECISO LAVAZZA 50 G | J743: #N/A | K743: #N/A | L743: #REF! | M743: SECO | N743: IFS | O743: 20174 | P743: ELIMINAR LP SEPTIEMBRE 2024 | Q743: 46064 | R743: #REF! | S743: DESCONTINUADO | T743: #N/A | U743: #REF! | V743: 20174 | W743: #REF! | X743: #N/A | Y743: #N/A | Z743: #N/A | AA743: - | AB743: #REF! | AC743: #N/A | AD743: #REF! | AE743: #REF! | AF743: #N/A
A744: #N/A | B744: 101600042 | C744: #REF! | D744: #REF! | E744: MARLENE SCHWANER | G744: CAFE Y DERIVADOS | H744: CAPSULAS Y PODS | I744: CAPSULA ESPRESSO INTENSO LAVAZZA 58 G | J744: #N/A | K744: #N/A | L744: #REF! | M744: SECO | N744: IFS | O744: 21177.63 | P744: ELIMINAR LP SEPTIEMBRE 2024 | Q744: 46064 | R744: #REF! | S744: ACTIVO | T744: #N/A | U744: #REF! | V744: 21177.64 | W744: #REF! | X744: #N/A | Y744: #N/A | Z744: #N/A | AA744: - | AB744: #REF! | AC744: #N/A | AD744: #REF! | AE744: #REF! | AF744: #N/A
A745: #N/A | B745: 101600043 | C745: #REF! | D745: #REF! | E745: MARLENE SCHWANER | G745: CAFE Y DERIVADOS | H745: CAPSULAS Y PODS | I745: CAPSULA ESPRESSO QUALITA ORO LAVAZZA 55G | J745: #N/A | K745: #N/A | L745: #REF! | M745: SECO | N745: IFS | O745: 21400.25 | P745: ELIMINAR LP SEPTIEMBRE 2024 | Q745: 49434 | R745: #REF! | S745: ACTIVO | T745: #N/A | U745: #REF! | V745: 21400.17 | W745: #REF! | X745: #N/A | Y745: #N/A | Z745: #N/A | AA745: - | AB745: #REF! | AC745: #N/A | AD745: #REF! | AE745: #REF! | AF745: #N/A
A746: #N/A | B746: 101600003 | C746: #REF! | D746: #REF! | E746: MARLENE SCHWANER | G746: CAFE Y DERIVADOS | H746: CAPSULAS Y PODS | I746: CAPSULA LUNGO LEGGERO LAVAZZA 55 G | J746: #N/A | K746: #N/A | L746: #REF! | M746: SECO | N746: IFS | O746: 19922 | P746: ELIMINAR LP SEPTIEMBRE 2024 | Q746: 49434 | R746: #REF! | S746: DESCONTINUADO | T746: #N/A | U746: #REF! | V746: 19922 | W746: #REF! | X746: #REF! | Y746: #N/A | Z746: #REF! | AA746: - | AB746: #REF! | AC746: #N/A | AD746: #REF! | AE746: #REF! | AF746: #N/A
A747: ELIMINAR | B747: 150001914 | C747: #REF! | D747: #REF! | E747: MYRIAM GARIN | G747: JAMONES Y CECINAS | H747: EMBUTIDOS Y FIAMBRES | I747: SALCHICHA DE PAVO PF 1 KG 20 UDS. | J747: C06 | K747: UN | L747: #REF! | M747: FRIO | N747: NFS | O747: 14300.39 | P747: LP OCTUBRE | Q747: 20700 | R747: #REF! | S747: DESCONTINUADO | T747: VIAS DESCONTINUACION | U747: #REF! | V747: 14300.09 | W747: #REF! | X747: MANTIENE | Y747: 20700 | Z747: 0 | AA747: 0.3091744 | AB747: #REF! | AC747: 6 | AD747: #REF! | AE747: SI | AF747: 0.06 | AG747: 0.12
A748: ELIMINAR | B748: 104525470 | C748: #REF! | D748: #REF! | E748: MYRIAM GARIN | G748: QUESOS Y MANTEQUILLA | H748: MOZZARELLA | I748: QUESO MOZZARELLA LAMINADO 500 G | J748: 0 | K748: 0 | L748: #REF! | M748: FRIO | N748: NFS | O748: 19632 | P748: LP OCTUBRE | Q748: 25960 | R748: #REF! | S748: DESCONTINUADO | T748: VIAS DESCONTINUACION | U748: #REF! | V748: 19632 | W748: #REF! | Y748: 0 | Z748: INDICAR PRECIO VTA | AA748: - | AB748: #REF! | AD748: #REF! | AE748: 0 | AF748: 0 | AG748: 0
A749: ELIMINAR | B749: 104528010 | C749: #REF! | D749: #REF! | E749: MYRIAM GARIN | G749: PESCADOS Y MARISCOS | H749: PESCADOS | I749: PANGASIUS FILETE S/P 1KG 170-330G IMPORT | J749: 0 | K749: 0 | L749: Metro/Minuto | M749: CONGELADOS | N749: NFS | O749: 21610 | P749: LP OCTUBRE | Q749: 26900 | R749: 0 | S749: VIAS DESCONTINUACION | T749: DESCONTINUADO | U749: 21610 | W749: 0 | AE749: 0 | AF749: 0 | AG749: 0
A750: ELIMINAR | B750: 104523760 | C750: #REF! | D750: #REF! | E750: MYRIAM GARIN | G750: PESCADOS Y MARISCOS | H750: PESCADOS | I750: SALMON PORCION C/P 5 KG 170-200G CONG | J750: 0 | K750: 0 | L750: Metro/Minuto | M750: CONGELADOS | N750: NFS | O750: 41999.65 | P750: LP OCTUBRE | Q750: 65000 | R750: 0 | S750: DESCONTINUADO | T750: DESCONTINUADO | U750: 41999.65 | W750: 0 | AE750: 0 | AF750: 0 | AG750: 0
A751: ELIMINAR | B751: 104537650 | C751: #REF! | D751: #REF! | E751: MYRIAM GARIN | G751: QUESOS Y MANTEQUILLA | H751: QUESOS DUROS | I751: QUESO GOYA LA PAULINA 5,6 KG | J751: 0 | K751: 0 | L751: Metro/Minuto | M751: FRIO | N751: IFS | O751: 5882 | P751: LP OCTUBRE | Q751: 7750 | R751: 0 | S751: DESCONTINUADO | T751: DESCONTINUADO | U751: 5882 | W751: 0 | AE751: 0 | AF751: 0 | AG751: 0
A752: ELIMINAR | B752: 104540410 | C752: #REF! | D752: #REF! | E752: MYRIAM GARIN | G752: QUESOS Y MANTEQUILLA | H752: GOURMET | I752: QUESO MONTERREY JACK USA PREM 2,72 KG | J752: 0 | K752: 0 | L752: Metro/Minuto | M752: FRIO | N752: IFS | O752: 82554 | P752: LP OCTUBRE | Q752: 97866 | R752: 0 | S752: ACTIVO (AS) | T752: DESCONTINUADO | U752: 82554 | W752: 0 | AE752: 0 | AF752: 0 | AG752: 0
A753: ELIMINAR | B753: 104542600 | C753: 104542600FS00 | E753: MYRIAM GARIN | G753: HAMBURGUESAS | H753: HAMBURGUESAS CERTIFICADAS | I753: MOLIDA VACUNO 73/27/20 CAB 4,5 KG | P753: LP NOVIEMBRE 2024
A754: ELIMINAR | B754: 104529590 | C754: 104529590FS00 | E754: MYRIAM GARIN | G754: HAMBURGUESAS | H754: HAMBURGUESAS CERTIFICADAS | I754: MOLIDA VACUNO 80/20 CAB 4,5 KG | P754: LP NOVIEMBRE 2024
A755: ELIMINAR | B755: 104539130 | C755: 104539130FS00 | E755: MYRIAM GARIN | G755: HAMBURGUESAS | H755: HAMBURGUESAS CERTIFICADAS | I755: MOLIDA VACUNO 80/20 CAB 4,5 KG | P755: LP NOVIEMBRE 2024
A756: ELIMINAR | B756: 150002033 | C756: 150002033FS00 | E756: MYRIAM GARIN | G756: JAMONES Y CECINAS | H756: EMBUTIDOS Y FIAMBRES | I756: CHORIZO WINTER 1 KG | P756: LP NOVIEMBRE 2024
A757: ELIMINAR | B757: 150002034 | C757: 150002034FS00 | E757: MYRIAM GARIN | G757: JAMONES Y CECINAS | H757: EMBUTIDOS Y FIAMBRES | I757: LONGANIZA WINTER 1 KG | P757: LP NOVIEMBRE 2024
A758: ELIMINAR | B758: 104543950 | C758: 104543950FS00 | E758: MYRIAM GARIN | G758: JAMONES Y CECINAS | H758: JAMONES CURADOS | I758: JAMON SERRANO 500 GRS (Caja 8) | P758: LP NOVIEMBRE 2024
A759: ELIMINAR | B759: 104339920 | C759: 104339920FS00 | E759: MYRIAM GARIN | G759: PESCADOS Y MARISCOS | H759: MARISCOS Y MOLUSCOS | I759: KANIKAMA 18 CM 500G IMPORTADO | P759: LP NOVIEMBRE 2024
A760: ELIMINAR | B760: 104534670 | C760: 104534670FS00 | E760: MYRIAM GARIN | G760: PESCADOS Y MARISCOS | H760: PESCADOS | I760: REINETA FILETE 100-400G IQF 5 KG | P760: LP NOVIEMBRE 2024
A761: ELIMINAR | B761: 104519360 | C761: 104519360FS00 | E761: MYRIAM GARIN | G761: HAMBURGUESAS | H761: HAMBURGUESAS CERTIFICADAS | I761: HAMBURGUESA CERTIFIED ANGUS BEEF 225 G | P761: LP NOVIEMBRE 2024
A762: ELIMINAR | B762: 104541870 | C762: 104541870FS00 | E762: MYRIAM GARIN | G762: HAMBURGUESAS | H762: HAMBURGUESAS CERTIFICADAS | I762: HAMBURGUESA CERTIFIED ANGUS BEEF 225 GR. | P762: LP NOVIEMBRE 2024
A763: ELIMINAR | B763: 104540120 | C763: 104540120FS00 | E763: MYRIAM GARIN | G763: POLLO | H763: POLLO ENTERO | I763: POLLO ENTERO 2,3 SEARA CJ 16,1 KG | P763: LP NOVIEMBRE 2024
A764: ELIMINAR | B764: 104516650 | C764: 104516650FS00 | E764: MYRIAM GARIN | G764: PESCADOS Y MARISCOS | H764: CAMARONES | I764: CAMARON MARIP APANADO 1,36 KG IMPORTADO | P764: LP NOVIEMBRE 2024
... A801: ELIMINAR | B801: 104532670 | C801: 104532670FS00 | E801: MYRIAM GARIN | G801: JAMONES Y CECINAS | H801: EMBUTIDOS Y FIAMBRES | I801: JAMON DE BELLOTA IBERICO 100% (kg) | P801: LP NOVIEMBRE 2024
A802: LIQUIDACIÓN | B802: 104535480 | C802: =+#REF!&#REF!&#REF! -> #REF! | D802: =+_xlfn.CONCAT(#REF!,#REF!) -> #REF! | E802: MARÍA DE LOS ÁNGELES QUIRÓZ | G802: PLANT BASED | H802: QUESOS VEGANOS | I802: NOT CHEESE CHEDDAR LAMINADO 200 GR | J802: C24 | K802: UN | L802: =VLOOKUP(#REF!,VALIDACIONES!$J$5:$L$489,3,FALSE) -> #REF! | M802: FRIO | N802: NFS | O802: 49584 | P802: LP DICIEMBRE 2024 | Q802: 59000 | R802: 0 | S802: VIAS DESCONTINUACION | T802: DESCONTINUADO | U802: 9200 | V802: 49584 | W802: =+(#REF!-#REF!)/#REF! -> #REF! | X802: ELIMINAR LP | Y802: 0 | Z802: =IF(Y802=0,"INDICAR PRECIO VTA",Y802-Q802) -> INDICAR PRECIO VTA | AA802: =+IFERROR((Y802-V802)/Y802,"-") -> - | AB802: =+#REF!*#REF! -> #REF! | AC802: 4.8 | AD802: =+#REF!/#REF! -> #REF! | AE802: NO | AF802: 0 | AG802: 0
A803: LIQUIDACIÓN | B803: 104535490 | C803: =+#REF!&#REF!&#REF! -> #REF! | D803: =+_xlfn.CONCAT(#REF!,#REF!) -> #REF! | E803: MARÍA DE LOS ÁNGELES QUIRÓZ | G803: PLANT BASED | H803: QUESOS VEGANOS | I803: NOT CHEESE MANTECOSO LAMINADO 200 GR | J803: C24 | K803: UN | L803: =VLOOKUP(#REF!,VALIDACIONES!$J$5:$L$489,3,FALSE) -> #REF! | M803: FRIO | N803: NFS | O803: 49584 | P803: LP DICIEMBRE 2024 | Q803: 59000 | R803: 0 | S803: VIAS DESCONTINUACION | T803: DESCONTINUADO | U803: 2091 | V803: 49584 | W803: =+(#REF!-#REF!)/#REF! -> #REF! | X803: ELIMINAR LP | Y803: 0 | Z803: =IF(Y803=0,"INDICAR PRECIO VTA",Y803-Q803) -> INDICAR PRECIO VTA | AA803: =+IFERROR((Y803-V803)/Y803,"-") -> - | AB803: =+#REF!*#REF! -> #REF! | AC803: 4.8 | AD803: =+#REF!/#REF! -> #REF! | AE803: SI | AF803: 0 | AG803: 0
A804: LIQUIDACIÓN | B804: 209100029 | C804: =+#REF!&#REF!&#REF! -> #REF! | D804: =+_xlfn.CONCAT(#REF!,#REF!) -> #REF! | E804: MARÍA DE LOS ÁNGELES QUIRÓZ | G804: PLANT BASED | H804: HELADOS | I804: NOT ICE CREAM CREMA VAINILLA PALETA 65G | J804: C20 | K804: UN | L804: =VLOOKUP(#REF!,VALIDACIONES!$J$5:$L$489,3,FALSE) -> #REF! | M804: CONGELADOS | N804: NFS | O804: 9895.81 | P804: LP DICIEMBRE 2024 | Q804: 14800 | R804: 0 | S804: DESCONTINUADO | T804: DESCONTINUADO | U804: 2090.6 | V804: 9895.81 | W804: =+(#REF!-#REF!)/#REF! -> #REF! | X804: ELIMINAR LP | Y804: 0 | Z804: =IF(Y804=0,"INDICAR PRECIO VTA",Y804-Q804) -> INDICAR PRECIO VTA | AA804: =+IFERROR((Y804-V804)/Y804,"-") -> - | AB804: =+#REF!*#REF! -> #REF! | AC804: 1.3 | AD804: =+#REF!/#REF! -> #REF! | AE804: NO | AF804: 0 | AG804: 0 | AH804: SI
A805: LIQUIDACIÓN | B805: 201700224 | C805: =+#REF!&#REF!&#REF! -> #REF! | D805: =+_xlfn.CONCAT(#REF!,#REF!) -> #REF! | E805: MARÍA DE LOS ÁNGELES QUIRÓZ | G805: SNACKS Y FRUTOS SECOS | H805: OTROS SNACKS | I805: TERRA VEGGIE STICKS 130G DP | J805: C12 | K805: UN | L805: =VLOOKUP(#REF!,VALIDACIONES!$J$5:$L$489,3,FALSE) -> #REF! | M805: SECO | N805: FIB | O805: 11818 | P805: LP DICIEMBRE 2024 | Q805: 22990 | R805: 0 | S805: VIAS DESCONTINUACION | T805: DESCONTINUADO | U805: 2090.6 | V805: 11818 | W805: =+(#REF!-#REF!)/#REF! -> #REF! | X805: ELIMINAR LP | Y805: 0 | Z805: =IF(Y805=0,"INDICAR PRECIO VTA",Y805-Q805) -> INDICAR PRECIO VTA | AA805: =+IFERROR((Y805-V805)/Y805,"-") -> - | AB805: =+#REF!*#REF! -> #REF! | AC805: 1.56 | AD805: =+#REF!/#REF! -> #REF! | AE805: NO | AF805: 0 | AG805: 0
A806: LIQUIDACIÓN | B806: 104538230 | C806: =+#REF!&#REF!&#REF! -> #REF! | D806: =+_xlfn.CONCAT(#REF!,#REF!) -> #REF! | E806: MARÍA DE LOS ÁNGELES QUIRÓZ | G806: BOLLERIA Y REPOSTERIA | H806: BOLLERÍA LISTA PARA COMER | I806: CHURROS LISTOS 30 X 17G | J806: C05 | K806: UN | L806: =VLOOKUP(#REF!,VALIDACIONES!$J$5:$L$489,3,FALSE) -> #REF! | M806: CONGELADOS | N806: IFS | O806: 18560 | P806: LP DICIEMBRE 2024 | Q806: 30000 | R806: 0 | S806: ACTIVO (AS) | T806: DESCONTINUADO | U806: 2090.6 | V806: 18560 | W806: =+(#REF!-#REF!)/#REF! -> #REF! | X806: ELIMINAR LP | Y806: 0 | Z806: =IF(Y806=0,"INDICAR PRECIO VTA",Y806-Q806) -> INDICAR PRECIO VTA | AA806: =+IFERROR((Y806-V806)/Y806,"-") -> - | AB806: =+#REF!*#REF! -> #REF! | AC806: 2.5 | AD806: =+#REF!/#REF! -> #REF! | AE806: NO | AF806: 0 | AG806: 0
A807: LIQUIDACIÓN | B807: 104537510 | C807: =+#REF!&#REF!&#REF! -> #REF! | D807: =+_xlfn.CONCAT(#REF!,#REF!) -> #REF! | E807: MARÍA DE LOS ÁNGELES QUIRÓZ | G807: BOLLERIA Y REPOSTERIA | H807: PREMEZCLAS | I807: MASA MADRE GENUIT START CSM 1KG | J807: C10 | K807: UN | L807: =VLOOKUP(#REF!,VALIDACIONES!$J$5:$L$489,3,FALSE) -> #REF! | M807: SECO | N807: IFS | O807: 74130 | P807: LP DICIEMBRE 2024 | Q807: 119900 | R807: 0 | S807: VIAS DESCONTINUACION | T807: DESCONTINUADO | U807: 20639.4 | V807: 74130 | W807: =+(#REF!-#REF!)/#REF! -> #REF! | X807: ELIMINAR LP | Y807: 0 | Z807: =IF(Y807=0,"INDICAR PRECIO VTA",Y807-Q807) -> INDICAR PRECIO VTA | AA807: =+IFERROR((Y807-V807)/Y807,"-") -> - | AB807: =+#REF!*#REF! -> #REF! | AC807: 10 | AD807: =+#REF!/#REF! -> #REF! | AE807: SI | AF807: 0 | AG807: 0
